Workbook

Sheet VIGÊNCIA MAIO 2021
A1: GRAND MESSEJANA II - VIGÊNCIA MAIO 2021
A2: NOME | B2: APTO | C2: ALUGUEL | D2: DESCONTO | E2: ALUGUEL C/ DESCONTO | F2: GARAGEM | G2: IPTU | H2: SEG INC. | I2: TOTAL | J2: COMISSÃO | K2: REPASSE | L2: OBSERVAÇÃO | M2: VENC. | N2: CARÊNCIA
B3: 1
B4: 2
B5: 3
B6: 4
B7: 5
B8: 6
B9: 7
B10: 8
B11: 9
A12: JOÃO CARLOS | B12: 10 | C12: 600 | D12: =10%*C12 -> 60 | E12: =C12-D12 -> 540 | F12: 0 | G12: =B52 -> 8.5683215 | H12: 0 | I12: =SUM(E12:H12) -> 548.56832 | J12: =I12*7% -> 38.399783 | K12: =I12-J12 -> 510.16854 | L12: DESCONTO 10% (1/12). IPTU (1/1). SEGURO SERÁ COBRADO A PARTIR DE JUNHO. | M12: 10 | N12: 11
B13: 11
B14: 12
B15: 13
B16: 15
B17: 15
B18: 16
B19: 17
B20: 18
B21: 19
B22: 20
B23: 21
B24: 22
... B26: 24
A27: SHIRLEY | B27: 25 | C27: =704/31*3 -> 68.129032 | D27: =10%*C27 -> 6.8129032 | E27: =C27-D27 -> 61.316129 | F27: =30/31*3 -> 2.9032258 | G27: =D82 -> 8.5683215 | H27: 0 | I27: =SUM(E27:H27) -> 72.787676 | J27: =7%*I27 -> 5.0951373 | K27: =I27-J27 -> 67.692539 | L27: ALUGUEL PROPORCIONAL DE 03 DIAS (29/05 A 31/05). DESCONTO 10% (1/12). IPTU (1/1). SEGURO SERÁ COBRADO A PARTIR DE JUNHO. | M27: 10 | N27: 11
B28: 26
A29: LUIZA | B29: 27 | C29: =650/31*18 -> 377.41935 | D29: =10%*C29 -> 37.741935 | E29: =C29-D29 -> 339.67742 | F29: =60/31*18 -> 34.83871 | G29: =D86 -> 8.5683215 | H29: =D85 -> 19.836667 | I29: =SUM(E29:H29) -> 402.92112 | J29: =7%*I29 -> 28.204478 | K29: =I29-J29 -> 374.71664 | L29: ALUGUEL PROPORCIONAL DE 18 DIAS (14/05 A 31/05). DESCONTO 10% (1/12). IPTU (1/1). SEGURO (1/6). | M29: 10 | N29: 11
A30: TOTAL | C30: =SUM(C3:C29) -> 1045.5484 | D30: =SUM(D3:D29) -> 104.55484 | E30: =SUM(E3:E29) -> 940.99355 | F30: =SUM(F3:F29) -> 37.741935 | G30: =SUM(G3:G29) -> 25.704965 | H30: =SUM(H3:H29) -> 19.836667 | I30: =SUM(I3:I29) -> 1024.2771 | J30: =SUM(J3:J29) -> 71.699398 | K30: =SUM(K3:K29) -> 952.57772
A32: OBSERVAÇÕES | L32: COMISSÃO ADMINISTRAÇÃO
A33: SEGURO 01 | L33: COMISSÃO 7% | N33: =J30 -> 71.699398
A34: IPTU 01
A35: SEGURO 02
A36: IPTU 02 | L36: OUTRAS COMISSÕES E DESPESAS
A37: SEGURO 03 | L37: SEGURO APTO 27 (1/6) | N37: =D85 -> 19.836667
A38: IPTU 03 | L38: 05 LIMPEZAS (01/05 - 08/05 - 15/05 - 22/05 - 29/05) | N38: =100*5 -> 500
A39: SEGURO 04
A40: IPTU 04
A41: SEGURO 05
A42: IPTU 05
A43: SEGURO 06
A44: IPTU 06
A45: SEGURO 07
A46: IPTU 07
A47: SEGURO 08
A48: IPTU 08
A49: SEGURO 09 | L49: TOTAL COMISSÃO + DESPESAS | N49: =SUM(N33:N48) -> 591.53606
A50: IPTU 09
A51: SEGURO 10 | L51: R$ RECEBIDOS EM NOME DO LOCADOR
A52: IPTU 10 | B52: ='GERAL 2021'!J12 -> 8.5683215 | L52: =I30 -> 1024.2771
A53: SEGURO 11
A54: IPTU 11 | L54: TOTAL A REPASSAR | N54: =L52-N49 -> 432.74105
A55: SEGURO 12 | L55: VALOR JÁ REPASSADO | N55: 422.57
A56: IPTU 12 | L56: DIFERENÇA A REPASSAR | N56: =N54-N55 -> 10.17105
A57: SEGURO 13
A58: IPTU 13
A59: SEGURO 14
A60: IPTU 14
A61: SEGURO 15
A62: IPTU 15
A63: SEGURO 16
A64: IPTU 16
A65: SEGURO 17
A66: IPTU 17
A67: SEGURO 18
A68: IPTU 18
... A81: SEGURO 25
A82: IPTU 25 | B82: ='GERAL 2021'!I27 -> 1.0710402 | C82: 8 | D82: =B82*C82 -> 8.5683215
A83: SEGURO 26
A84: IPTU 26
A85: SEGURO 27 | B85: ='GERAL 2021'!K29 -> 119.02 | C85: 6 | D85: =B85/C85 -> 19.836667
A86: IPTU 27 | B86: ='GERAL 2021'!I29 -> 1.0710402 | C86: 8 | D86: =B86*C86 -> 8.5683215

Sheet VIGÊNCIA JUNHO 2021
A1: GRAND MESSEJANA II - VIGÊNCIA JUNHO 2021
A2: INTERMEDIAÇÃO DE MAIO
A3: NOME | B3: APTO | C3: ALUGUEL | D3: DESCONTO | E3: ALUGUEL C/ DESCONTO | F3: GARAGEM | G3: IPTU | H3: SEG INC. | I3: TOTAL | J3: COMISSÃO | K3: REPASSE | L3: OBSERVAÇÃO | M3: VENC. | N3: CARÊNCIA
A4: JOÃO CARLOS | B4: 10 | C4: 600 | D4: =10%*C4 -> 60 | E4: =C4-D4 -> 540 | F4: 0 | G4: 0 | H4: =D58 -> 17.825 | I4: =SUM(E4:H4) -> 557.825 | J4: =(C4+F4)*50% -> 300 | K4: =I4-J4 -> 257.825 | L4: DESCONTO 10% (2/12). SEGURO (1/6). | M4: 10 | N4: 11
A5: SHIRLEY | B5: 25 | C5: =704 -> 704 | D5: =10%*C5 -> 70.4 | E5: =C5-D5 -> 633.6 | F5: =30 -> 30 | G5: 0 | H5: =D88 -> 19.95 | I5: =SUM(E5:H5) -> 683.55 | J5: =(C5+F5)*50% -> 367 | K5: =I5-J5 -> 316.55 | L5: DESCONTO 10% (2/12). SEGURO (1/6). | M5: 10 | N5: 11
A6: LUIZA | B6: 27 | C6: =650 -> 650 | D6: =10%*C6 -> 65 | E6: =C6-D6 -> 585 | F6: =60 -> 60 | G6: 0 | H6: =D92 -> 19.836667 | I6: =SUM(E6:H6) -> 664.83667 | J6: =(C6+F6)*50% -> 355 | K6: =I6-J6 -> 309.83667 | L6: DESCONTO 10% (2/12). SEGURO (2/6). | M6: 10 | N6: 11
A7: TOTAL | C7: =SUM(C4:C6) -> 1954 | D7: =SUM(D4:D6) -> 195.4 | E7: =SUM(E4:E6) -> 1758.6 | F7: =SUM(F4:F6) -> 90 | G7: =SUM(G4:G6) -> 0 | H7: =SUM(H4:H6) -> 57.611667 | I7: =SUM(I4:I6) -> 1906.2117 | J7: =SUM(J4:J6) -> 1022 | K7: =SUM(K4:K6) -> 884.21167
A8: JUNHO DE 2021
A9: NOME | B9: APTO | C9: ALUGUEL | D9: DESCONTO | E9: ALUGUEL C/ DESCONTO | F9: GARAGEM | G9: IPTU | H9: SEG INC. | I9: TOTAL | J9: COMISSÃO | K9: REPASSE | L9: OBSERVAÇÃO | M9: VENC. | N9: CARÊNCIA
B10: 1
B11: 2
B12: 3
B13: 4
B14: 5
B15: 6
B16: 7
B17: 8
B18: 9
A19: JOÃO CARLOS | B19: 10 | L19: INTERMEDIAÇÃO
B20: 11
B21: 12
B22: 13
B23: 15
B24: 15
A25: VANESSA | B25: 16 | C25: ='GERAL 2021'!G18/30*13 -> 277.33333 | D25: =10%*C25 -> 27.733333 | E25: =C25-D25 -> 249.6 | F25: =60/30*13 -> 26 | G25: =D71 -> 7.4972813 | H25: =D70 -> 19.811667 | I25: =SUM(E25:H25) -> 302.90895 | J25: =I25*7% -> 21.203626 | K25: =I25-J25 -> 281.70532 | L25: ALUGUEL PROPORCIONAL DE 13 DIAS (18/06 A 30/06). DESCONTO 10% (1/12). IPTU (1/1). SEGURO (1/6). | M25: 10 | N25: 11
B26: 17
A27: FREDSON | B27: 18 | C27: ='GERAL 2021'!G20/30*24 -> 520 | D27: =10%*C27 -> 52 | E27: =C27-D27 -> 468 | F27: =30/30*24 -> 24 | G27: =D75 -> 7.4972813 | H27: =D74 -> 19.836667 | I27: =SUM(E27:H27) -> 519.33395 | J27: =I27*7% -> 36.353376 | K27: =I27-J27 -> 482.98057 | L27: ALUGUEL PROPORCIONAL DE 24 DIAS (07/06 A 30/06). DESCONTO 10% (1/12). IPTU (1/1). SEGURO (1/6). | M27: 10 | N27: 11
B28: 19
B29: 20
B30: 21
B31: 22
B32: 23
B33: 24
A34: SHIRLEY | B34: 25 | L34: INTERMEDIAÇÃO
B35: 26
A36: LUIZA | B36: 27 | L36: INTERMEDIAÇÃO
A37: TOTAL | C37: =SUM(C10:C36) -> 797.33333 | D37: =SUM(D10:D36) -> 79.733333 | E37: =SUM(E10:E36) -> 717.6 | F37: =SUM(F10:F36) -> 50 | G37: =SUM(G10:G36) -> 14.994563 | H37: =SUM(H10:H36) -> 39.648333 | I37: =SUM(I10:I36) -> 822.2429 | J37: =SUM(J10:J36) -> 57.557003 | K37: =SUM(K10:K36) -> 764.68589
A39: OBSERVAÇÕES | L39: COMISSÃO ADMINISTRAÇÃO
A40: SEGURO 01 | L40: COMISSÃO 7% | N40: =J37 -> 57.557003
A41: IPTU 01 | L41: INTERMEDIAÇÃO | N41: =J7 -> 1022
A42: SEGURO 02
A43: IPTU 02
A44: SEGURO 03 | L44: OUTRAS COMISSÕES E DESPESAS
A45: IPTU 03 | L45: SEGURO APTO 10 (1/6) | N45: 17.8
A46: SEGURO 04 | L46: SEGURO APTO 16 (1/6) | N46: 19.82
A47: IPTU 04 | L47: SEGURO APTO 18 (1/6) | N47: 19.82
A48: SEGURO 05 | L48: SEGURO APTO 25 (1/6) | N48: 19.95
A49: IPTU 05 | L49: SEGURO APTO 27 (2/6) | N49: 19.84
A50: SEGURO 06 | L50: 04 LIMPEZAS (05/06 - 12/06 - 19/06 - 26/06) | N50: =120*4 -> 480
A51: IPTU 06 | L51: RECONHECIMENTO FIRMA CONTRATO APTO 16 E 18 | N51: =7.92*2 -> 15.84
A52: SEGURO 07 | L52: 27 CÓPIAS CHAVE ENTRADA EDIFÍCIO | N52: =5*27 -> 135
A53: IPTU 07
A54: SEGURO 08
A55: IPTU 08
A56: SEGURO 09
A57: IPTU 09 | L57: TOTAL COMISSÃO + DESPESAS | N57: =SUM(N40:N56) -> 1807.627
A58: SEGURO 10 | B58: ='GERAL 2021'!K12 -> 106.95 | C58: 6 | D58: =B58/C58 -> 17.825
A59: IPTU 10 | L59: R$ RECEBIDOS EM NOME DO LOCADOR
A60: SEGURO 11 | L60: =I7+I37 -> 2728.4546
A61: IPTU 11
A62: SEGURO 12 | L62: TOTAL A REPASSAR | N62: =L60-N57 -> 920.82756
A63: IPTU 12
A64: SEGURO 13
A65: IPTU 13
A66: SEGURO 14
A67: IPTU 14
A68: SEGURO 15
A69: IPTU 15
A70: SEGURO 16 | B70: ='GERAL 2021'!K18 -> 118.87 | C70: 6 | D70: =B70/C70 -> 19.811667
A71: IPTU 16 | B71: ='GERAL 2021'!I18 -> 1.0710402 | C71: 7 | D71: =B71*C71 -> 7.4972813
A72: SEGURO 17
A73: IPTU 17
A74: SEGURO 18 | B74: ='GERAL 2021'!K20 -> 119.02 | C74: 6 | D74: =B74/C74 -> 19.836667
A75: IPTU 18 | B75: ='GERAL 2021'!I20 -> 1.0710402 | C75: 7 | D75: =B75*C75 -> 7.4972813
A76: SEGURO 19
A77: IPTU 19
A78: SEGURO 20
A79: IPTU 20
A80: SEGURO 21
A81: IPTU 21
A82: SEGURO 22
A83: IPTU 22
A84: SEGURO 23
A85: IPTU 23
A86: SEGURO 24
A87: IPTU 24
A88: SEGURO 25 | B88: ='GERAL 2021'!K27 -> 119.7 | C88: 6 | D88: =B88/C88 -> 19.95
A89: IPTU 25
A90: SEGURO 26
A91: IPTU 26
A92: SEGURO 27 | B92: ='GERAL 2021'!K29 -> 119.02 | C92: 6 | D92: =B92/C92 -> 19.836667
A93: IPTU 27

Sheet VIGÊNCIA JULHO 2021
A1: GRAND MESSEJANA II
A2: INTERMEDIAÇÃO DE JUNHO
A3: NOME | B3: APTO | C3: ALUGUEL | D3: DESCONTO | E3: ALUGUEL C/ DESCONTO | F3: GARAGEM | G3: IPTU | H3: SEG INC. | I3: TOTAL | J3: COMISSÃO | K3: REPASSE | L3: OBSERVAÇÃO | M3: VENC. | N3: CARÊNCIA
A4: VANESSA | B4: 16 | C4: ='GERAL 2021'!G18 -> 640 | D4: =10%*C4 -> 64 | E4: =C4-D4 -> 576 | F4: =60 -> 60 | G4: 0 | H4: =D69 -> 19.811667 | I4: =SUM(E4:H4) -> 655.81167 | J4: =60%*(C4+F4) -> 420 | K4: =I4-J4 -> 235.81167 | L4: DESCONTO 10% (2/12). SEGURO (2/6). | M4: 10 | N4: 11
A5: FREDSON | B5: 18 | C5: ='GERAL 2021'!G20 -> 650 | D5: =10%*C5 -> 65 | E5: =C5-D5 -> 585 | F5: =30 -> 30 | G5: 0 | H5: 19.9 | I5: =SUM(E5:H5) -> 634.9 | J5: =60%*(C5+F5) -> 408 | K5: =I5-J5 -> 226.9 | L5: DESCONTO 10% (2/12). SEGURO (2/6). | M5: 10 | N5: 11
A6: TOTAL | C6: =SUM(C4:C5) -> 1290 | D6: =SUM(D4:D5) -> 129 | E6: =SUM(E4:E5) -> 1161 | F6: =SUM(F4:F5) -> 90 | G6: =SUM(G4:G5) -> 0 | H6: =SUM(H4:H5) -> 39.711667 | I6: =SUM(I4:I5) -> 1290.7117 | J6: =SUM(J4:J5) -> 828 | K6: =SUM(K4:K5) -> 462.71167
A7: VIGÊNCIA DE JULHO DE 2021
A8: NOME | B8: APTO | C8: ALUGUEL | D8: DESCONTO | E8: ALUGUEL C/ DESCONTO | F8: GARAGEM | G8: IPTU | H8: SEG INC. | I8: TOTAL | J8: COMISSÃO | K8: REPASSE | L8: OBSERVAÇÃO | M8: VENC. | N8: CARÊNCIA
A9: JOÃO PAULO | B9: 1 | C9: =600/31*2 -> 38.709677 | D9: =C9*10% -> 3.8709677 | E9: =C9-D9 -> 34.83871 | F9: =50/31*2 -> 3.2258065 | G9: =D40 -> 6.4262411 | H9: 0 | I9: =SUM(E9:H9) -> 44.490757 | J9: =I9*7% -> 3.114353 | K9: =I9-J9 -> 41.376404 | L9: ALUGUEL E IPTU PROPORCIONAIS A 02 DIAS (30/07 A 31/07). DESCONTO 10% (1/12). IPTU (1/1). SEGURO SERÁ COBRADO A PARTIR DE AGOSTO. | M9: 10 | N9: 11
B10: 2
B11: 3
B12: 4
B13: 5
B14: 6
B15: 7
B16: 8
B17: 9
A18: JOÃO CARLOS | B18: 10 | C18: 600 | D18: =10%*C18 -> 60 | E18: =C18-D18 -> 540 | F18: 0 | G18: 0 | H18: =D57 -> 17.825 | I18: =SUM(E18:H18) -> 557.825 | J18: =I18*7% -> 39.04775 | K18: =I18-J18 -> 518.77725 | L18: DESCONTO 10% (3/12). SEGURO (2/6). | M18: 10 | N18: 11
B19: 11
B20: 12
B21: 13
B22: 15
B23: 15
A24: VANESSA | B24: 16 | C24: 0 | D24: =10%*C24 -> 0 | E24: =C24-D24 -> 0 | F24: 0 | G24: 0 | H24: 0 | I24: =SUM(E24:H24) -> 0 | J24: =I24*7% -> 0 | K24: =I24-J24 -> 0 | L24: INTERMEDIAÇÃO | M24: 10 | N24: 11
A25: MATEUS | B25: 17 | C25: ='GERAL 2021'!G19/31*20 -> 412.90323 | D25: =10%*C25 -> 41.290323 | E25: =(C25-D25) -> 371.6129 | F25: 0 | G25: =D72 -> 6.4262411 | H25: 19.82 | I25: =SUM(E25:H25) -> 397.85914 | J25: =I25*7% -> 27.85014 | K25: =I25-J25 -> 370.009 | L25: ALUGUEL E IPTU PROPORCIONAIS A 20 DIAS (12/07 A 31/07). DESCONTO 10% (1/12). IPTU (1/1). SEGURO (1/6).
A26: FREDSON | B26: 18 | C26: 0 | D26: =10%*C26 -> 0 | E26: =C26-D26 -> 0 | F26: 0 | G26: 0 | H26: 0 | I26: =SUM(E26:H26) -> 0 | J26: =I26*7% -> 0 | K26: =I26-J26 -> 0 | L26: INTERMEDIAÇÃO | M26: 10 | N26: 11
B27: 19
B28: 20
B29: 21
B30: 22
B31: 23
B32: 24
A33: SHIRLEY | B33: 25 | C33: =704 -> 704 | D33: =10%*C33 -> 70.4 | E33: =C33-D33 -> 633.6 | F33: =30 -> 30 | G33: 0 | H33: 19.99 | I33: =SUM(E33:H33) -> 683.59 | J33: =I33*7% -> 47.8513 | K33: =I33-J33 -> 635.7387 | L33: DESCONTO 10% (3/12). SEGURO (2/6). | M33: 10 | N33: 11
B34: 26
A35: LUIZA | B35: 27 | C35: =650 -> 650 | D35: =10%*C35 -> 65 | E35: =C35-D35 -> 585 | F35: =60 -> 60 | G35: 0 | H35: =D91 -> 19.836667 | I35: =SUM(E35:H35) -> 664.83667 | J35: =I35*7% -> 46.538567 | K35: =I35-J35 -> 618.2981 | L35: DESCONTO 10% (3/12). SEGURO (3/6). | M35: 10 | N35: 11
A36: TOTAL | C36: =SUM(C9:C35) -> 2405.6129 | D36: =SUM(D9:D35) -> 240.56129 | E36: =SUM(E9:E35) -> 2165.0516 | F36: =SUM(F9:F35) -> 93.225806 | G36: =SUM(G9:G35) -> 12.852482 | H36: =SUM(H9:H35) -> 77.471667 | I36: =SUM(I9:I35) -> 2348.6016 | J36: =SUM(J9:J35) -> 164.40211 | K36: =SUM(K9:K35) -> 2184.1995
A38: OBSERVAÇÕES | L38: COMISSÃO ADMINISTRAÇÃO
A39: SEGURO 01 | B39: ='GERAL 2021'!K3 -> 118.43 | C39: 6 | D39: =B39/C39 -> 19.738333 | L39: COMISSÃO 7% | N39: =J36 -> 164.40211
A40: IPTU 01 | B40: ='GERAL 2021'!I3 -> 1.0710402 | C40: 6 | D40: =B40*C40 -> 6.4262411 | L40: INTERMEDIAÇÃO | N40: =J6 -> 828
A41: SEGURO 02
A42: IPTU 02
A43: SEGURO 03 | L43: OUTRAS COMISSÕES E DESPESAS
A44: IPTU 03 | L44: SEGURO APTO 10 (2/6) | N44: 17.82
A45: SEGURO 04 | L45: SEGURO APTO 16 (2/6) | N45: 19.81
A46: IPTU 04 | L46: SEGURO APTO 17 (1/6) | N46: 19.82
A47: SEGURO 05 | L47: SEGURO APTO 18 (2/6) | N47: 19.9
A48: IPTU 05 | L48: SEGURO APTO 25 (2/6) | N48: 19.99
A49: SEGURO 06 | L49: SEGURO APTO 27 (3/6) | N49: 19.84
A50: IPTU 06 | L50: 05 LIMPEZAS (03/07/2021 - 10/07/2021 - 17/07/2021 - 24/07/2021 - 31/07/2021) | N50: =120*5 -> 600
A51: SEGURO 07 | L51: RECONHECIMENTO FIRMA CONTRATO APTO 01 E 17 | N51: =7.92*2 -> 15.84
A52: IPTU 07 | L52: ENEL | N52: 555.56
A53: SEGURO 08 | L53: CAGECE | N53: 500.39
A54: IPTU 08
A55: SEGURO 09
A56: IPTU 09
A57: SEGURO 10 | B57: ='GERAL 2021'!K12 -> 106.95 | C57: 6 | D57: =B57/C57 -> 17.825 | L57: TOTAL COMISSÃO + DESPESAS | N57: =SUM(N39:N56) -> 2781.3721
A58: IPTU 10 | B58: ='GERAL 2021'!I12 -> 1.0710402 | C58: 8 | D58: =B58*C58 -> 8.5683215
A59: SEGURO 11 | L59: R$ RECEBIDOS EM NOME DO LOCADOR
A60: IPTU 11 | L60: =I6+I36 -> 3639.3132
A61: SEGURO 12
A62: IPTU 12 | L62: TOTAL A REPASSAR | N62: =L60-N57 -> 857.94113
A63: SEGURO 13
A64: IPTU 13
A65: SEGURO 14
A66: IPTU 14
A67: SEGURO 15
A68: IPTU 15
A69: SEGURO 16 | B69: ='GERAL 2021'!K18 -> 118.87 | C69: 6 | D69: =B69/C69 -> 19.811667
A70: IPTU 16 | B70: ='GERAL 2021'!I18 -> 1.0710402 | C70: 7 | D70: =B70*C70 -> 7.4972813
A71: SEGURO 17 | B71: ='GERAL 2021'!K19 -> 118.87 | C71: 6 | D71: =B71/C71 -> 19.811667
A72: IPTU 17 | B72: ='GERAL 2021'!I19 -> 1.0710402 | C72: 6 | D72: =B72*C72 -> 6.4262411
A73: SEGURO 18 | B73: ='GERAL 2021'!K20 -> 119.02 | C73: 6 | D73: =B73/C73 -> 19.836667
A74: IPTU 18 | B74: ='GERAL 2021'!I20 -> 1.0710402 | C74: 7 | D74: =B74*C74 -> 7.4972813
A75: SEGURO 19
A76: IPTU 19
A77: SEGURO 20
A78: IPTU 20
A79: SEGURO 21
A80: IPTU 21
A81: SEGURO 22
A82: IPTU 22
A83: SEGURO 23
A84: IPTU 23
A85: SEGURO 24
A86: IPTU 24
A87: SEGURO 25 | B87: ='GERAL 2021'!K27 -> 119.7 | C87: 6 | D87: =B87/C87 -> 19.95
A88: IPTU 25 | B88: ='GERAL 2021'!I27 -> 1.0710402 | C88: 6 | D88: =B88*C88 -> 6.4262411
A89: SEGURO 26
A90: IPTU 26
A91: SEGURO 27 | B91: ='GERAL 2021'!K29 -> 119.02 | C91: 6 | D91: =B91/C91 -> 19.836667
A92: IPTU 27 | B92: ='GERAL 2021'!I29 -> 1.0710402 | C92: 8 | D92: =B92*C92 -> 8.5683215

Sheet VIGÊNCIA AGOSTO 2021
A1: GRAND MESSEJANA II
A2: INTERMEDIAÇÃO DE JULHO
A3: NOME | B3: APTO | C3: ALUGUEL | D3: DESCONTO | E3: ALUGUEL C/ DESCONTO | F3: GARAGEM | G3: IPTU | H3: SEG INC. | I3: TOTAL | J3: COMISSÃO | K3: REPASSE | L3: OBSERVAÇÃO | M3: VENC. | N3: CARÊNCIA
A4: JOÃO PAULO | B4: 1 | C4: =600 -> 600 | D4: =C4*10% -> 60 | E4: =C4-D4 -> 540 | F4: =50 -> 50 | G4: 0 | H4: =D38 -> 19.738333 | I4: =SUM(E4:H4) -> 609.73833 | J4: =60%*(C4+F4) -> 390 | K4: =I4-J4 -> 219.73833 | L4: DESCONTO 10% (2/12). SEGURO (1/6) | M4: 10 | N4: 11
A5: MATEUS | B5: 17 | C5: ='GERAL 2021'!G19 -> 640 | D5: =10%*C5 -> 64 | E5: =(C5-D5) -> 576 | F5: 0 | G5: 0 | H5: =D70 -> 19.811667 | I5: =SUM(E5:H5) -> 595.81167 | J5: =60%*(C5+F5) -> 384 | K5: =I5-J5 -> 211.81167 | L5: DESCONTO 10% (2/12). SEGURO (2/6). | M5: 10 | N5: 11
A6: TOTAL | C6: =SUM(C4:C5) -> 1240 | D6: =SUM(D4:D5) -> 124 | E6: =SUM(E4:E5) -> 1116 | F6: =SUM(F4:F5) -> 50 | G6: =SUM(G4:G5) -> 0 | H6: =SUM(H4:H5) -> 39.55 | I6: =SUM(I4:I5) -> 1205.55 | J6: =SUM(J4:J5) -> 774 | K6: =SUM(K4:K5) -> 431.55
A7: VIGÊNCIA DE AGOSTO DE 2021
A8: NOME | B8: APTO | C8: ALUGUEL | D8: DESCONTO | E8: ALUGUEL C/ DESCONTO | F8: GARAGEM | G8: IPTU | H8: SEG INC. | I8: TOTAL | J8: COMISSÃO | K8: REPASSE | L8: OBSERVAÇÃO | M8: VENC. | N8: CARÊNCIA
A9: JOÃO PAULO | B9: 1 | L9: INTERMEDIAÇÃO
B10: 2
B11: 3
B12: 4
B13: 5
B14: 6
B15: 7
B16: 8
B17: 9
A18: JOÃO CARLOS | B18: 10 | C18: 600 | D18: =10%*C18 -> 60 | E18: =C18-D18 -> 540 | F18: 0 | G18: 0 | H18: =D56 -> 17.825 | I18: =SUM(E18:H18) -> 557.825 | J18: =I18*7% -> 39.04775 | K18: =I18-J18 -> 518.77725 | L18: DESCONTO 10% (4/12). SEGURO (3/6). | M18: 10 | N18: 11
B19: 11
B20: 12
B21: 13
A22: CATIANA | B22: 15 | C22: 730 | D22: 60 | E22: =(C22-D22)/31*26 -> 561.93548 | F22: =50/31*26 -> 41.935484 | G22: =D67 -> 5.3552009 | H22: =D66 -> 19.99 | I22: =SUM(E22:H22) -> 629.21617 | J22: =7%*I22 -> 44.045132 | K22: =I22-J22 -> 585.17104 | L22: ALUGUEL, GARAGEM E IPTU PROPORCIONAIS A 26 DIAS (06/08 A 31/08). DESCONTO R$ 60,00 (1/12). IPTU (1/1). SEGURO (1/6) | M22: 10 | N22: 11
A23: VANESSA | B23: 16 | C23: ='GERAL 2021'!G18 -> 640 | D23: =10%*C23 -> 64 | E23: =C23-D23 -> 576 | F23: =60 -> 60 | G23: 0 | H23: =D68 -> 19.811667 | I23: =SUM(E23:H23) -> 655.81167 | J23: =7%*I23 -> 45.906817 | K23: =I23-J23 -> 609.90485 | L23: DESCONTO 10% (3/12). SEGURO (3/6). | M23: 10 | N23: 11
A24: MATEUS | B24: 17 | L24: INTERMEDIAÇÃO
A25: FREDSON | B25: 18 | C25: ='GERAL 2021'!G20 -> 650 | D25: =10%*C25 -> 65 | E25: =C25-D25 -> 585 | F25: =30 -> 30 | G25: 0 | H25: =D72 -> 19.836667 | I25: =SUM(E25:H25) -> 634.83667 | J25: =7%*I25 -> 44.438567 | K25: =I25-J25 -> 590.3981 | L25: DESCONTO 10% (3/12). SEGURO (3/6). | M25: 10 | N25: 11
A26: ERIVANDO | B26: 19 | C26: 600 | D26: =10%*C26 -> 60 | E26: =(C26-D26)/31*8 -> 139.35484 | F26: =50/31*8 -> 12.903226 | G26: =D75 -> 5.3552009 | H26: =D74 -> 19.738333 | I26: =SUM(E26:H26) -> 177.3516 | J26: =7%*I26 -> 12.414612 | K26: =I26-J26 -> 164.93699 | L26: ALUGUEL, GARAGEM E IPTU PROPORCIONAIS A 08 DIAS (24/08/2021 A 31/08/2021). DESCONTO 10% (1/12). IPTU (1/1). SEGURO (1/6) | M26: 10 | N26: 11
B27: 20
B28: 21
B29: 22
B30: 23
B31: 24
A32: SHIRLEY | B32: 25 | C32: =704 -> 704 | D32: =10%*C32 -> 70.4 | E32: =C32-D32 -> 633.6 | F32: =30 -> 30 | G32: 0 | H32: 19.99 | I32: =SUM(E32:H32) -> 683.59 | J32: =I32*7% -> 47.8513 | K32: =I32-J32 -> 635.7387 | L32: DESCONTO 10% (4/12). SEGURO (3/6). | M32: 10 | N32: 11
B33: 26
A34: LUIZA | B34: 27 | C34: =650 -> 650 | D34: =10%*C34 -> 65 | E34: =C34-D34 -> 585 | F34: =60 -> 60 | G34: 0 | H34: =D90 -> 19.836667 | I34: =SUM(E34:H34) -> 664.83667 | J34: =I34*7% -> 46.538567 | K34: =I34-J34 -> 618.2981 | L34: DESCONTO 10% (4/12). SEGURO (4/6). | M34: 10 | N34: 11
A35: TOTAL | C35: =SUM(C9:C34) -> 4574 | D35: =SUM(D9:D34) -> 444.4 | E35: =SUM(E9:E34) -> 3620.8903 | F35: =SUM(F9:F34) -> 234.83871 | G35: =SUM(G9:G34) -> 10.710402 | H35: =SUM(H9:H34) -> 137.02833 | I35: =SUM(I9:I34) -> 4003.4678 | J35: =SUM(J9:J34) -> 280.24274 | K35: =SUM(K9:K34) -> 3723.225
A37: OBSERVAÇÕES | L37: COMISSÃO ADMINISTRAÇÃO
A38: SEGURO 01 | B38: ='GERAL 2021'!K3 -> 118.43 | C38: 6 | D38: =B38/C38 -> 19.738333 | L38: COMISSÃO 7% | N38: =J35 -> 280.24274
A39: IPTU 01 | B39: ='GERAL 2021'!I3 -> 1.0710402 | C39: 6 | D39: =B39*C39 -> 6.4262411 | L39: INTERMEDIAÇÃO | N39: =J6 -> 774
A40: SEGURO 02
A41: IPTU 02
A42: SEGURO 03 | L42: OUTRAS COMISSÕES E DESPESAS
A43: IPTU 03 | L43: SEGURO APTO 01 (1/6) | N43: =19.73 -> 19.73
A44: SEGURO 04 | L44: SEGURO APTO 10 (3/6) | N44: 17.82
A45: IPTU 04 | L45: SEGURO APTO 15 (1/6) | N45: 19.99
A46: SEGURO 05 | L46: SEGURO APTO 16 (3/6) | N46: 19.81
A47: IPTU 05 | L47: SEGURO APTO 17 (2/6) | N47: 19.81
A48: SEGURO 06 | L48: SEGURO APTO 18 (3/6) | N48: 19.84
A49: IPTU 06 | L49: SEGURO APTO 19 (1/6) | N49: 19.73
A50: SEGURO 07 | L50: SEGURO APTO 25 (3/6) | N50: 19.93
A51: IPTU 07 | L51: SEGURO APTO 27 (4/6) | N51: 19.84
A52: SEGURO 08 | L52: 04 LIMPEZAS (07/08 - 14/08 - 21/08 - 28/08) | N52: =4*120 -> 480
A53: IPTU 08 | L53: RECONHECIMENTO FIRMA CONTRATO APTO 15 E 19 | N53: =7.92*2 -> 15.84
A54: SEGURO 09 | L54: ENEL | N54: 136.8
A55: IPTU 09 | L55: CAGECE | N55: 199.48
A56: SEGURO 10 | B56: ='GERAL 2021'!K12 -> 106.95 | C56: 6 | D56: =B56/C56 -> 17.825
A57: IPTU 10 | B57: ='GERAL 2021'!I12 -> 1.0710402 | C57: 8 | D57: =B57*C57 -> 8.5683215
A58: SEGURO 11 | L58: TOTAL COMISSÃO + DESPESAS | N58: =SUM(N38:N57) -> 2062.8627
A59: IPTU 11
A60: SEGURO 12 | L60: R$ RECEBIDOS EM NOME DO LOCADOR
A61: IPTU 12 | L61: =I6+I35 -> 5209.0178
A62: SEGURO 13
A63: IPTU 13 | L63: TOTAL A REPASSAR | N63: =L61-N58 -> 3146.155
A64: SEGURO 14
A65: IPTU 14
A66: SEGURO 15 | B66: ='GERAL 2021'!K17 -> 119.94 | C66: 6 | D66: =B66/C66 -> 19.99
A67: IPTU 15 | B67: ='GERAL 2021'!I17 -> 1.0710402 | C67: 5 | D67: =B67*C67 -> 5.3552009
A68: SEGURO 16 | B68: ='GERAL 2021'!K18 -> 118.87 | C68: 6 | D68: =B68/C68 -> 19.811667
A69: IPTU 16 | B69: ='GERAL 2021'!I18 -> 1.0710402 | C69: 7 | D69: =B69*C69 -> 7.4972813
A70: SEGURO 17 | B70: ='GERAL 2021'!K19 -> 118.87 | C70: 6 | D70: =B70/C70 -> 19.811667
A71: IPTU 17 | B71: ='GERAL 2021'!I19 -> 1.0710402 | C71: 6 | D71: =B71*C71 -> 6.4262411
A72: SEGURO 18 | B72: ='GERAL 2021'!K20 -> 119.02 | C72: 6 | D72: =B72/C72 -> 19.836667
A73: IPTU 18 | B73: ='GERAL 2021'!I20 -> 1.0710402 | C73: 7 | D73: =B73*C73 -> 7.4972813
A74: SEGURO 19 | B74: ='GERAL 2021'!K21 -> 118.43 | C74: 6 | D74: =B74/C74 -> 19.738333
A75: IPTU 19 | B75: ='GERAL 2021'!I21 -> 1.0710402 | C75: 5 | D75: =B75*C75 -> 5.3552009
A76: SEGURO 20
A77: IPTU 20
A78: SEGURO 21
A79: IPTU 21
A80: SEGURO 22
A81: IPTU 22
A82: SEGURO 23
A83: IPTU 23
A84: SEGURO 24
A85: IPTU 24
A86: SEGURO 25 | B86: ='GERAL 2021'!K27 -> 119.7 | C86: 6 | D86: =B86/C86 -> 19.95
A87: IPTU 25 | B87: ='GERAL 2021'!I27 -> 1.0710402 | C87: 6 | D87: =B87*C87 -> 6.4262411
A88: SEGURO 26
A89: IPTU 26
A90: SEGURO 27 | B90: ='GERAL 2021'!K29 -> 119.02 | C90: 6 | D90: =B90/C90 -> 19.836667
A91: IPTU 27 | B91: ='GERAL 2021'!I29 -> 1.0710402 | C91: 8 | D91: =B91*C91 -> 8.5683215

Sheet VIGÊNCIA SETEMBRO 2021
A1: GRAND MESSEJANA II
A2: INTERMEDIAÇÃO DE AGOSTO
A3: NOME | B3: APTO | C3: ALUGUEL | D3: DESCONTO | E3: ALUGUEL C/ DESCONTO | F3: GARAGEM | G3: IPTU | H3: SEG INC. | I3: TOTAL | J3: COMISSÃO | K3: REPASSE | L3: OBSERVAÇÃO | M3: VENC. | N3: CARÊNCIA
A4: CATIANA | B4: 15 | C4: 730 | D4: 60 | E4: =(C4-D4) -> 670 | F4: =50 -> 50 | G4: 0 | H4: =D71 -> 19.99 | I4: =SUM(E4:H4) -> 739.99 | J4: =60%*(C4+F4) -> 468 | K4: =I4-J4 -> 271.99 | L4: DESCONTO R$ 60,00 (2/12). SEGURO (2/6). | M4: 10 | N4: 11
A5: ERIVANDO | B5: 19 | C5: 600 | D5: =10%*C5 -> 60 | E5: =(C5-D5) -> 540 | F5: =50 -> 50 | G5: 0 | H5: =D79 -> 19.738333 | I5: =SUM(E5:H5) -> 609.73833 | J5: =60%*(C5+F5) -> 390 | K5: =I5-J5 -> 219.73833 | L5: DESCONTO 10% (2/12). SEGURO (2/6). | M5: 10 | N5: 11
A6: TOTAL | C6: =SUM(C4:C5) -> 1330 | D6: =SUM(D4:D5) -> 120 | E6: =SUM(E4:E5) -> 1210 | F6: =SUM(F4:F5) -> 100 | G6: =SUM(G4:G5) -> 0 | H6: =SUM(H4:H5) -> 39.728333 | I6: =SUM(I4:I5) -> 1349.7283 | J6: =SUM(J4:J5) -> 858 | K6: =SUM(K4:K5) -> 491.72833
A7: VIGÊNCIA DE SETEMBRO DE 2021
A8: NOME | B8: APTO | C8: ALUGUEL | D8: DESCONTO | E8: ALUGUEL C/ DESCONTO | F8: GARAGEM | G8: IPTU | H8: SEG INC. | I8: TOTAL | J8: COMISSÃO | K8: REPASSE | L8: OBSERVAÇÃO | M8: VENC. | N8: CARÊNCIA
A9: JOÃO PAULO | B9: 1 | C9: 0 | D9: =C9*10% -> 0 | E9: =C9-D9 -> 0 | F9: 0 | G9: 0 | H9: 0 | I9: =SUM(E9:H9) -> 0 | J9: =7%*I9 -> 0 | K9: =I9-J9 -> 0 | L9: INADIMPLÊNCIA | M9: 10 | N9: 11
B10: 2 | J10: =7%*I10 -> 0
B11: 3 | J11: =7%*I11 -> 0
B12: 4 | J12: =7%*I12 -> 0
B13: 5 | J13: =7%*I13 -> 0
B14: 6 | J14: =7%*I14 -> 0
B15: 7 | J15: =7%*I15 -> 0
B16: 8 | J16: =7%*I16 -> 0
B17: 9 | J17: =7%*I17 -> 0
A18: JOÃO CARLOS | B18: 10 | C18: 600 | D18: =10%*C18 -> 60 | E18: =C18-D18 -> 540 | F18: 0 | G18: 0 | H18: =D61 -> 17.825 | I18: =SUM(E18:H18) -> 557.825 | J18: =7%*I18 -> 39.04775 | K18: =I18-J18 -> 518.77725 | L18: DESCONTO 10% (5/12). SEGURO (4/6). | M18: 10 | N18: 11
B19: 11 | J19: =7%*I19 -> 0
B20: 12 | J20: =7%*I20 -> 0
B21: 13 | J21: =7%*I21 -> 0
B22: 14 | J22: =7%*I22 -> 0
A23: CATIANA | B23: 15 | J23: =7%*I23 -> 0 | L23: INTERMEDIAÇÃO
A24: VANESSA | B24: 16 | C24: ='GERAL 2021'!G18 -> 640 | D24: =10%*C24 -> 64 | E24: =C24-D24 -> 576 | F24: =60 -> 60 | G24: 0 | H24: =D73 -> 19.811667 | I24: =SUM(E24:H24) -> 655.81167 | J24: =7%*I24 -> 45.906817 | K24: =I24-J24 -> 609.90485 | L24: DESCONTO 10% (4/12). SEGURO (4/6). | M24: 10 | N24: 11
A25: MATEUS | B25: 17 | C25: ='GERAL 2021'!G19 -> 640 | D25: =10%*C25 -> 64 | E25: =(C25-D25) -> 576 | F25: 0 | G25: 0 | H25: =D75 -> 19.811667 | I25: =SUM(E25:H25) -> 595.81167 | J25: =7%*I25 -> 41.706817 | K25: =I25-J25 -> 554.10485 | L25: DESCONTO 10% (3/12). SEGURO (3/6). | M25: 10 | N25: 11
A26: FREDSON | B26: 18 | C26: ='GERAL 2021'!G20 -> 650 | D26: =10%*C26 -> 65 | E26: =C26-D26 -> 585 | F26: =30 -> 30 | G26: 0 | H26: =D77 -> 19.836667 | I26: =SUM(E26:H26) -> 634.83667 | J26: =7%*I26 -> 44.438567 | K26: =I26-J26 -> 590.3981 | L26: DESCONTO 10% (4/12). SEGURO (4/6). | M26: 10 | N26: 11
A27: ERIVANDO | B27: 19 | J27: =7%*I27 -> 0 | L27: INTERMEDIAÇÃO
B28: 20 | J28: =7%*I28 -> 0
B29: 21 | J29: =7%*I29 -> 0
B30: 22 | J30: =7%*I30 -> 0
B31: 23 | J31: =7%*I31 -> 0
B32: 24 | J32: =7%*I32 -> 0
A33: SHIRLEY | B33: 25 | C33: =704 -> 704 | D33: =10%*C33 -> 70.4 | E33: =C33-D33 -> 633.6 | F33: =30 -> 30 | G33: 0 | H33: 19.99 | I33: =SUM(E33:H33) -> 683.59 | J33: =7%*I33 -> 47.8513 | K33: =I33-J33 -> 635.7387 | L33: DESCONTO 10% (5/12). SEGURO (4/6). | M33: 10 | N33: 11
B34: 26 | J34: =7%*I34 -> 0
A35: LUIZA | B35: 27 | C35: =650 -> 650 | D35: =10%*C35 -> 65 | E35: =C35-D35 -> 585 | F35: =60 -> 60 | G35: 0 | H35: =D95 -> 19.836667 | I35: =SUM(E35:H35) -> 664.83667 | J35: =7%*I35 -> 46.538567 | K35: =I35-J35 -> 618.2981 | L35: DESCONTO 10% (5/12). SEGURO (5/6). | M35: 10 | N35: 11
A36: TOTAL | C36: =SUM(C9:C35) -> 3884 | D36: =SUM(D9:D35) -> 388.4 | E36: =SUM(E9:E35) -> 3495.6 | F36: =SUM(F9:F35) -> 180 | G36: =SUM(G9:G35) -> 0 | H36: =SUM(H9:H35) -> 117.11167 | I36: =SUM(I9:I35) -> 3792.7117 | J36: =SUM(J9:J35) -> 265.48982 | K36: =SUM(K9:K35) -> 3527.2218
A37: INADIMPLÊNCIAS
A38: NOME | B38: APTO | C38: PRINCIPAL | D38: CONDIÇÃO | I38: R$ PARCELA | L38: OBSERVAÇÃO | M38: VENC. | N38: CARÊNCIA
A39: JOÃO PAULO | B39: 1 | C39: =600+50+19.74 -> 669.74 | D39: R$ 600,00 (ALUGUEL SETEMBRO) + R$ 50,00 (GARAGEM) + R$ 19,74 (SEGURO 2/6). | I39: =600+50+19.74 -> 669.74 | L39: ALUGUEL DE SETEMBRO. PERDA DO DESCONTO (3/12). SEGURO (2/6). | M39: 10 | N39: 11
A40: TOTAL | I40: =SUM(I39) -> 669.74
A42: OBSERVAÇÕES | L42: COMISSÃO ADMINISTRAÇÃO
A43: SEGURO 01 | B43: ='GERAL 2021'!K3 -> 118.43 | C43: 6 | D43: =B43/C43 -> 19.738333 | L43: COMISSÃO 7% | N43: =J36 -> 265.48982
A44: IPTU 01 | B44: ='GERAL 2021'!I3 -> 1.0710402 | C44: 6 | D44: =B44*C44 -> 6.4262411 | L44: INTERMEDIAÇÃO | N44: =J6 -> 858
A45: SEGURO 02
A46: IPTU 02
A47: SEGURO 03 | L47: OUTRAS COMISSÕES E DESPESAS
A48: IPTU 03 | L48: SEGURO APTO 01 (2/6) | N48: 19.74
A49: SEGURO 04 | L49: SEGURO APTO 10 (4/6) | N49: 17.82
A50: IPTU 04 | L50: SEGURO APTO 15 (2/6) | N50: 19.99
A51: SEGURO 05 | L51: SEGURO APTO 16 (4/6) | N51: 19.81
A52: IPTU 05 | L52: SEGURO APTO 17 (3/6) | N52: 19.81
A53: SEGURO 06 | L53: SEGURO APTO 18 (4/6) | N53: 19.84
A54: IPTU 06 | L54: SEGURO APTO 19 (2/6) | N54: 19.74
A55: SEGURO 07 | L55: SEGURO APTO 25 (4/6) | N55: 19.93
A56: IPTU 07 | L56: SEGURO APTO 27 (5/6) | N56: 19.84
A57: SEGURO 08 | L57: 04 LIMPEZAS (04/09 - 11/09 - 18/09 - 25/09) | N57: =4*120 -> 480
A58: IPTU 08 | L58: CAGECE | N58: 151.43
A59: SEGURO 09
A60: IPTU 09
A61: SEGURO 10 | B61: ='GERAL 2021'!K12 -> 106.95 | C61: 6 | D61: =B61/C61 -> 17.825
A62: IPTU 10 | B62: ='GERAL 2021'!I12 -> 1.0710402 | C62: 8 | D62: =B62*C62 -> 8.5683215
A63: SEGURO 11 | L63: TOTAL COMISSÃO + DESPESAS | N63: =SUM(N43:N62) -> 1931.4398
A64: IPTU 11
A65: SEGURO 12 | L65: R$ RECEBIDOS EM NOME DO LOCADOR
A66: IPTU 12 | L66: =I6+I36 -> 5142.44
A67: SEGURO 13
A68: IPTU 13 | L68: TOTAL A REPASSAR | N68: =L66-N63 -> 3211.0002
A69: SEGURO 14
A70: IPTU 14
A71: SEGURO 15 | B71: ='GERAL 2021'!K17 -> 119.94 | C71: 6 | D71: =B71/C71 -> 19.99
A72: IPTU 15 | B72: ='GERAL 2021'!I17 -> 1.0710402 | C72: 5 | D72: =B72*C72 -> 5.3552009
A73: SEGURO 16 | B73: ='GERAL 2021'!K18 -> 118.87 | C73: 6 | D73: =B73/C73 -> 19.811667
A74: IPTU 16 | B74: ='GERAL 2021'!I18 -> 1.0710402 | C74: 7 | D74: =B74*C74 -> 7.4972813
A75: SEGURO 17 | B75: ='GERAL 2021'!K19 -> 118.87 | C75: 6 | D75: =B75/C75 -> 19.811667
A76: IPTU 17 | B76: ='GERAL 2021'!I19 -> 1.0710402 | C76: 6 | D76: =B76*C76 -> 6.4262411
A77: SEGURO 18 | B77: ='GERAL 2021'!K20 -> 119.02 | C77: 6 | D77: =B77/C77 -> 19.836667
A78: IPTU 18 | B78: ='GERAL 2021'!I20 -> 1.0710402 | C78: 7 | D78: =B78*C78 -> 7.4972813
A79: SEGURO 19 | B79: ='GERAL 2021'!K21 -> 118.43 | C79: 6 | D79: =B79/C79 -> 19.738333
A80: IPTU 19 | B80: ='GERAL 2021'!I21 -> 1.0710402 | C80: 5 | D80: =B80*C80 -> 5.3552009
A81: SEGURO 20
A82: IPTU 20
A83: SEGURO 21
A84: IPTU 21
A85: SEGURO 22
A86: IPTU 22
A87: SEGURO 23
A88: IPTU 23
A89: SEGURO 24
A90: IPTU 24
A91: SEGURO 25 | B91: ='GERAL 2021'!K27 -> 119.7 | C91: 6 | D91: =B91/C91 -> 19.95
A92: IPTU 25 | B92: ='GERAL 2021'!I27 -> 1.0710402 | C92: 6 | D92: =B92*C92 -> 6.4262411
A93: SEGURO 26
A94: IPTU 26
A95: SEGURO 27 | B95: ='GERAL 2021'!K29 -> 119.02 | C95: 6 | D95: =B95/C95 -> 19.836667
A96: IPTU 27 | B96: ='GERAL 2021'!I29 -> 1.0710402 | C96: 8 | D96: =B96*C96 -> 8.5683215

Sheet VIGÊNCIA OUTUBRO 2021
A1: GRAND MESSEJANA II
A2: VIGÊNCIA DE OUTUBRO DE 2021
A3: NOME | B3: APTO | C3: ALUGUEL | D3: DESCONTO | E3: ALUGUEL C/ DESCONTO | F3: GARAGEM | G3: IPTU | H3: SEG INC. | I3: TOTAL | J3: COMISSÃO | K3: REPASSE | L3: OBSERVAÇÃO | M3: VENC. | N3: CARÊNCIA
A4: JOÃO PAULO | B4: 1 | C4: 0 | D4: =C4*10% -> 0 | E4: =C4-D4 -> 0 | F4: 0 | G4: 0 | H4: 0 | I4: =SUM(E4:H4) -> 0 | J4: =7%*I4 -> 0 | K4: =I4-J4 -> 0 | L4: INADIMPLÊNCIA | M4: 10 | N4: 11
B5: 2 | J5: =7%*I5 -> 0
B6: 3 | J6: =7%*I6 -> 0
B7: 4 | J7: =7%*I7 -> 0
B8: 5 | J8: =7%*I8 -> 0
B9: 6 | J9: =7%*I9 -> 0
B10: 7 | J10: =7%*I10 -> 0
B11: 8 | J11: =7%*I11 -> 0
B12: 9 | J12: =7%*I12 -> 0
A13: JOÃO CARLOS | B13: 10 | C13: 600 | D13: =10%*C13 -> 60 | E13: =C13-D13 -> 540 | F13: 0 | G13: 0 | H13: =D60 -> 17.825 | I13: =SUM(E13:H13) -> 557.825 | J13: =7%*I13 -> 39.04775 | K13: =I13-J13 -> 518.77725 | L13: DESCONTO 10% (6/12). SEGURO (5/6). | M13: 10 | N13: 11
B14: 11 | J14: =7%*I14 -> 0
B15: 12 | J15: =7%*I15 -> 0
B16: 13 | J16: =7%*I16 -> 0
B17: 14 | J17: =7%*I17 -> 0
A18: CATIANA | B18: 15 | C18: 730 | D18: 60 | E18: =(C18-D18) -> 670 | F18: =50 -> 50 | G18: 0 | H18: =D70 -> 19.99 | I18: =SUM(E18:H18) -> 739.99 | J18: =7%*I18 -> 51.7993 | K18: =I18-J18 -> 688.1907 | L18: DESCONTO R$ 60,00 (3/12). SEGURO (3/6). | M18: 10 | N18: 11
A19: VANESSA | B19: 16 | C19: ='GERAL 2021'!G18 -> 640 | D19: =10%*C19 -> 64 | E19: =C19-D19 -> 576 | F19: =60 -> 60 | G19: 0 | H19: =D72 -> 19.811667 | I19: =SUM(E19:H19) -> 655.81167 | J19: =7%*I19 -> 45.906817 | K19: =I19-J19 -> 609.90485 | L19: DESCONTO 10% (5/12). SEGURO (5/6). | M19: 10 | N19: 11
A20: MATEUS | B20: 17 | C20: ='GERAL 2021'!G19 -> 640 | D20: =10%*C20 -> 64 | E20: =(C20-D20) -> 576 | F20: 0 | G20: 0 | H20: =D74 -> 19.811667 | I20: =SUM(E20:H20) -> 595.81167 | J20: =7%*I20 -> 41.706817 | K20: =I20-J20 -> 554.10485 | L20: DESCONTO 10% (4/12). SEGURO (4/6). | M20: 10 | N20: 11
A21: FREDSON | B21: 18 | C21: ='GERAL 2021'!G20 -> 650 | D21: =10%*C21 -> 65 | E21: =C21-D21 -> 585 | F21: =30 -> 30 | G21: 0 | H21: =D76 -> 19.836667 | I21: =SUM(E21:H21) -> 634.83667 | J21: =7%*I21 -> 44.438567 | K21: =I21-J21 -> 590.3981 | L21: DESCONTO 10% (5/12). SEGURO (5/6). | M21: 10 | N21: 11
A22: ERIVANDO | B22: 19 | C22: 600 | D22: =10%*C22 -> 60 | E22: =(C22-D22) -> 540 | F22: =50 -> 50 | G22: 0 | H22: =D78 -> 19.738333 | I22: =SUM(E22:H22) -> 609.73833 | J22: =7%*I22 -> 42.681683 | K22: =I22-J22 -> 567.05665 | L22: DESCONTO 10% (3/12). SEGURO (3/6). | M22: 10 | N22: 11
B23: 20 | J23: =7%*I23 -> 0
B24: 21 | J24: =7%*I24 -> 0
B25: 22 | J25: =7%*I25 -> 0
B26: 23 | J26: =7%*I26 -> 0
B27: 24 | J27: =7%*I27 -> 0
A28: SHIRLEY | B28: 25 | C28: =704 -> 704 | D28: =10%*C28 -> 70.4 | E28: =C28-D28 -> 633.6 | F28: =30 -> 30 | G28: 0 | H28: 19.99 | I28: =SUM(E28:H28) -> 683.59 | J28: =7%*I28 -> 47.8513 | K28: =I28-J28 -> 635.7387 | L28: DESCONTO 10% (6/12). SEGURO (5/6). | M28: 10 | N28: 11
B29: 26 | J29: =7%*I29 -> 0
A30: LUIZA | B30: 27 | C30: =650 -> 650 | D30: =10%*C30 -> 65 | E30: =C30-D30 -> 585 | F30: =60 -> 60 | G30: 0 | H30: =D94 -> 19.836667 | I30: =SUM(E30:H30) -> 664.83667 | J30: =7%*I30 -> 46.538567 | K30: =I30-J30 -> 618.2981 | L30: DESCONTO 10% (6/12). SEGURO (6/6). | M30: 10 | N30: 11
A31: TOTAL | C31: =SUM(C4:C30) -> 5214 | D31: =SUM(D4:D30) -> 508.4 | E31: =SUM(E4:E30) -> 4705.6 | F31: =SUM(F4:F30) -> 280 | G31: =SUM(G4:G30) -> 0 | H31: =SUM(H4:H30) -> 156.84 | I31: =SUM(I4:I30) -> 5142.44 | J31: =SUM(J4:J30) -> 359.9708 | K31: =SUM(K4:K30) -> 4782.4692
A32: ALUGUÉIS ATRASADOS/ACORDOS/RESCISÕES RECEBIDAS EM OUTUBRO 2021
A33: NOME | B33: APTO | C33: ALUGUEL | D33: GARAGEM | E33: IPTU | F33: SEGURO | G33: MULTA | H33: JUROS | I33: TOTAL | J33: COMISSÃO | K33: REPASSE | L33: OBSERVAÇÃO | M33: VENC. | N33: CARÊNCIA
A34: JOÃO PAULO | B34: 1 | C34: 600 | D34: 50 | E34: 0 | F34: 19.74 | G34: =10%*(C34+D34+F34) -> 66.974 | H34: 4.46 | I34: =SUM(C34:H34) -> 741.174 | J34: =7%*I34 -> 51.88218 | K34: =I34-J34 -> 689.29182 | L34: ALUGUEL DE SETEMBRO. PERDA DO DESCONTO (3/12). SEGURO (2/6). PAGO DIA 29/10/2021. | M34: 10 | N34: 11
A35: TOTAL | I35: =SUM(I34) -> 741.174
A36: INADIMPLÊNCIAS
A37: NOME | B37: APTO | C37: PRINCIPAL | D37: CONDIÇÃO | I37: TOTAL | L37: OBSERVAÇÃO | M37: VENC. | N37: CARÊNCIA
A38: JOÃO PAULO | B38: 1 | C38: =600+50+19.74 -> 669.74 | D38: R$ 600,00 (ALUGUEL OUTUBRO) + R$ 50,00 (GARAGEM) + R$ 19,74 (SEGURO 2/6). | I38: =600+50+19.74 -> 669.74 | L38: ALUGUEL DE OUTUBRO. PERDA DO DESCONTO (4/12). SEGURO (3/6). | M38: 10 | N38: 11
A39: TOTAL | I39: =SUM(I38) -> 669.74
A41: OBSERVAÇÕES | L41: COMISSÃO ADMINISTRAÇÃO
A42: SEGURO 01 | B42: ='GERAL 2021'!K3 -> 118.43 | C42: 6 | D42: =B42/C42 -> 19.738333 | L42: COMISSÃO 7% | N42: =J31+J34 -> 411.85298
A43: IPTU 01 | B43: ='GERAL 2021'!I3 -> 1.0710402 | C43: 6 | D43: =B43*C43 -> 6.4262411
A44: SEGURO 02
A45: IPTU 02
A46: SEGURO 03 | L46: OUTRAS COMISSÕES E DESPESAS
A47: IPTU 03 | L47: SEGURO APTO 01 (3/6) | N47: 19.74
A48: SEGURO 04 | L48: SEGURO APTO 10 (5/6) | N48: 17.82
A49: IPTU 04 | L49: SEGURO APTO 15 (3/6) | N49: 19.99
A50: SEGURO 05 | L50: SEGURO APTO 16 (5/6) | N50: 19.81
A51: IPTU 05 | L51: SEGURO APTO 17 (4/6) | N51: 19.81
A52: SEGURO 06 | L52: SEGURO APTO 18 (5/6) | N52: 19.84
A53: IPTU 06 | L53: SEGURO APTO 19 (3/6) | N53: 19.74
A54: SEGURO 07 | L54: SEGURO APTO 25 (5/6) | N54: 19.93
A55: IPTU 07 | L55: SEGURO APTO 27 (6/6) | N55: 19.84
A56: SEGURO 08 | L56: 05 LIMPEZAS (02/10 - 09/10 - 16/10 - 23/10 - 30/10) | N56: =5*120 -> 600
A57: IPTU 08 | L57: ENEL | N57: 129.62
A58: SEGURO 09 | L58: CAGECE | N58: 137.49
A59: IPTU 09
A60: SEGURO 10 | B60: ='GERAL 2021'!K12 -> 106.95 | C60: 6 | D60: =B60/C60 -> 17.825
A61: IPTU 10 | B61: ='GERAL 2021'!I12 -> 1.0710402 | C61: 8 | D61: =B61*C61 -> 8.5683215
A62: SEGURO 11 | L62: TOTAL COMISSÃO + DESPESAS | N62: =SUM(N42:N61) -> 1455.483
A63: IPTU 11
A64: SEGURO 12 | L64: R$ RECEBIDOS EM NOME DO LOCADOR
A65: IPTU 12 | L65: =I31+I35 -> 5883.614
A66: SEGURO 13
A67: IPTU 13 | L67: TOTAL A REPASSAR | N67: =L65-N62 -> 4428.131
A68: SEGURO 14
A69: IPTU 14
A70: SEGURO 15 | B70: ='GERAL 2021'!K17 -> 119.94 | C70: 6 | D70: =B70/C70 -> 19.99
A71: IPTU 15 | B71: ='GERAL 2021'!I17 -> 1.0710402 | C71: 5 | D71: =B71*C71 -> 5.3552009
A72: SEGURO 16 | B72: ='GERAL 2021'!K18 -> 118.87 | C72: 6 | D72: =B72/C72 -> 19.811667
A73: IPTU 16 | B73: ='GERAL 2021'!I18 -> 1.0710402 | C73: 7 | D73: =B73*C73 -> 7.4972813
A74: SEGURO 17 | B74: ='GERAL 2021'!K19 -> 118.87 | C74: 6 | D74: =B74/C74 -> 19.811667
A75: IPTU 17 | B75: ='GERAL 2021'!I19 -> 1.0710402 | C75: 6 | D75: =B75*C75 -> 6.4262411
A76: SEGURO 18 | B76: ='GERAL 2021'!K20 -> 119.02 | C76: 6 | D76: =B76/C76 -> 19.836667
A77: IPTU 18 | B77: ='GERAL 2021'!I20 -> 1.0710402 | C77: 7 | D77: =B77*C77 -> 7.4972813
A78: SEGURO 19 | B78: ='GERAL 2021'!K21 -> 118.43 | C78: 6 | D78: =B78/C78 -> 19.738333
A79: IPTU 19 | B79: ='GERAL 2021'!I21 -> 1.0710402 | C79: 5 | D79: =B79*C79 -> 5.3552009
A80: SEGURO 20
A81: IPTU 20
A82: SEGURO 21
A83: IPTU 21
A84: SEGURO 22
A85: IPTU 22
A86: SEGURO 23
A87: IPTU 23
A88: SEGURO 24
A89: IPTU 24
A90: SEGURO 25 | B90: ='GERAL 2021'!K27 -> 119.7 | C90: 6 | D90: =B90/C90 -> 19.95
A91: IPTU 25 | B91: ='GERAL 2021'!I27 -> 1.0710402 | C91: 6 | D91: =B91*C91 -> 6.4262411
A92: SEGURO 26
A93: IPTU 26
A94: SEGURO 27 | B94: ='GERAL 2021'!K29 -> 119.02 | C94: 6 | D94: =B94/C94 -> 19.836667
A95: IPTU 27 | B95: ='GERAL 2021'!I29 -> 1.0710402 | C95: 8 | D95: =B95*C95 -> 8.5683215

Sheet VIGÊNCIA NOVEMBRO 2021
A1: GRAND MESSEJANA II
A2: VIGÊNCIA DE NOVEMBRO DE 2021
A3: NOME | B3: APTO | C3: ALUGUEL | D3: DESCONTO | E3: ALUGUEL C/ DESCONTO | F3: GARAGEM | G3: IPTU | H3: SEG INC. | I3: TOTAL | J3: COMISSÃO | K3: REPASSE | L3: OBSERVAÇÃO | M3: VENC. | N3: CARÊNCIA
A4: JOÃO PAULO | B4: 1 | C4: 0 | D4: =C4*10% -> 0 | E4: =C4-D4 -> 0 | F4: 0 | G4: 0 | H4: 0 | I4: =SUM(E4:H4) -> 0 | J4: =7%*I4 -> 0 | K4: =I4-J4 -> 0 | L4: INADIMPLÊNCIA | M4: 10 | N4: 11
B5: 2 | J5: =7%*I5 -> 0
B6: 3 | J6: =7%*I6 -> 0
B7: 4 | J7: =7%*I7 -> 0
B8: 5 | J8: =7%*I8 -> 0
B9: 6 | J9: =7%*I9 -> 0
B10: 7 | J10: =7%*I10 -> 0
B11: 8 | J11: =7%*I11 -> 0
B12: 9 | J12: =7%*I12 -> 0
A13: JOÃO CARLOS | B13: 10 | C13: 600 | D13: =10%*C13 -> 60 | E13: =C13-D13 -> 540 | F13: 0 | G13: 0 | H13: =D57 -> 17.825 | I13: =SUM(E13:H13) -> 557.825 | J13: =7%*I13 -> 39.04775 | K13: =I13-J13 -> 518.77725 | L13: DESCONTO 10% (7/12). SEGURO (6/6). | M13: 10 | N13: 11
B14: 11 | J14: =7%*I14 -> 0
B15: 12 | J15: =7%*I15 -> 0
B16: 13 | J16: =7%*I16 -> 0
B17: 14 | J17: =7%*I17 -> 0
A18: CATIANA | B18: 15 | C18: 730 | D18: 60 | E18: =(C18-D18) -> 670 | F18: =50 -> 50 | G18: 0 | H18: =D67 -> 19.99 | I18: =SUM(E18:H18) -> 739.99 | J18: =7%*I18 -> 51.7993 | K18: =I18-J18 -> 688.1907 | L18: DESCONTO R$ 60,00 (4/12). SEGURO (4/6). | M18: 10 | N18: 11
A19: VANESSA | B19: 16 | C19: ='GERAL 2021'!G18 -> 640 | D19: =10%*C19 -> 64 | E19: =C19-D19 -> 576 | F19: =60 -> 60 | G19: 0 | H19: =D69 -> 19.811667 | I19: =SUM(E19:H19) -> 655.81167 | J19: =7%*I19 -> 45.906817 | K19: =I19-J19 -> 609.90485 | L19: DESCONTO 10% (6/12). SEGURO (6/6). | M19: 10 | N19: 11
A20: MATEUS | B20: 17 | C20: ='GERAL 2021'!G19 -> 640 | D20: =10%*C20 -> 64 | E20: =(C20-D20) -> 576 | F20: 0 | G20: 0 | H20: =D71 -> 19.811667 | I20: =SUM(E20:H20) -> 595.81167 | J20: =7%*I20 -> 41.706817 | K20: =I20-J20 -> 554.10485 | L20: DESCONTO 10% (5/12). SEGURO (5/6). | M20: 10 | N20: 11
A21: FREDSON | B21: 18 | C21: ='GERAL 2021'!G20 -> 650 | D21: =10%*C21 -> 65 | E21: =C21-D21 -> 585 | F21: =30 -> 30 | G21: 0 | H21: =D73 -> 19.836667 | I21: =SUM(E21:H21) -> 634.83667 | J21: =7%*I21 -> 44.438567 | K21: =I21-J21 -> 590.3981 | L21: DESCONTO 10% (6/12). SEGURO (6/6). | M21: 10 | N21: 11
A22: ERIVANDO | B22: 19 | C22: 600 | D22: =10%*C22 -> 60 | E22: =(C22-D22) -> 540 | F22: =50 -> 50 | G22: 0 | H22: =D75 -> 19.738333 | I22: =SUM(E22:H22) -> 609.73833 | J22: =7%*I22 -> 42.681683 | K22: =I22-J22 -> 567.05665 | L22: DESCONTO 10% (4/12). SEGURO (4/6). | M22: 10 | N22: 11
B23: 20 | J23: =7%*I23 -> 0
B24: 21 | J24: =7%*I24 -> 0
B25: 22 | J25: =7%*I25 -> 0
B26: 23 | J26: =7%*I26 -> 0
B27: 24 | J27: =7%*I27 -> 0
A28: SHIRLEY | B28: 25 | C28: =704 -> 704 | D28: =10%*C28 -> 70.4 | E28: =C28-D28 -> 633.6 | F28: =30 -> 30 | G28: 0 | H28: 19.99 | I28: =SUM(E28:H28) -> 683.59 | J28: =7%*I28 -> 47.8513 | K28: =I28-J28 -> 635.7387 | L28: DESCONTO 10% (7/12). SEGURO (6/6). | M28: 10 | N28: 11
B29: 26 | J29: =7%*I29 -> 0
A30: LUIZA | B30: 27 | C30: =650 -> 650 | D30: =10%*C30 -> 65 | E30: =C30-D30 -> 585 | F30: =60 -> 60 | G30: 0 | H30: 0 | I30: =SUM(E30:H30) -> 645 | J30: =7%*I30 -> 45.15 | K30: =I30-J30 -> 599.85 | L30: DESCONTO 10% (7/12). SEGURO QUITADO. | M30: 10 | N30: 11
A31: TOTAL | C31: =SUM(C4:C30) -> 5214 | D31: =SUM(D4:D30) -> 508.4 | E31: =SUM(E4:E30) -> 4705.6 | F31: =SUM(F4:F30) -> 280 | G31: =SUM(G4:G30) -> 0 | H31: =SUM(H4:H30) -> 137.00333 | I31: =SUM(I4:I30) -> 5122.6033 | J31: =SUM(J4:J30) -> 358.58223 | K31: =SUM(K4:K30) -> 4764.0211
A32: INADIMPLÊNCIAS
A33: NOME | B33: APTO | C33: PRINCIPAL | D33: CONDIÇÃO | I33: TOTAL | L33: OBSERVAÇÃO | M33: VENC. | N33: CARÊNCIA
A34: JOÃO PAULO | B34: 1 | C34: =600+50+19.74 -> 669.74 | D34: R$ 600,00 (ALUGUEL OUTUBRO) + R$ 50,00 (GARAGEM) + R$ 19,74 (SEGURO 3/6). | I34: =600+50+19.74 -> 669.74 | L34: ALUGUEL DE OUTUBRO. PERDA DO DESCONTO (4/12). SEGURO (3/6). | M34: 10 | N34: 11
A35: JOÃO PAULO | B35: 1 | C35: =600+50+19.74 -> 669.74 | D35: R$ 600,00 (ALUGUEL NOVEMBRO) + R$ 50,00 (GARAGEM) + R$ 19,74 (SEGURO 4/6). | I35: =600+50+19.74 -> 669.74 | L35: ALUGUEL DE NOVEMBRO. PERDA DO DESCONTO (5/12). SEGURO (4/6). | M35: 10 | N35: 11
A36: TOTAL | I36: =SUM(I34:I35) -> 1339.48
A38: OBSERVAÇÕES | L38: COMISSÃO ADMINISTRAÇÃO
A39: SEGURO 01 | B39: ='GERAL 2021'!K3 -> 118.43 | C39: 6 | D39: =B39/C39 -> 19.738333 | L39: COMISSÃO 7% | N39: =J31 -> 358.58223
A40: IPTU 01 | B40: ='GERAL 2021'!I3 -> 1.0710402 | C40: 6 | D40: =B40*C40 -> 6.4262411
A41: SEGURO 02
A42: IPTU 02
A43: SEGURO 03 | L43: OUTRAS COMISSÕES E DESPESAS
A44: IPTU 03 | L44: SEGURO APTO 01 (4/6) | N44: 19.74
A45: SEGURO 04 | L45: SEGURO APTO 10 (6/6) | N45: 17.83
A46: IPTU 04 | L46: SEGURO APTO 15 (4/6) | N46: 19.99
A47: SEGURO 05 | L47: SEGURO APTO 16 (6/6) | N47: 19.81
A48: IPTU 05 | L48: SEGURO APTO 17 (5/6) | N48: 19.81
A49: SEGURO 06 | L49: SEGURO APTO 18 (6/6) | N49: 19.84
A50: IPTU 06 | L50: SEGURO APTO 19 (4/6) | N50: 19.74
A51: SEGURO 07 | L51: SEGURO APTO 25 (6/6) | N51: 19.93
A52: IPTU 07 | L52: 04 LIMPEZAS (06/11/2021 - 13/11/2021 - 20/11/2021 - 27/11/2021) | N52: =4*120 -> 480
A53: SEGURO 08 | L53: ENEL | N53: 135.68
A54: IPTU 08 | L54: CAGECE | N54: 45.2
A55: SEGURO 09 | L55: SERVIÇO INSTALAÇÃO FECHADURA TETRA | N55: 900
A56: IPTU 09
A57: SEGURO 10 | B57: ='GERAL 2021'!K12 -> 106.95 | C57: 6 | D57: =B57/C57 -> 17.825
A58: IPTU 10 | B58: ='GERAL 2021'!I12 -> 1.0710402 | C58: 8 | D58: =B58*C58 -> 8.5683215 | L58: TOTAL COMISSÃO + DESPESAS | N58: =SUM(N39:N57) -> 2076.1522
A59: SEGURO 11
A60: IPTU 11 | L60: R$ RECEBIDOS EM NOME DO LOCADOR
A61: SEGURO 12 | L61: =I31 -> 5122.6033
A62: IPTU 12
A63: SEGURO 13 | L63: TOTAL A REPASSAR | N63: =L61-N58 -> 3046.4511
A64: IPTU 13
A65: SEGURO 14
A66: IPTU 14
A67: SEGURO 15 | B67: ='GERAL 2021'!K17 -> 119.94 | C67: 6 | D67: =B67/C67 -> 19.99
A68: IPTU 15 | B68: ='GERAL 2021'!I17 -> 1.0710402 | C68: 5 | D68: =B68*C68 -> 5.3552009
A69: SEGURO 16 | B69: ='GERAL 2021'!K18 -> 118.87 | C69: 6 | D69: =B69/C69 -> 19.811667
A70: IPTU 16 | B70: ='GERAL 2021'!I18 -> 1.0710402 | C70: 7 | D70: =B70*C70 -> 7.4972813
A71: SEGURO 17 | B71: ='GERAL 2021'!K19 -> 118.87 | C71: 6 | D71: =B71/C71 -> 19.811667
A72: IPTU 17 | B72: ='GERAL 2021'!I19 -> 1.0710402 | C72: 6 | D72: =B72*C72 -> 6.4262411
A73: SEGURO 18 | B73: ='GERAL 2021'!K20 -> 119.02 | C73: 6 | D73: =B73/C73 -> 19.836667
A74: IPTU 18 | B74: ='GERAL 2021'!I20 -> 1.0710402 | C74: 7 | D74: =B74*C74 -> 7.4972813
A75: SEGURO 19 | B75: ='GERAL 2021'!K21 -> 118.43 | C75: 6 | D75: =B75/C75 -> 19.738333
A76: IPTU 19 | B76: ='GERAL 2021'!I21 -> 1.0710402 | C76: 5 | D76: =B76*C76 -> 5.3552009
A77: SEGURO 20
A78: IPTU 20
A79: SEGURO 21
A80: IPTU 21
A81: SEGURO 22
A82: IPTU 22
A83: SEGURO 23
A84: IPTU 23
A85: SEGURO 24
A86: IPTU 24
A87: SEGURO 25 | B87: ='GERAL 2021'!K27 -> 119.7 | C87: 6 | D87: =B87/C87 -> 19.95
A88: IPTU 25 | B88: ='GERAL 2021'!I27 -> 1.0710402 | C88: 6 | D88: =B88*C88 -> 6.4262411
A89: SEGURO 26
A90: IPTU 26
A91: SEGURO 27 | B91: ='GERAL 2021'!K29 -> 119.02
A92: IPTU 27 | B92: ='GERAL 2021'!I29 -> 1.0710402 | C92: 8 | D92: =B92*C92 -> 8.5683215

Sheet VIGÊNCIA DEZEMBRO 2021
A1: GRAND MESSEJANA II
A2: VIGÊNCIA DE DEZEMBRO DE 2021
A3: NOME | B3: APTO | C3: ALUGUEL | D3: DESCONTO | E3: ALUGUEL C/ DESCONTO | F3: GARAGEM | G3: IPTU | H3: SEG INC. | I3: TOTAL | J3: COMISSÃO | K3: REPASSE | L3: OBSERVAÇÃO | M3: VENC. | N3: CARÊNCIA
A4: JOÃO PAULO | B4: 1 | C4: 0 | D4: 0 | E4: =C4-D4 -> 0 | F4: 0 | G4: 0 | H4: 0 | I4: =SUM(E4:H4) -> 0 | J4: =7%*I4 -> 0 | K4: =I4-J4 -> 0 | L4: INADIMPLÊNCIA | M4: 10 | N4: 11
B5: 2 | J5: =7%*I5 -> 0
B6: 3 | J6: =7%*I6 -> 0
B7: 4 | J7: =7%*I7 -> 0
B8: 5 | J8: =7%*I8 -> 0
B9: 6 | J9: =7%*I9 -> 0
B10: 7 | J10: =7%*I10 -> 0
B11: 8 | J11: =7%*I11 -> 0
B12: 9 | J12: =7%*I12 -> 0
A13: JOÃO CARLOS | B13: 10 | C13: 600 | D13: =10%*C13 -> 60 | E13: =C13-D13 -> 540 | F13: 0 | G13: 0 | H13: 0 | I13: =SUM(E13:H13) -> 540 | J13: =7%*I13 -> 37.8 | K13: =I13-J13 -> 502.2 | L13: DESCONTO 10% (8/12). SEGURO QUITADO. | M13: 10 | N13: 11
B14: 11 | J14: =7%*I14 -> 0
B15: 12 | J15: =7%*I15 -> 0
B16: 13 | J16: =7%*I16 -> 0
B17: 14 | J17: =7%*I17 -> 0
A18: CATIANA | B18: 15 | C18: 730 | D18: 60 | E18: =(C18-D18) -> 670 | F18: =50 -> 50 | G18: 0 | H18: =D68 -> 19.99 | I18: =SUM(E18:H18) -> 739.99 | J18: =7%*I18 -> 51.7993 | K18: =I18-J18 -> 688.1907 | L18: DESCONTO R$ 60,00 (5/12). SEGURO (5/6). | M18: 10 | N18: 11
A19: VANESSA | B19: 16 | C19: ='GERAL 2021'!G18 -> 640 | D19: =10%*C19 -> 64 | E19: =C19-D19 -> 576 | F19: =60 -> 60 | G19: 0 | H19: 0 | I19: =SUM(E19:H19) -> 636 | J19: =7%*I19 -> 44.52 | K19: =I19-J19 -> 591.48 | L19: DESCONTO 10% (7/12). SEGURO QUITADO. | M19: 10 | N19: 11
A20: MATEUS | B20: 17 | C20: ='GERAL 2021'!G19 -> 640 | D20: =10%*C20 -> 64 | E20: =(C20-D20) -> 576 | F20: 0 | G20: 0 | H20: =D72 -> 19.811667 | I20: =SUM(E20:H20) -> 595.81167 | J20: =7%*I20 -> 41.706817 | K20: =I20-J20 -> 554.10485 | L20: DESCONTO 10% (6/12). SEGURO (6/6). | M20: 10 | N20: 11
A21: FREDSON | B21: 18 | C21: ='GERAL 2021'!G20 -> 650 | D21: =10%*C21 -> 65 | E21: =C21-D21 -> 585 | F21: =30 -> 30 | G21: 0 | H21: 0 | I21: =SUM(E21:H21) -> 615 | J21: =7%*I21 -> 43.05 | K21: =I21-J21 -> 571.95 | L21: DESCONTO 10% (7/12). SEGURO QUITADO. | M21: 10 | N21: 11
A22: ERIVANDO | B22: 19 | C22: 600 | D22: =10%*C22 -> 60 | E22: =(C22-D22) -> 540 | F22: =50 -> 50 | G22: 0 | H22: =D76 -> 19.738333 | I22: =SUM(E22:H22) -> 609.73833 | J22: =7%*I22 -> 42.681683 | K22: =I22-J22 -> 567.05665 | L22: DESCONTO 10% (5/12). SEGURO (5/6). | M22: 10 | N22: 11
B23: 20 | J23: =7%*I23 -> 0
B24: 21 | J24: =7%*I24 -> 0
B25: 22 | J25: =7%*I25 -> 0
B26: 23 | J26: =7%*I26 -> 0
B27: 24 | J27: =7%*I27 -> 0
A28: SHIRLEY | B28: 25 | C28: =704 -> 704 | D28: =10%*C28 -> 70.4 | E28: =C28-D28 -> 633.6 | F28: =30 -> 30 | G28: 0 | H28: 0 | I28: =SUM(E28:H28) -> 663.6 | J28: =7%*I28 -> 46.452 | K28: =I28-J28 -> 617.148 | L28: DESCONTO 10% (8/12). SEGURO QUITADO. | M28: 10 | N28: 11
B29: 26 | J29: =7%*I29 -> 0
A30: LUIZA | B30: 27 | C30: =650 -> 650 | D30: =10%*C30 -> 65 | E30: =C30-D30 -> 585 | F30: =60 -> 60 | G30: 0 | H30: 0 | I30: =SUM(E30:H30) -> 645 | J30: =7%*I30 -> 45.15 | K30: =I30-J30 -> 599.85 | L30: DESCONTO 10% (8/12). SEGURO QUITADO. | M30: 10 | N30: 11
A31: TOTAL | C31: =SUM(C4:C30) -> 5214 | D31: =SUM(D4:D30) -> 508.4 | E31: =SUM(E4:E30) -> 4705.6 | F31: =SUM(F4:F30) -> 280 | G31: =SUM(G4:G30) -> 0 | H31: =SUM(H4:H30) -> 59.54 | I31: =SUM(I4:I30) -> 5045.14 | J31: =SUM(J4:J30) -> 353.1598 | K31: =SUM(K4:K30) -> 4691.9802
A32: INADIMPLÊNCIAS
A33: NOME | B33: APTO | C33: PRINCIPAL | D33: CONDIÇÃO | I33: TOTAL | L33: OBSERVAÇÃO | M33: VENC. | N33: CARÊNCIA
A34: JOÃO PAULO | B34: 1 | C34: =600+50+19.74 -> 669.74 | D34: R$ 600,00 (ALUGUEL OUTUBRO) + R$ 50,00 (GARAGEM) + R$ 19,74 (SEGURO 3/6). | I34: =600+50+19.74 -> 669.74 | L34: ALUGUEL DE OUTUBRO. PERDA DO DESCONTO (4/12). SEGURO (3/6). | M34: 10 | N34: 11
A35: JOÃO PAULO | B35: 1 | C35: =600+50+19.74 -> 669.74 | D35: R$ 600,00 (ALUGUEL NOVEMBRO) + R$ 50,00 (GARAGEM) + R$ 19,74 (SEGURO 4/6). | I35: =600+50+19.74 -> 669.74 | L35: ALUGUEL DE NOVEMBRO. PERDA DO DESCONTO (5/12). SEGURO (4/6). | M35: 10 | N35: 11
A36: JOÃO PAULO | B36: 1 | C36: =600+50+19.74 -> 669.74 | D36: R$ 600,00 (ALUGUEL DEZEMBBRO) + R$ 50,00 (GARAGEM) + R$ 19,74 (SEGURO 5/6). | I36: =600+50+19.74 -> 669.74 | L36: ALUGUEL DE DEZEMBRO. PERDA DO DESCONTO (6/12). SEGURO (5/6). | M36: 10 | N36: 11
A37: TOTAL | I37: =SUM(I34:I36) -> 2009.22
A39: OBSERVAÇÕES | L39: COMISSÃO ADMINISTRAÇÃO
A40: SEGURO 01 | B40: ='GERAL 2021'!K3 -> 118.43 | C40: 6 | D40: =B40/C40 -> 19.738333 | L40: COMISSÃO 7% | N40: =J31 -> 353.1598
A41: IPTU 01 | B41: ='GERAL 2021'!I3 -> 1.0710402 | C41: 6 | D41: =B41*C41 -> 6.4262411
A42: SEGURO 02
A43: IPTU 02
A44: SEGURO 03 | L44: OUTRAS COMISSÕES E DESPESAS
A45: IPTU 03 | L45: SEGURO APTO 01 (5/6) | N45: 19.74
A46: SEGURO 04 | L46: SEGURO APTO 15 (5/6) | N46: 19.99
A47: IPTU 04 | L47: SEGURO APTO 17 (6/6) | N47: 19.81
A48: SEGURO 05 | L48: SEGURO APTO 19 (5/6) | N48: 19.74
A49: IPTU 05 | L49: 04 LIMPEZAS (04/12/2021 - 11/12/2021 - 18/12/2021 - 25/12/2021) | N49: =4*120 -> 480
A50: SEGURO 06 | L50: ENEL | N50: 136.48
A51: IPTU 06 | L51: CAGECE | N51: 1770.73
A52: SEGURO 07 | L52: RESSARCIMENTO 50% FECHADURA TETRA APTO 18 FREDSON | N52: 60.5
A53: IPTU 07
A54: SEGURO 08
A55: IPTU 08
A56: SEGURO 09
A57: IPTU 09
A58: SEGURO 10 | B58: ='GERAL 2021'!K12 -> 106.95 | C58: 6 | D58: =B58/C58 -> 17.825
A59: IPTU 10 | B59: ='GERAL 2021'!I12 -> 1.0710402 | C59: 8 | D59: =B59*C59 -> 8.5683215 | L59: TOTAL COMISSÃO + DESPESAS | N59: =SUM(N40:N58) -> 2880.1498
A60: SEGURO 11
A61: IPTU 11 | L61: R$ RECEBIDOS EM NOME DO LOCADOR
A62: SEGURO 12 | L62: =I31 -> 5045.14
A63: IPTU 12
A64: SEGURO 13 | L64: TOTAL A REPASSAR | N64: =L62-N59 -> 2164.9902
A65: IPTU 13
A66: SEGURO 14
A67: IPTU 14
A68: SEGURO 15 | B68: ='GERAL 2021'!K17 -> 119.94 | C68: 6 | D68: =B68/C68 -> 19.99
A69: IPTU 15 | B69: ='GERAL 2021'!I17 -> 1.0710402 | C69: 5 | D69: =B69*C69 -> 5.3552009
A70: SEGURO 16 | B70: ='GERAL 2021'!K18 -> 118.87 | C70: 6 | D70: =B70/C70 -> 19.811667
A71: IPTU 16 | B71: ='GERAL 2021'!I18 -> 1.0710402 | C71: 7 | D71: =B71*C71 -> 7.4972813
A72: SEGURO 17 | B72: ='GERAL 2021'!K19 -> 118.87 | C72: 6 | D72: =B72/C72 -> 19.811667
A73: IPTU 17 | B73: ='GERAL 2021'!I19 -> 1.0710402 | C73: 6 | D73: =B73*C73 -> 6.4262411
A74: SEGURO 18 | B74: ='GERAL 2021'!K20 -> 119.02 | C74: 6 | D74: =B74/C74 -> 19.836667
A75: IPTU 18 | B75: ='GERAL 2021'!I20 -> 1.0710402 | C75: 7 | D75: =B75*C75 -> 7.4972813
A76: SEGURO 19 | B76: ='GERAL 2021'!K21 -> 118.43 | C76: 6 | D76: =B76/C76 -> 19.738333
A77: IPTU 19 | B77: ='GERAL 2021'!I21 -> 1.0710402 | C77: 5 | D77: =B77*C77 -> 5.3552009
A78: SEGURO 20
A79: IPTU 20
A80: SEGURO 21
A81: IPTU 21
A82: SEGURO 22
A83: IPTU 22
A84: SEGURO 23
A85: IPTU 23
A86: SEGURO 24
A87: IPTU 24
A88: SEGURO 25 | B88: ='GERAL 2021'!K27 -> 119.7 | C88: 6 | D88: =B88/C88 -> 19.95
A89: IPTU 25 | B89: ='GERAL 2021'!I27 -> 1.0710402 | C89: 6 | D89: =B89*C89 -> 6.4262411
A90: SEGURO 26
A91: IPTU 26
A92: SEGURO 27 | B92: ='GERAL 2021'!K29 -> 119.02
A93: IPTU 27 | B93: ='GERAL 2021'!I29 -> 1.0710402 | C93: 8 | D93: =B93*C93 -> 8.5683215

Sheet VIGÊNCIA JANEIRO 2022
A1: GRAND MESSEJANA II
A2: VIGÊNCIA DE JANEIRO 2022
A3: NOME | B3: APTO | C3: ALUGUEL | D3: DESCONTO | E3: ALUGUEL C/ DESCONTO | F3: GARAGEM | G3: IPTU | H3: SEG INC. | I3: TOTAL | J3: COMISSÃO | K3: REPASSE | L3: OBSERVAÇÃO | M3: VENC. | N3: CARÊNCIA
A4: JOÃO PAULO | B4: 1 | C4: 0 | D4: =10%*C4 -> 0 | E4: =C4-D4 -> 0 | F4: 0 | G4: 0 | H4: 0 | I4: =SUM(E4:H4) -> 0 | J4: =7%*I4 -> 0 | K4: =I4-J4 -> 0 | L4: INADIMPLÊNCIA | M4: 10 | N4: 11
B5: 2 | J5: =7%*I5 -> 0
B6: 3 | J6: =7%*I6 -> 0
B7: 4 | J7: =7%*I7 -> 0
B8: 5 | J8: =7%*I8 -> 0
B9: 6 | J9: =7%*I9 -> 0
B10: 7 | J10: =7%*I10 -> 0
B11: 8 | J11: =7%*I11 -> 0
A12: ALCIDES / RENÊ | B12: 9 | C12: ='GERAL 2022'!G11/31*12 -> 224.51613 | D12: 0 | E12: =C12-D12 -> 224.51613 | F12: =75/31*12 -> 29.032258 | G12: =D58/31*12 -> 1.0981194 | H12: =D57 -> 19.696667 | I12: =SUM(E12:H12) -> 274.34317 | J12: =7%*I12 -> 19.204022 | K12: =I12-J12 -> 255.13915 | L12: ALUGUEL, GARAGEM E IPTU DE 12 DIAS (20/01 A 31/01). SEM DESCONTO. SEGURO (1/6). IPTU (1/5). | M12: 10 | N12: 11
A13: JOÃO CARLOS | B13: 10 | C13: ='GERAL 2022'!G12 -> 600 | D13: =10%*C13 -> 60 | E13: =C13-D13 -> 540 | F13: 0 | G13: =D60 -> 2.8368085 | H13: 0 | I13: =SUM(E13:H13) -> 542.83681 | J13: =7%*I13 -> 37.998577 | K13: =I13-J13 -> 504.83823 | L13: DESCONTO 10% (9/12). SEGURO QUITADO. IPTU (1/5). | M13: 10 | N13: 11
B14: 11 | J14: =7%*I14 -> 0
B15: 12 | J15: =7%*I15 -> 0
B16: 13 | J16: =7%*I16 -> 0
B17: 14 | J17: =7%*I17 -> 0
A18: CATIANA | B18: 15 | C18: 730 | D18: 60 | E18: =(C18-D18) -> 670 | F18: =50 -> 50 | G18: =D70 -> 3.9715319 | H18: =D69 -> 19.99 | I18: =SUM(E18:H18) -> 743.96153 | J18: =7%*I18 -> 52.077307 | K18: =I18-J18 -> 691.88422 | L18: DESCONTO R$ 60,00 (6/12). SEGURO (6/6). IPTU (1/5). | M18: 10 | N18: 11
A19: VANESSA | B19: 16 | C19: ='GERAL 2022'!G18 -> 640 | D19: =10%*C19 -> 64 | E19: =C19-D19 -> 576 | F19: =60 -> 60 | G19: =D72 -> 2.8368085 | H19: 0 | I19: =SUM(E19:H19) -> 638.83681 | J19: =7%*I19 -> 44.718577 | K19: =I19-J19 -> 594.11823 | L19: DESCONTO 10% (8/12). SEGURO QUITADO. IPTU (1/5). | M19: 10 | N19: 11
A20: MATEUS | B20: 17 | C20: ='GERAL 2022'!G19 -> 640 | D20: =10%*C20 -> 64 | E20: =(C20-D20) -> 576 | F20: 0 | G20: =D74 -> 2.8368085 | H20: 0 | I20: =SUM(E20:H20) -> 578.83681 | J20: =7%*I20 -> 40.518577 | K20: =I20-J20 -> 538.31823 | L20: DESCONTO 10% (7/12). SEGURO QUITADO. IPTU (1/5). | M20: 10 | N20: 11
A21: FREDSON | B21: 18 | C21: ='GERAL 2022'!G20 -> 650 | D21: =10%*C21 -> 65 | E21: =C21-D21 -> 585 | F21: =30 -> 30 | G21: =D76 -> 2.8368085 | H21: 0 | I21: =SUM(E21:H21) -> 617.83681 | J21: =7%*I21 -> 43.248577 | K21: =I21-J21 -> 574.58823 | L21: DESCONTO 10% (8/12). SEGURO QUITADO. IPTU (1/5). | M21: 10 | N21: 11
A22: ERIVANDO | B22: 19 | C22: ='GERAL 2022'!G21 -> 600 | D22: =10%*C22 -> 60 | E22: =(C22-D22) -> 540 | F22: =50 -> 50 | G22: =D78 -> 2.8368085 | H22: =D77 -> 19.738333 | I22: =SUM(E22:H22) -> 612.57514 | J22: =7%*I22 -> 42.88026 | K22: =I22-J22 -> 569.69488 | L22: DESCONTO 10% (6/12). SEGURO (6/6). IPTU (1/5). | M22: 10 | N22: 11
B23: 20 | J23: =7%*I23 -> 0
B24: 21 | J24: =7%*I24 -> 0
B25: 22 | J25: =7%*I25 -> 0
B26: 23 | J26: =7%*I26 -> 0
B27: 24 | C27: ='VIGÊNCIA FEVEREIRO 2022'!C31 -> 0 | J27: =7%*I27 -> 0
A28: SHIRLEY | B28: 25 | C28: ='GERAL 2022'!G27 -> 704 | D28: =10%*C28 -> 70.4 | E28: =C28-D28 -> 633.6 | F28: =30 -> 30 | G28: =D90 -> 2.8368085 | H28: 0 | I28: =SUM(E28:H28) -> 666.43681 | J28: =7%*I28 -> 46.650577 | K28: =I28-J28 -> 619.78623 | L28: DESCONTO 10% (9/12). SEGURO QUITADO. IPTU (1/5). | M28: 10 | N28: 11
B29: 26 | J29: =7%*I29 -> 0
A30: LUIZA | B30: 27 | C30: ='GERAL 2022'!G29 -> 650 | D30: =10%*C30 -> 65 | E30: =C30-D30 -> 585 | F30: =60 -> 60 | G30: =D94 -> 2.8368085 | H30: 0 | I30: =SUM(E30:H30) -> 647.83681 | J30: =7%*I30 -> 45.348577 | K30: =I30-J30 -> 602.48823 | L30: DESCONTO 10% (9/12). SEGURO QUITADO. IPTU (1/5). | M30: 10 | N30: 11
A31: TOTAL | C31: =SUM(C4:C30) -> 5438.5161 | D31: =SUM(D4:D30) -> 508.4 | E31: =SUM(E4:E30) -> 4930.1161 | F31: =SUM(F4:F30) -> 309.03226 | G31: =SUM(G4:G30) -> 24.927311 | H31: =SUM(H4:H30) -> 59.425 | I31: =SUM(I4:I30) -> 5323.5007 | J31: =SUM(J4:J30) -> 372.64505 | K31: =SUM(K4:K30) -> 4950.8556
A32: INADIMPLÊNCIAS
A33: NOME | B33: APTO | C33: PRINCIPAL | D33: CONDIÇÃO | I33: TOTAL | L33: OBSERVAÇÃO | M33: VENC. | N33: CARÊNCIA
A34: JOÃO PAULO | B34: 1 | C34: =600+50+19.74 -> 669.74 | D34: R$ 600,00 (ALUGUEL OUTUBRO) + R$ 50,00 (GARAGEM) + R$ 19,74 (SEGURO 3/6). | I34: =600+50+19.74 -> 669.74 | L34: ALUGUEL DE OUTUBRO/2021. PERDA DO DESCONTO (4/12). SEGURO (3/6). | M34: 10 | N34: 11
A35: JOÃO PAULO | B35: 1 | C35: =600+50+19.74 -> 669.74 | D35: R$ 600,00 (ALUGUEL NOVEMBRO) + R$ 50,00 (GARAGEM) + R$ 19,74 (SEGURO 4/6). | I35: =600+50+19.74 -> 669.74 | L35: ALUGUEL DE NOVEMBRO/2021. PERDA DO DESCONTO (5/12). SEGURO (4/6). | M35: 10 | N35: 11
A36: JOÃO PAULO | B36: 1 | C36: =600+50+19.74 -> 669.74 | D36: R$ 600,00 (ALUGUEL DEZEMBRO) + R$ 50,00 (GARAGEM) + R$ 19,74 (SEGURO 5/6). | I36: =600+50+19.74 -> 669.74 | L36: ALUGUEL DE DEZEMBRO/2021. PERDA DO DESCONTO (6/12). SEGURO (5/6). | M36: 10 | N36: 11
A37: JOÃO PAULO | B37: 1 | C37: =600+50+19.74+2.84 -> 672.58 | D37: R$ 600,00 (ALUGUEL JANEIRO) + R$ 50,00 (GARAGEM) + R$ 19,74 (SEGURO 5/6). | I37: =600+50+19.74+2.84 -> 672.58 | L37: ALUGUEL DE JANEIRO/2022. PERDA DO DESCONTO (7/12). SEGURO (6/6). IPTU (1/5). | M37: 10 | N37: 11
A38: TOTAL | I38: =SUM(I34:I37) -> 2681.8
A40: OBSERVAÇÕES | L40: COMISSÃO ADMINISTRAÇÃO
A41: SEGURO 01 | B41: ='GERAL 2022'!J3 -> 118.43 | C41: 6 | D41: =B41/C41 -> 19.738333 | L41: COMISSÃO 7% | N41: =J31 -> 372.64505
A42: IPTU 01 | B42: ='GERAL 2022'!H3 -> 14.184043 | C42: 5 | D42: =B42/C42 -> 2.8368085
A43: SEGURO 02
A44: IPTU 02
A45: SEGURO 03 | L45: OUTRAS COMISSÕES E DESPESAS
A46: IPTU 03 | L46: SEGURO APTO 01 (6/6) | N46: 19.74
A47: SEGURO 04 | L47: SEGURO APTO 09 (1/6) | N47: 19.68
A48: IPTU 04 | L48: SEGURO APTO 15 (6/6) | N48: 19.99
A49: SEGURO 05 | L49: SEGURO APTO 19 (6/6) | N49: 19.74
A50: IPTU 05 | L50: 05 LIMPEZAS (01/01/2022 - 08/01/2022 - 15/01/2022 - 22/01/2022 - 29/01/2022) | N50: =120*5 -> 600
A51: SEGURO 06 | L51: ENEL | N51: 139.15
A52: IPTU 06 | L52: CAGECE | N52: 387.36
A53: SEGURO 07 | L53: DOCS PARA PROTESTO JOÃO PAULO APTO 01 | N53: 36.99
A54: IPTU 07 | L54: RECONHECIMENTO DE FIRMA APTO 09 | N54: 7.92
A55: SEGURO 08
A56: IPTU 08
A57: SEGURO 09 | B57: ='GERAL 2022'!J11 -> 118.18 | C57: 6 | D57: =B57/C57 -> 19.696667
A58: IPTU 09 | B58: ='GERAL 2022'!H11 -> 14.184043 | C58: 5 | D58: =B58/C58 -> 2.8368085
A59: SEGURO 10 | B59: ='GERAL 2022'!J12 -> 106.95 | C59: 6 | D59: =B59/C59 -> 17.825
A60: IPTU 10 | B60: ='GERAL 2022'!H12 -> 14.184043 | C60: 5 | D60: =B60/C60 -> 2.8368085 | L60: TOTAL COMISSÃO + DESPESAS | N60: =SUM(N41:N59) -> 1623.215
A61: SEGURO 11
A62: IPTU 11 | L62: R$ RECEBIDOS EM NOME DO LOCADOR
A63: SEGURO 12 | L63: =I31 -> 5323.5007
A64: IPTU 12
A65: SEGURO 13 | L65: TOTAL A REPASSAR | N65: =L63-N60 -> 3700.2856
A66: IPTU 13
A67: SEGURO 14
A68: IPTU 14
A69: SEGURO 15 | B69: ='GERAL 2022'!J17 -> 119.94 | C69: 6 | D69: =B69/C69 -> 19.99
A70: IPTU 15 | B70: ='GERAL 2022'!H17 -> 19.85766 | C70: 5 | D70: =B70/C70 -> 3.9715319
A71: SEGURO 16 | B71: ='GERAL 2022'!J18 -> 118.87 | C71: 6 | D71: =B71/C71 -> 19.811667
A72: IPTU 16 | B72: ='GERAL 2022'!H18 -> 14.184043 | C72: 5 | D72: =B72/C72 -> 2.8368085
A73: SEGURO 17 | B73: ='GERAL 2022'!J19 -> 118.87 | C73: 6 | D73: =B73/C73 -> 19.811667
A74: IPTU 17 | B74: ='GERAL 2022'!H19 -> 14.184043 | C74: 5 | D74: =B74/C74 -> 2.8368085
A75: SEGURO 18 | B75: ='GERAL 2022'!J20 -> 119.02 | C75: 6 | D75: =B75/C75 -> 19.836667
A76: IPTU 18 | B76: ='GERAL 2022'!H20 -> 14.184043 | C76: 5 | D76: =B76/C76 -> 2.8368085
A77: SEGURO 19 | B77: ='GERAL 2022'!J21 -> 118.43 | C77: 6 | D77: =B77/C77 -> 19.738333
A78: IPTU 19 | B78: ='GERAL 2022'!H21 -> 14.184043 | C78: 5 | D78: =B78/C78 -> 2.8368085
A79: SEGURO 20
A80: IPTU 20
A81: SEGURO 21
A82: IPTU 21
A83: SEGURO 22
A84: IPTU 22
A85: SEGURO 23
A86: IPTU 23
A87: SEGURO 24
A88: IPTU 24
A89: SEGURO 25 | B89: ='GERAL 2022'!J27 -> 119.7 | C89: 6 | D89: =B89/C89 -> 19.95
A90: IPTU 25 | B90: ='GERAL 2022'!H27 -> 14.184043 | C90: 5 | D90: =B90/C90 -> 2.8368085
A91: SEGURO 26
A92: IPTU 26
A93: SEGURO 27 | B93: ='GERAL 2022'!J29 -> 119.02 | C93: 6 | D93: =B93/C93 -> 19.836667
A94: IPTU 27 | B94: ='GERAL 2022'!H29 -> 14.184043 | C94: 5 | D94: =B94/C94 -> 2.8368085

Sheet VIGÊNCIA FEVEREIRO 2022
A1: GRAND MESSEJANA II
A2: INTERMEDIAÇÃO DE JANEIRO DE 2022
A3: NOME | B3: APTO | C3: ALUGUEL | D3: DESCONTO | E3: ALUGUEL C/ DESCONTO | F3: GARAGEM | G3: IPTU | H3: SEG INC. | I3: TOTAL | J3: COMISSÃO | K3: REPASSE | L3: OBSERVAÇÃO | M3: VENC. | N3: CARÊNCIA
A4: ALCIDES / RENÊ | B4: 9 | C4: ='GERAL 2022'!G11 -> 580 | D4: 0 | E4: =C4-D4 -> 580 | F4: 75 | G4: =D67 -> 2.8368085 | H4: =D66 -> 19.696667 | I4: =SUM(E4:H4) -> 677.53348 | J4: =60%*(C4+F4) -> 393 | K4: =I4-J4 -> 284.53348 | L4: SEM DESCONTO. SEGURO (2/6). IPTU (2/5). | M4: 10 | N4: 11
A5: TOTAL | C5: =SUM(C4:C4) -> 580 | D5: =SUM(D4:D4) -> 0 | E5: =SUM(E4:E4) -> 580 | F5: =SUM(F4:F4) -> 75 | G5: =SUM(G4:G4) -> 2.8368085 | H5: =SUM(H4:H4) -> 19.696667 | I5: =SUM(I4:I4) -> 677.53348 | J5: =SUM(J4:J4) -> 393 | K5: =SUM(K4:K4) -> 284.53348
A6: VIGÊNCIA DE FEVEREIRO 2022
A7: NOME | B7: APTO | C7: ALUGUEL | D7: DESCONTO | E7: ALUGUEL C/ DESCONTO | F7: GARAGEM | G7: IPTU | H7: SEG INC. | I7: TOTAL | J7: COMISSÃO | K7: REPASSE | L7: OBSERVAÇÃO | M7: VENC. | N7: CARÊNCIA
A8: JOÃO PAULO | B8: 1 | C8: 0 | D8: =10%*C8 -> 0 | E8: =C8-D8 -> 0 | F8: 0 | G8: 0 | H8: 0 | I8: =SUM(E8:H8) -> 0 | J8: =7%*I8 -> 0 | K8: =I8-J8 -> 0 | L8: INADIMPLÊNCIA | M8: 10 | N8: 11
B9: 2 | J9: =7%*I9 -> 0
B10: 3 | J10: =7%*I10 -> 0
A11: AMANDA | B11: 4 | C11: ='GERAL 2022'!G6/28*12 -> 235.71429 | D11: 0 | E11: =C11-D11 -> 235.71429 | F11: =50/28*12 -> 21.428571 | G11: =D57/28*12 -> 1.2157751 | H11: =D56 -> 19.641667 | I11: =SUM(E11:H11) -> 278.0003 | J11: =7%*I11 -> 19.460021 | K11: =I11-J11 -> 258.54028 | L11: PROPORCIONAL DE 12 DIAS (17/02 A 28/02). IPTU (2/5). SEGUROS (1/6). | M11: 10 | N11: 11
B12: 5 | J12: =7%*I12 -> 0
B13: 6 | J13: =7%*I13 -> 0
B14: 7 | J14: =7%*I14 -> 0
A15: ARMANDO | B15: 8 | C15: ='GERAL 2022'!G10/28*25 -> 544.64286 | D15: 0 | E15: =C15-D15 -> 544.64286 | F15: 0 | G15: =D65/28*25 -> 2.5328647 | H15: =D64 -> 19.755 | I15: =SUM(E15:H15) -> 566.93072 | J15: =7%*I15 -> 39.685151 | K15: =I15-J15 -> 527.24557 | L15: PROPORCIONAL DE 25 DIAS (04/02 A 28/02). IPTU (2/5). SEGUROS (1/6). | M15: 10 | N15: 11
A16: ALCIDES / RENÊ | B16: 9 | C16: ='GERAL 2022'!G11 -> 580 | D16: 0 | E16: =C16-D16 -> 580 | F16: 755 | G16: 2.84 | H16: 0 | I16: =SUM(E16:H16) -> 1337.84 | J16: =7%*I16 -> 93.6488 | K16: =I16-J16 -> 1244.1912 | L16: INTERMEDIAÇÃO | M16: 10 | N16: 11
A17: JOÃO CARLOS | B17: 10 | C17: ='GERAL 2022'!G12 -> 600 | D17: =10%*C17 -> 60 | E17: =C17-D17 -> 540 | F17: 0 | G17: =D69 -> 2.8368085 | H17: 0 | I17: =SUM(E17:H17) -> 542.83681 | J17: =7%*I17 -> 37.998577 | K17: =I17-J17 -> 504.83823 | L17: DESCONTO 10% (10/12). SEGURO QUITADO. IPTU (2/5). | M17: 10 | N17: 11
B18: 11 | J18: =7%*I18 -> 0
B19: 12 | J19: =7%*I19 -> 0
B20: 13 | J20: =7%*I20 -> 0
B21: 14 | J21: =7%*I21 -> 0
A22: CATIANA | B22: 15 | C22: 730 | D22: 60 | E22: =(C22-D22)/28*2 -> 47.857143 | F22: =50/28*2 -> 3.5714286 | G22: =D79/28*2 -> 0.28368085 | H22: 0 | I22: =SUM(E22:H22) -> 51.712252 | J22: =7%*I22 -> 3.6198577 | K22: =I22-J22 -> 48.092395 | L22: RESCISÃO. PROPORCIONAL 02 DIAS (01/02 A 02/02). DESCONTO R$ 60,00 (7/12). SEGURO QUITADO. IPTU (2/5). | M22: 10 | N22: 11
A23: BIANCA | B23: 15 | C23: ='GERAL 2022'!G40/28*6 -> 139.28571 | D23: 0 | E23: =C23-D23 -> 139.28571 | F23: =25/28*6 -> 5.3571429 | G23: =D81/28*6 -> 0.85104255 | H23: =D80 -> 19.836667 | I23: =SUM(E23:H23) -> 165.33057 | J23: =7%*I23 -> 11.57314 | K23: =I23-J23 -> 153.75743 | L23: PROPORCIONAL DE 06 DIAS (23/02 A 28/02). IPTU (2/5). SEGUROS (1/6). | M23: 10 | N23: 11
A24: VANESSA | B24: 16 | C24: ='GERAL 2022'!G18 -> 640 | D24: =10%*C24 -> 64 | E24: =C24-D24 -> 576 | F24: =60 -> 60 | G24: =D83 -> 2.8368085 | H24: 0 | I24: =SUM(E24:H24) -> 638.83681 | J24: =7%*I24 -> 44.718577 | K24: =I24-J24 -> 594.11823 | L24: DESCONTO 10% (9/12). SEGURO QUITADO. IPTU (2/5). | M24: 10 | N24: 11
A25: MATEUS | B25: 17 | C25: ='GERAL 2022'!G19 -> 640 | D25: =10%*C25 -> 64 | E25: =(C25-D25) -> 576 | F25: 0 | G25: =D85 -> 2.8368085 | H25: 0 | I25: =SUM(E25:H25) -> 578.83681 | J25: =7%*I25 -> 40.518577 | K25: =I25-J25 -> 538.31823 | L25: DESCONTO 10% (8/12). SEGURO QUITADO. IPTU (2/5). | M25: 10 | N25: 11
A26: FREDSON | B26: 18 | C26: ='GERAL 2022'!G20 -> 650 | D26: =10%*C26 -> 65 | E26: =C26-D26 -> 585 | F26: =30 -> 30 | G26: =D87 -> 2.8368085 | H26: 0 | I26: =SUM(E26:H26) -> 617.83681 | J26: =7%*I26 -> 43.248577 | K26: =I26-J26 -> 574.58823 | L26: DESCONTO 10% (9/12). SEGURO QUITADO. IPTU (2/5). | M26: 10 | N26: 11
A27: ERIVANDO | B27: 19 | C27: ='GERAL 2022'!G21 -> 600 | D27: =10%*C27 -> 60 | E27: =(C27-D27) -> 540 | F27: =50 -> 50 | G27: =D89 -> 2.8368085 | H27: 0 | I27: =SUM(E27:H27) -> 592.83681 | J27: =7%*I27 -> 41.498577 | K27: =I27-J27 -> 551.33823 | L27: DESCONTO 10% (7/12). SEGURO QUITADO. IPTU (2/5). | M27: 10 | N27: 11
B28: 20 | J28: =7%*I28 -> 0
B29: 21 | J29: =7%*I29 -> 0
B30: 22 | J30: =7%*I30 -> 0
B31: 23 | J31: =7%*I31 -> 0
A32: JOÃO LEVI | B32: 24 | C32: ='GERAL 2022'!G26 -> 650 | D32: 0 | E32: =C32-D32 -> 650 | F32: 50 | G32: =D99 -> 3.9715319 | H32: =D98 -> 19.836667 | I32: =SUM(E32:H32) -> 723.8082 | J32: =7%*I32 -> 50.666574 | K32: =I32-J32 -> 673.14162 | L32: IPTU (2/5). SEGURO (1/6). | M32: 10 | N32: 11
A33: SHIRLEY | B33: 25 | C33: ='GERAL 2022'!G27 -> 704 | D33: =10%*C33 -> 70.4 | E33: =C33-D33 -> 633.6 | F33: =30 -> 30 | G33: =D101 -> 2.8368085 | H33: 0 | I33: =SUM(E33:H33) -> 666.43681 | J33: =7%*I33 -> 46.650577 | K33: =I33-J33 -> 619.78623 | L33: DESCONTO 10% (10/12). SEGURO QUITADO. IPTU (2/5). | M33: 10 | N33: 11
B34: 26 | J34: =7%*I34 -> 0
A35: LUIZA | B35: 27 | C35: ='GERAL 2022'!G29 -> 650 | D35: =10%*C35 -> 65 | E35: =C35-D35 -> 585 | F35: =60 -> 60 | G35: =D105 -> 2.8368085 | H35: 0 | I35: =SUM(E35:H35) -> 647.83681 | J35: =7%*I35 -> 45.348577 | K35: =I35-J35 -> 602.48823 | L35: DESCONTO 10% (10/12). SEGURO QUITADO. IPTU (2/5). | M35: 10 | N35: 11
A36: TOTAL | C36: =SUM(C8:C35) -> 7363.6429 | D36: =SUM(D8:D35) -> 508.4 | E36: =SUM(E8:E35) -> 6233.1 | F36: =SUM(F8:F35) -> 1065.3571 | G36: =SUM(G8:G35) -> 31.552555 | H36: =SUM(H8:H35) -> 79.07 | I36: =SUM(I8:I35) -> 7409.0797 | J36: =SUM(J8:J35) -> 518.63558 | K36: =SUM(K8:K35) -> 6890.4441
A38: ACORDOS/RESCISÕES RECEBIDAS EM FEVEREIRO DE 2022
A39: NOME | B39: APTO | C39: PRINCIPAL | D39: CONDIÇÃO | I39: TOTAL | J39: COMISSÃO | K39: REPASSE | L39: OBSERVAÇÃO | M39: VENC. | N39: CARÊNCIA
A40: CATIANA | B40: 15 | C40: 1608 | D40: 1X DE R$ 1.608,00 | I40: 1608 | J40: =7%*I40 -> 112.56 | K40: =I40-J40 -> 1495.44 | L40: RESCISÃO. PAGO NO DIA 02/02/2022. | M40: 10 | N40: 11
A41: JOÃO PAULO | B41: 1 | C41: 1520 | D41: 1X DE R$ 1.520,00 | I41: 1520 | J41: =7%*I41 -> 106.4 | K41: =I41-J41 -> 1413.6 | L41: CAUÇÃO PARA PAGAMENTO DE PARTE DO DÉBITO. PAGO NO DIA 19/02/2022. | M41: 10 | N41: 11
A42: TOTAL | I42: =SUM(I40:I41) -> 3128 | J42: =SUM(J40:J41) -> 218.96 | K42: =SUM(K40:K41) -> 2909.04
A44: INADIMPLÊNCIAS
A45: NOME | B45: APTO | C45: PRINCIPAL | D45: CONDIÇÃO | I45: TOTAL | L45: OBSERVAÇÃO | M45: VENC. | N45: CARÊNCIA
A46: JOÃO PAULO | B46: 1 | C46: =4977.59-1520 -> 3457.59 | D46: R$ 4.977,59 (DÉBITO TOTAL) - R$ 1.520,00 (CAUÇÃO) | I46: =4977.59-1520 -> 3457.59 | L46: DÉBITO ATUALIZADO EM 19/02/2022 (OUT/21 A FEV/22 E MULTA), DIFERENÇA APÓS UTILIZAÇÃO DA CAUÇÃO | M46: 10 | N46: 11
A47: TOTAL | I47: =SUM(I46:I46) -> 3457.59
A49: OBSERVAÇÕES | L49: COMISSÃO ADMINISTRAÇÃO
A50: SEGURO 01 | B50: ='GERAL 2022'!J3 -> 118.43 | C50: 6 | D50: =B50/C50 -> 19.738333 | L50: COMISSÃO 7% | N50: =J36+J42 -> 737.59558
A51: IPTU 01 | B51: ='GERAL 2022'!H3 -> 14.184043 | C51: 5 | D51: =B51/C51 -> 2.8368085 | L51: INTERMEDIAÇÃO 60% | N51: =J5 -> 393
A52: SEGURO 02
A53: IPTU 02
A54: SEGURO 03 | L54: OUTRAS COMISSÕES E DESPESAS
A55: IPTU 03 | L55: SEGURO APTO 04 (1/6) | N55: 19.65 | O55: ok
A56: SEGURO 04 | B56: ='GERAL 2022'!J6 -> 117.85 | C56: 6 | D56: =B56/C56 -> 19.641667 | L56: SEGURO APTO 08 (1/6) | N56: 19.78 | O56: ok
A57: IPTU 04 | B57: ='GERAL 2022'!H6 -> 14.184043 | C57: 5 | D57: =B57/C57 -> 2.8368085 | L57: SEGURO APTO 09 (2/6) | N57: 19.7
A58: SEGURO 05 | L58: SEGURO APTO 15 (1/6) | N58: 19.82 | O58: ok
A59: IPTU 05 | L59: SEGURO APTO 24 (1/6) | N59: 19.82 | O59: ok
A60: SEGURO 06 | L60: 04 LIMPEZAS (05/02/2022 - 12/02/2022 - 19/02/2022 - 26/02/2022) | N60: =120*4 -> 480
A61: IPTU 06 | L61: ENEL | N61: 134.5
A62: SEGURO 07 | L62: CAGECE | N62: 502.43
A63: IPTU 07 | L63: RECONHECIMENTO DE FIRMA APTO 04, 08, 15 E 24 | N63: =8.77*4 -> 35.08
A64: SEGURO 08 | B64: ='GERAL 2022'!J10 -> 118.53 | C64: 6 | D64: =B64/C64 -> 19.755 | L64: MATERIAL DE LIMPEZA | N64: 108.89
A65: IPTU 08 | B65: ='GERAL 2022'!H10 -> 14.184043 | C65: 5 | D65: =B65/C65 -> 2.8368085 | L65: CÓPIAS CHAVES CORREDORES | N65: 72
A66: SEGURO 09 | B66: ='GERAL 2022'!J11 -> 118.18 | C66: 6 | D66: =B66/C66 -> 19.696667 | L66: CÓPIA UMA CHAVE TETRA | N66: 20
A67: IPTU 09 | B67: ='GERAL 2022'!H11 -> 14.184043 | C67: 5 | D67: =B67/C67 -> 2.8368085
A68: SEGURO 10 | B68: ='GERAL 2022'!J12 -> 106.95 | C68: 6 | D68: =B68/C68 -> 17.825
A69: IPTU 10 | B69: ='GERAL 2022'!H12 -> 14.184043 | C69: 5 | D69: =B69/C69 -> 2.8368085
A70: SEGURO 11 | L70: TOTAL COMISSÃO + DESPESAS | N70: =SUM(N50:N69) -> 2582.2656
A71: IPTU 11
A72: SEGURO 12 | L72: R$ RECEBIDOS EM NOME DO LOCADOR
A73: IPTU 12 | L73: =I5+I36+I42 -> 11214.613
A74: SEGURO 13
A75: IPTU 13 | L75: TOTAL A REPASSAR | N75: =L73-N70 -> 8632.3476
A76: SEGURO 14
A77: IPTU 14
A78: SEGURO 15 | B78: ='GERAL 2022'!J17 -> 119.94 | C78: 6 | D78: =B78/C78 -> 19.99
A79: IPTU 15 | B79: ='GERAL 2022'!H17 -> 19.85766 | C79: 5 | D79: =B79/C79 -> 3.9715319
A80: SEGURO 15 NOVO | B80: ='GERAL 2022'!J40 -> 119.02 | C80: 6 | D80: =B80/C80 -> 19.836667
A81: IPTU 15 NOVO | B81: ='GERAL 2022'!H40 -> 19.85766 | C81: 5 | D81: =B81/C81 -> 3.9715319
A82: SEGURO 16 | B82: ='GERAL 2022'!J18 -> 118.87 | C82: 6 | D82: =B82/C82 -> 19.811667
A83: IPTU 16 | B83: ='GERAL 2022'!H18 -> 14.184043 | C83: 5 | D83: =B83/C83 -> 2.8368085
A84: SEGURO 17 | B84: ='GERAL 2022'!J19 -> 118.87 | C84: 6 | D84: =B84/C84 -> 19.811667
A85: IPTU 17 | B85: ='GERAL 2022'!H19 -> 14.184043 | C85: 5 | D85: =B85/C85 -> 2.8368085
A86: SEGURO 18 | B86: ='GERAL 2022'!J20 -> 119.02 | C86: 6 | D86: =B86/C86 -> 19.836667
A87: IPTU 18 | B87: ='GERAL 2022'!H20 -> 14.184043 | C87: 5 | D87: =B87/C87 -> 2.8368085
A88: SEGURO 19 | B88: ='GERAL 2022'!J21 -> 118.43 | C88: 6 | D88: =B88/C88 -> 19.738333
A89: IPTU 19 | B89: ='GERAL 2022'!H21 -> 14.184043 | C89: 5 | D89: =B89/C89 -> 2.8368085
A90: SEGURO 20
A91: IPTU 20
A92: SEGURO 21
A93: IPTU 21
A94: SEGURO 22
A95: IPTU 22
A96: SEGURO 23
A97: IPTU 23
A98: SEGURO 24 | B98: ='GERAL 2022'!J26 -> 119.02 | C98: 6 | D98: =B98/C98 -> 19.836667
A99: IPTU 24 | B99: ='GERAL 2022'!H26 -> 19.85766 | C99: 5 | D99: =B99/C99 -> 3.9715319
A100: SEGURO 25 | B100: ='GERAL 2022'!J27 -> 119.7 | C100: 6 | D100: =B100/C100 -> 19.95
A101: IPTU 25 | B101: ='GERAL 2022'!H27 -> 14.184043 | C101: 5 | D101: =B101/C101 -> 2.8368085
A102: SEGURO 26
A103: IPTU 26
...

Sheet VIGÊNCIA MARÇO 2022
A1: GRAND MESSEJANA II
A2: INTERMEDIAÇÃO DE FEVEREIRO DE 2022
A3: NOME | B3: APTO | C3: ALUGUEL | D3: DESCONTO | E3: ALUGUEL C/ DESCONTO | F3: GARAGEM | G3: IPTU | H3: SEG INC. | I3: TOTAL | J3: COMISSÃO | K3: REPASSE | L3: OBSERVAÇÃO | M3: VENC. | N3: CARÊNCIA
A4: AMANDA | B4: 4 | C4: ='GERAL 2022'!G6 -> 550 | D4: 0 | E4: =C4-D4 -> 550 | F4: 50 | G4: =D68 -> 2.8368085 | H4: 19.64 | I4: =SUM(E4:H4) -> 622.47681 | J4: =60%*(C4+F4) -> 360 | K4: =I4-J4 -> 262.47681 | L4: SEM DESCONTO. IPTU (3/5). SEGUROS (2/6). | M4: 10 | N4: 11
A5: ARMANDO | B5: 8 | C5: ='GERAL 2022'!G10 -> 610 | D5: 0 | E5: =C5-D5 -> 610 | F5: 0 | G5: 2.84 | H5: 19.76 | I5: =SUM(E5:H5) -> 632.6 | J5: =60%*(C5+F5) -> 366 | K5: =I5-J5 -> 266.6 | L5: SEM DESCONTO. IPTU (3/5). SEGUROS (2/6).
A6: BIANCA | B6: 15 | C6: ='GERAL 2022'!G40 -> 650 | D6: 0 | E6: =C6-D6 -> 650 | F6: 25 | G6: 3.97 | H6: 19.84 | I6: =SUM(E6:H6) -> 698.81 | J6: =60%*(C6+F6) -> 405 | K6: =I6-J6 -> 293.81 | L6: SEM DESCONTO. IPTU (3/5). SEGUROS (2/6).
A7: JOÃO LEVI | B7: 24 | C7: ='GERAL 2022'!G26 -> 650 | D7: 0 | E7: =C7-D7 -> 650 | F7: 50 | G7: 3.97 | H7: 19.84 | I7: =SUM(E7:H7) -> 723.81 | J7: =60%*(C7+F7) -> 420 | K7: =I7-J7 -> 303.81 | L7: SEM DESCONTO. IPTU (3/5). SEGUROS (2/6).
A8: TOTAL | C8: =SUM(C4:C7) -> 2460 | D8: =SUM(D4:D7) -> 0 | E8: =SUM(E4:E7) -> 2460 | F8: =SUM(F4:F7) -> 125 | G8: =SUM(G4:G7) -> 13.616809 | H8: =SUM(H4:H7) -> 79.08 | I8: =SUM(I4:I7) -> 2677.6968 | J8: =SUM(J4:J7) -> 1551 | K8: =SUM(K4:K7) -> 1126.6968
A9: VIGÊNCIA DE MARÇO 2022
A10: NOME | B10: APTO | C10: ALUGUEL | D10: DESCONTO | E10: ALUGUEL C/ DESCONTO | F10: GARAGEM | G10: IPTU | H10: SEG INC. | I10: TOTAL | J10: COMISSÃO | K10: REPASSE | L10: OBSERVAÇÃO | M10: VENC. | N10: CARÊNCIA
B11: 1
B12: 2 | J12: =7%*I12 -> 0
B13: 3 | J13: =7%*I13 -> 0
A14: AMANDA | B14: 4 | C14: 0 | D14: 0 | E14: =C14-D14 -> 0 | F14: 0 | G14: 0 | H14: 0 | I14: =SUM(E14:H14) -> 0 | J14: =7%*I14 -> 0 | K14: =I14-J14 -> 0 | L14: INTERMEDIAÇÃO | M14: 10 | N14: 11
B15: 5 | J15: =7%*I15 -> 0
A16: LIGIA | B16: 6 | C16: ='GERAL 2022'!G8/31*15 -> 314.51613 | D16: 0 | E16: =C16-D16 -> 314.51613 | F16: =25/31*15 -> 12.096774 | G16: =D62/31*15 -> 1.921709 | H16: =D61 -> 19.836667 | I16: =SUM(E16:H16) -> 348.37128 | J16: =7%*I16 -> 24.38599 | K16: =I16-J16 -> 323.98529 | L16: PROPORCIONAL DE 15 DIAS (17/03 A 31/03). IPTU (1/5). SEGUROS (1/6). | M16: 10 | N16: 11
B17: 7 | I17: 0 | J17: =7%*I17 -> 0
A18: ARMANDO | B18: 8 | C18: 0 | D18: 0 | E18: =C18-D18 -> 0 | F18: 0 | G18: 0 | H18: 0 | I18: =SUM(E18:H18) -> 0 | J18: =7%*I18 -> 0 | K18: =I18-J18 -> 0 | L18: INTERMEDIAÇÃO | M18: 10 | N18: 11
A19: ALCIDES / RENÊ | B19: 9 | C19: ='GERAL 2022'!G11 -> 580 | D19: 0 | E19: =C19-D19 -> 580 | F19: =50+(25/31*15) -> 62.096774 | G19: 2.84 | H19: 19.7 | I19: =SUM(E19:H19) -> 664.63677 | J19: =7%*I19 -> 46.524574 | K19: =I19-J19 -> 618.1122 | L19: RESCISÃO DE UMA VAGA DE MOTO DIA 17/03 (PROPORCIONAL DE 15 DIAS). SEM DESCONTO. SEGURO (3/6). IPTU (3/5). | M19: 10 | N19: 11
A20: JOÃO CARLOS | B20: 10 | C20: ='GERAL 2022'!G12 -> 600 | D20: =10%*C20 -> 60 | E20: =C20-D20 -> 540 | F20: 0 | G20: =D70 -> 2.8368085 | H20: 0 | I20: =SUM(E20:H20) -> 542.83681 | J20: =7%*I20 -> 37.998577 | K20: =I20-J20 -> 504.83823 | L20: DESCONTO 10% (10/12). SEGURO QUITADO. IPTU (2/5). | M20: 10 | N20: 11
B21: 11 | J21: =7%*I21 -> 0
B22: 12 | J22: =7%*I22 -> 0
B23: 13 | J23: =7%*I23 -> 0
A24: HOSANA | B24: 14 | C24: ='GERAL 2022'!G16/31*8 -> 141.93548 | D24: 0 | E24: =C24-D24 -> 141.93548 | F24: 0 | G24: =D78/31*8 -> 0.73207962 | H24: =D77 -> 19.641667 | I24: =SUM(E24:H24) -> 162.30923 | J24: =7%*I24 -> 11.361646 | K24: =I24-J24 -> 150.94758 | L24: PROPORCIONAL DE 8 DIAS (24/03 A 31/03). IPTU (1/5). SEGUROS (1/6). | M24: 10 | N24: 11
A25: BIANCA | B25: 15 | C25: 0 | D25: 0 | E25: =C25-D25 -> 0 | F25: 0 | G25: 0 | H25: 0 | I25: =SUM(E25:H25) -> 0 | J25: =7%*I25 -> 0 | K25: =I25-J25 -> 0 | L25: INTERMEDIAÇÃO | M25: 10 | N25: 11
A26: VANESSA | B26: 16 | C26: ='GERAL 2022'!G18 -> 640 | D26: =10%*C26 -> 64 | E26: =C26-D26 -> 576 | F26: =60 -> 60 | G26: =D84 -> 2.8368085 | H26: 0 | I26: =SUM(E26:H26) -> 638.83681 | J26: =7%*I26 -> 44.718577 | K26: =I26-J26 -> 594.11823 | L26: DESCONTO 10% (10/12). SEGURO QUITADO. IPTU (3/5). | M26: 10 | N26: 11
A27: MATEUS LEVI | B27: 17 | C27: ='GERAL 2022'!G19 -> 640 | D27: =10%*C27 -> 64 | E27: =(C27-D27) -> 576 | F27: 0 | G27: =D86 -> 2.8368085 | H27: 0 | I27: =SUM(E27:H27) -> 578.83681 | J27: =7%*I27 -> 40.518577 | K27: =I27-J27 -> 538.31823 | L27: DESCONTO 10% (9/12). SEGURO QUITADO. IPTU (3/5). | M27: 10 | N27: 11
A28: FREDSON | B28: 18 | C28: ='GERAL 2022'!G20 -> 650 | D28: =10%*C28 -> 65 | E28: =C28-D28 -> 585 | F28: =30 -> 30 | G28: =D88 -> 2.8368085 | H28: 0 | I28: =SUM(E28:H28) -> 617.83681 | J28: =7%*I28 -> 43.248577 | K28: =I28-J28 -> 574.58823 | L28: DESCONTO 10% (10/12). SEGURO QUITADO. IPTU (3/5). | M28: 10 | N28: 11
A29: ERIVANDO | B29: 19 | C29: ='GERAL 2022'!G21 -> 600 | D29: =10%*C29 -> 60 | E29: =(C29-D29) -> 540 | F29: =50 -> 50 | G29: =D90 -> 2.8368085 | H29: 0 | I29: =SUM(E29:H29) -> 592.83681 | J29: =7%*I29 -> 41.498577 | K29: =I29-J29 -> 551.33823 | L29: DESCONTO 10% (8/12). SEGURO QUITADO. IPTU (3/5). | M29: 10 | N29: 11
B30: 20 | J30: =7%*I30 -> 0
B31: 21 | J31: =7%*I31 -> 0
B32: 22 | J32: =7%*I32 -> 0
B33: 23 | J33: =7%*I33 -> 0
A34: JOÃO LEVI | B34: 24 | C34: 0 | D34: 0 | E34: =C34-D34 -> 0 | F34: 0 | G34: 0 | H34: 0 | I34: =SUM(E34:H34) -> 0 | J34: =7%*I34 -> 0 | K34: =I34-J34 -> 0 | L34: INTERMEDIAÇÃO | M34: 10 | N34: 11
A35: SHIRLEY | B35: 25 | C35: ='GERAL 2022'!G27 -> 704 | D35: =10%*C35 -> 70.4 | E35: =C35-D35 -> 633.6 | F35: =30 -> 30 | G35: =D102 -> 2.8368085 | H35: 0 | I35: =SUM(E35:H35) -> 666.43681 | J35: =7%*I35 -> 46.650577 | K35: =I35-J35 -> 619.78623 | L35: DESCONTO 10% (11/12). SEGURO QUITADO. IPTU (2/5). | M35: 10 | N35: 11
B36: 26 | J36: =7%*I36 -> 0
A37: LUIZA | B37: 27 | C37: ='GERAL 2022'!G29/31*29 -> 608.06452 | D37: =10%*C37 -> 60.806452 | E37: =C37-D37 -> 547.25806 | F37: =60/31*29 -> 56.129032 | G37: =D106/31*29 -> 2.6537886 | H37: 0 | I37: =SUM(E37:H37) -> 606.04089 | J37: =7%*I37 -> 42.422862 | K37: =I37-J37 -> 563.61802 | L37: RESCISÃO. PROPORCIONAL DE 01/03 A 29/03. DESCONTO 10% (11/12). SEGURO QUITADO. IPTU (3/5). | M37: 10 | N37: 11
A38: TOTAL | C38: =SUM(C11:C37) -> 5478.5161 | D38: =SUM(D11:D37) -> 444.20645 | E38: =SUM(E11:E37) -> 5034.3097 | F38: =SUM(F11:F37) -> 300.32258 | G38: =SUM(G11:G37) -> 25.168428 | H38: =SUM(H11:H37) -> 59.178333 | I38: =SUM(I11:I37) -> 5418.979 | J38: =SUM(J11:J37) -> 379.32853 | K38: =SUM(K11:K37) -> 5039.6505
A40: ACORDOS/RESCISÕES RECEBIDAS EM MARÇO DE 2022
A41: NOME | B41: APTO | C41: PRINCIPAL | D41: CONDIÇÃO | I41: TOTAL | J41: COMISSÃO | K41: REPASSE | L41: OBSERVAÇÃO | M41: VENC. | N41: CARÊNCIA
A42: LUIZA | B42: 27 | C42: 1111.5 | D42: 1x R$ 1.111,50 | I42: 1111.5 | J42: =7%*I42 -> 77.805 | K42: =I42-J42 -> 1033.695 | L42: MULTA POR RESCISÃO ANTES DO PRAZO. PAGO DIA 29/03/2022. | M42: 10 | N42: 11
A43: TOTAL | I43: =SUM(I42) -> 1111.5 | J43: =SUM(J42) -> 77.805 | K43: =SUM(K42) -> 1033.695
A45: INADIMPLÊNCIAS
A46: NOME | B46: APTO | C46: PRINCIPAL | D46: CONDIÇÃO | I46: TOTAL | L46: OBSERVAÇÃO | M46: VENC. | N46: CARÊNCIA
A47: JOÃO PAULO | B47: 1 | C47: =4977.59-1520 -> 3457.59 | D47: R$ 4.977,59 (DÉBITO TOTAL) - R$ 1.520,00 (CAUÇÃO) | I47: =4977.59-1520 -> 3457.59 | L47: DÉBITO ATUALIZADO EM 19/02/2022 (OUT/21 A FEV/22 E MULTA), DIFERENÇA APÓS UTILIZAÇÃO DA CAUÇÃO | M47: 10 | N47: 11
A48: TOTAL | I48: =SUM(I47:I47) -> 3457.59
A50: OBSERVAÇÕES | L50: COMISSÕES
A51: SEGURO 01 | B51: ='GERAL 2022'!J3 -> 118.43 | C51: 6 | D51: =B51/C51 -> 19.738333 | L51: COMISSÃO 7% | N51: =J38+J43 -> 457.13353
A52: IPTU 01 | B52: ='GERAL 2022'!H3 -> 14.184043 | C52: 5 | D52: =B52/C52 -> 2.8368085 | L52: INTERMEDIAÇÃO 60% | N52: =J8 -> 1551
A53: SEGURO 02
A54: IPTU 02
A55: SEGURO 03 | L55: OUTRAS COMISSÕES E DESPESAS
A56: IPTU 03 | L56: SEGURO APTO 04 (2/6) | N56: 19.64
A57: SEGURO 04 | B57: ='GERAL 2022'!J6 -> 117.85 | C57: 6 | D57: =B57/C57 -> 19.641667 | L57: SEGURO APTO 06 (1/6) | N57: 19.82
A58: IPTU 04 | B58: ='GERAL 2022'!H6 -> 14.184043 | C58: 5 | D58: =B58/C58 -> 2.8368085 | L58: SEGURO APTO 08 (2/6) | N58: 19.76
A59: SEGURO 05 | L59: SEGURO APTO 09 (3/6) | N59: 19.7
A60: IPTU 05 | L60: SEGURO APTO 14 (1/6) | N60: 19.65
A61: SEGURO 06 | B61: ='GERAL 2022'!J8 -> 119.02 | C61: 6 | D61: =B61/C61 -> 19.836667 | L61: SEGURO APTO 15 (2/6) | N61: 19.84
A62: IPTU 06 | B62: ='GERAL 2022'!H8 -> 19.85766 | C62: 5 | D62: =B62/C62 -> 3.9715319 | L62: SEGURO APTO 24 (2/6) | N62: 19.84
A63: SEGURO 07 | L63: 04 LIMPEZAS (05/03/2022 - 12/03/2022 - 19/03/2022 - 26/03/2022) | N63: =120*4 -> 480
A64: IPTU 07 | L64: RECONHECIMENTOS DE FIRMA CONTRATOS APTO 06 E 14 | N64: =8.77*2 -> 17.54
A65: SEGURO 08 | B65: ='GERAL 2022'!J10 -> 118.53 | C65: 6 | D65: =B65/C65 -> 19.755 | L65: ENEL | N65: 138.6
A66: IPTU 08 | B66: ='GERAL 2022'!H10 -> 14.184043 | C66: 5 | D66: =B66/C66 -> 2.8368085 | L66: CAGECE (SEM FATURA)
A67: SEGURO 09 | B67: ='GERAL 2022'!J11 -> 118.18 | C67: 6 | D67: =B67/C67 -> 19.696667
A68: IPTU 09 | B68: ='GERAL 2022'!H11 -> 14.184043 | C68: 5 | D68: =B68/C68 -> 2.8368085
A69: SEGURO 10 | B69: ='GERAL 2022'!J12 -> 106.95 | C69: 6 | D69: =B69/C69 -> 17.825
A70: IPTU 10 | B70: ='GERAL 2022'!H12 -> 14.184043 | C70: 5 | D70: =B70/C70 -> 2.8368085
A71: SEGURO 11
A72: IPTU 11
A73: SEGURO 12
A74: IPTU 12 | L74: TOTAL COMISSÃO + DESPESAS | N74: =SUM(N51:N73) -> 2782.5235
A75: SEGURO 13
A76: IPTU 13 | L76: R$ RECEBIDOS EM NOME DO LOCADOR | N76: =I8+I38+I43 -> 9208.1758
A77: SEGURO 14 | B77: ='GERAL 2022'!J16 -> 117.85 | C77: 6 | D77: =B77/C77 -> 19.641667 | L77: ERRO APTO 15 NA VIGÊNCIA DE MARÇO | N77: 22.56
A78: IPTU 14 | B78: ='GERAL 2022'!H16 -> 14.184043 | C78: 5 | D78: =B78/C78 -> 2.8368085 | L78: TOTAL | N78: =N76+N77 -> 9230.7358
A79: SEGURO 15 | B79: ='GERAL 2022'!J17 -> 119.94 | C79: 6 | D79: =B79/C79 -> 19.99
A80: IPTU 15 | B80: ='GERAL 2022'!H17 -> 19.85766 | C80: 5 | D80: =B80/C80 -> 3.9715319 | L80: TOTAL A REPASSAR | N80: =N78-N74 -> 6448.2123
A81: SEGURO 15 NOVO | B81: ='GERAL 2022'!J40 -> 119.02 | C81: 6 | D81: =B81/C81 -> 19.836667
A82: IPTU 15 NOVO | B82: ='GERAL 2022'!H40 -> 19.85766 | C82: 5 | D82: =B82/C82 -> 3.9715319
A83: SEGURO 16 | B83: ='GERAL 2022'!J18 -> 118.87 | C83: 6 | D83: =B83/C83 -> 19.811667
A84: IPTU 16 | B84: ='GERAL 2022'!H18 -> 14.184043 | C84: 5 | D84: =B84/C84 -> 2.8368085
A85: SEGURO 17 | B85: ='GERAL 2022'!J19 -> 118.87 | C85: 6 | D85: =B85/C85 -> 19.811667
A86: IPTU 17 | B86: ='GERAL 2022'!H19 -> 14.184043 | C86: 5 | D86: =B86/C86 -> 2.8368085
A87: SEGURO 18 | B87: ='GERAL 2022'!J20 -> 119.02 | C87: 6 | D87: =B87/C87 -> 19.836667
A88: IPTU 18 | B88: ='GERAL 2022'!H20 -> 14.184043 | C88: 5 | D88: =B88/C88 -> 2.8368085
A89: SEGURO 19 | B89: ='GERAL 2022'!J21 -> 118.43 | C89: 6 | D89: =B89/C89 -> 19.738333
A90: IPTU 19 | B90: ='GERAL 2022'!H21 -> 14.184043 | C90: 5 | D90: =B90/C90 -> 2.8368085
A91: SEGURO 20
A92: IPTU 20
A93: SEGURO 21
A94: IPTU 21
A95: SEGURO 22
A96: IPTU 22
A97: SEGURO 23
A98: IPTU 23
A99: SEGURO 24 | B99: ='GERAL 2022'!J26 -> 119.02 | C99: 6 | D99: =B99/C99 -> 19.836667
A100: IPTU 24 | B100: ='GERAL 2022'!H26 -> 19.85766 | C100: 5 | D100: =B100/C100 -> 3.9715319
A101: SEGURO 25 | B101: ='GERAL 2022'!J27 -> 119.7 | C101: 6 | D101: =B101/C101 -> 19.95
A102: IPTU 25 | B102: ='GERAL 2022'!H27 -> 14.184043 | C102: 5 | D102: =B102/C102 -> 2.8368085
A103: SEGURO 26
...

Sheet VIGÊNCIA ABRIL 2022
A1: GRAND MESSEJANA II
A2: INTERMEDIAÇÃO DE MARÇO DE 2022
A3: NOME | B3: APTO | C3: ALUGUEL | D3: DESCONTO | E3: ALUGUEL C/ DESCONTO | F3: GARAGEM | G3: IPTU | H3: SEG INC. | I3: TOTAL | J3: COMISSÃO | K3: REPASSE | L3: OBSERVAÇÃO | M3: VENC. | N3: CARÊNCIA
A4: LIGIA | B4: 6 | C4: ='GERAL 2022'!G8 -> 650 | D4: 0 | E4: =C4-D4 -> 650 | F4: =25 -> 25 | G4: =D55 -> 3.9715319 | H4: =D54 -> 19.836667 | I4: =SUM(E4:H4) -> 698.8082 | J4: =60%*(C4+F4) -> 405 | K4: =I4-J4 -> 293.8082 | L4: SEM DESCONTO. IPTU (2/5). SEGURO (2/6). | M4: 10 | N4: 11
A5: HOSANA | B5: 14 | C5: ='GERAL 2022'!G16 -> 550 | D5: 0 | E5: =C5-D5 -> 550 | F5: 0 | G5: =D71 -> 2.8368085 | H5: =D70 -> 19.641667 | I5: =SUM(E5:H5) -> 572.47848 | J5: =60%*(C5+F5) -> 330 | K5: =I5-J5 -> 242.47848 | L5: SEM DESCONTO. IPTU (2/5). SEGUROS (2/6). | M5: 10 | N5: 11
A6: TOTAL | C6: =SUM(C4:C5) -> 1200 | D6: =SUM(D4:D5) -> 0 | E6: =SUM(E4:E5) -> 1200 | F6: =SUM(F4:F5) -> 25 | G6: =SUM(G4:G5) -> 6.8083404 | H6: =SUM(H4:H5) -> 39.478333 | I6: =SUM(I4:I5) -> 1271.2867 | J6: =SUM(J4:J5) -> 735 | K6: =SUM(K4:K5) -> 536.28667
A7: VIGÊNCIA DE ABRIL 2022
A8: NOME | B8: APTO | C8: ALUGUEL | D8: DESCONTO | E8: ALUGUEL C/ DESCONTO | F8: GARAGEM | G8: IPTU | H8: SEG INC. | I8: TOTAL | J8: COMISSÃO | K8: REPASSE | L8: OBSERVAÇÃO | M8: VENC. | N8: CARÊNCIA
B9: 1
B10: 2 | J10: =7%*I10 -> 0
B11: 3 | J11: =7%*I11 -> 0
A12: AMANDA | B12: 4 | C12: ='GERAL 2022'!G16 -> 550 | D12: 0 | E12: =C12-D12 -> 550 | F12: 50 | G12: =D51 -> 2.8368085 | H12: =D50 -> 19.641667 | I12: =SUM(E12:H12) -> 622.47848 | J12: =7%*I12 -> 43.573493 | K12: =I12-J12 -> 578.90498 | L12: SEM DESCONTO. IPTU (4/5). SEGUROS (3/6). | M12: 10 | N12: 11
B13: 5 | J13: =7%*I13 -> 0
A14: LIGIA | B14: 6 | C14: 0 | D14: 0 | E14: =C14-D14 -> 0 | F14: 0 | G14: 0 | H14: 0 | I14: =SUM(E14:H14) -> 0 | J14: =7%*I14 -> 0 | K14: =I14-J14 -> 0 | L14: INTERMEDIAÇÃO | M14: 10 | N14: 11
B15: 7 | I15: 0 | J15: =7%*I15 -> 0
A16: ARMANDO | B16: 8 | C16: ='GERAL 2022'!G10 -> 610 | D16: 0 | E16: =C16-D16 -> 610 | F16: 0 | G16: =D59 -> 2.8368085 | H16: =D58 -> 19.755 | I16: =SUM(E16:H16) -> 632.59181 | J16: =7%*I16 -> 44.281427 | K16: =I16-J16 -> 588.31038 | L16: SEM DESCONTO. IPTU (4/5). SEGUROS (3/6). | M16: 10 | N16: 11
A17: ALCIDES / RENÊ | B17: 9 | C17: ='GERAL 2022'!G11 -> 580 | D17: 0 | E17: =C17-D17 -> 580 | F17: =50 -> 50 | G17: =D61 -> 2.8368085 | H17: =D60 -> 19.696667 | I17: =SUM(E17:H17) -> 652.53348 | J17: =7%*I17 -> 45.677343 | K17: =I17-J17 -> 606.85613 | L17: SEM DESCONTO. SEGURO (4/6). IPTU (4/5). | M17: 10 | N17: 11
B18: 10
A19: JOCÉLIO | B19: 11 | C19: ='GERAL 2022'!G13 -> 550 | D19: 0 | E19: =C19-D19 -> 550 | F19: 0 | G19: =D65 -> 2.8368085 | H19: =D64 -> 19.641667 | I19: =SUM(E19:H19) -> 572.47848 | J19: =7%*I19 -> 40.073493 | K19: =I19-J19 -> 532.40498 | L19: SEM DESCONTO. IPTU (1/5). SEGURO (1/6). | M19: 10 | N19: 11
B20: 12 | J20: =7%*I20 -> 0
B21: 13 | J21: =7%*I21 -> 0
A22: HOSANA | B22: 14 | C22: 0 | D22: 0 | E22: =C22-D22 -> 0 | F22: 0 | G22: 0 | H22: 0 | I22: =SUM(E22:H22) -> 0 | J22: =7%*I22 -> 0 | K22: =I22-J22 -> 0 | L22: INTERMEDIAÇÃO | M22: 10 | N22: 11
A23: BIANCA | B23: 15 | C23: ='GERAL 2022'!G40 -> 650 | D23: 0 | E23: =C23-D23 -> 650 | F23: 25 | G23: =D73 -> 3.9715319 | H23: =D72 -> 19.836667 | I23: =SUM(E23:H23) -> 698.8082 | J23: =7%*I23 -> 48.916574 | K23: =I23-J23 -> 649.89162 | L23: SEM DESCONTO. IPTU (4/5). SEGUROS (3/6).
A24: VANESSA | B24: 16 | C24: ='GERAL 2022'!G18 -> 640 | D24: =10%*C24 -> 64 | E24: =C24-D24 -> 576 | F24: =60 -> 60 | G24: =D77 -> 2.8368085 | H24: 0 | I24: =SUM(E24:H24) -> 638.83681 | J24: =7%*I24 -> 44.718577 | K24: =I24-J24 -> 594.11823 | L24: DESCONTO 10% (11/12). SEGURO QUITADO. IPTU (4/5). | M24: 10 | N24: 11
A25: MATEUS LEVI | B25: 17 | C25: ='GERAL 2022'!G19 -> 640 | D25: =10%*C25 -> 64 | E25: =(C25-D25) -> 576 | F25: 0 | G25: =D79 -> 2.8368085 | H25: 0 | I25: =SUM(E25:H25) -> 578.83681 | J25: =7%*I25 -> 40.518577 | K25: =I25-J25 -> 538.31823 | L25: DESCONTO 10% (10/12). SEGURO QUITADO. IPTU (4/5). | M25: 10 | N25: 11
A26: FREDSON | B26: 18 | C26: ='GERAL 2022'!G20 -> 650 | D26: =10%*C26 -> 65 | E26: =C26-D26 -> 585 | F26: =30 -> 30 | G26: =D81 -> 2.8368085 | H26: 0 | I26: =SUM(E26:H26) -> 617.83681 | J26: =7%*I26 -> 43.248577 | K26: =I26-J26 -> 574.58823 | L26: DESCONTO 10% (11/12). SEGURO QUITADO. IPTU (4/5). | M26: 10 | N26: 11
A27: ERIVANDO | B27: 19 | C27: ='GERAL 2022'!G21 -> 600 | D27: =10%*C27 -> 60 | E27: =(C27-D27) -> 540 | F27: =50 -> 50 | G27: =D83 -> 2.8368085 | H27: 0 | I27: =SUM(E27:H27) -> 592.83681 | J27: =7%*I27 -> 41.498577 | K27: =I27-J27 -> 551.33823 | L27: DESCONTO 10% (9/12). SEGURO QUITADO. IPTU (4/5). | M27: 10 | N27: 11
B28: 20 | J28: =7%*I28 -> 0
B29: 21 | J29: =7%*I29 -> 0
B30: 22 | J30: =7%*I30 -> 0
B31: 23 | J31: =7%*I31 -> 0
A32: JOÃO LEVI | B32: 24 | C32: ='GERAL 2022'!G26 -> 650 | D32: 0 | E32: =C32-D32 -> 650 | F32: 50 | G32: =D93 -> 3.9715319 | H32: =D92 -> 19.836667 | I32: =SUM(E32:H32) -> 723.8082 | J32: =7%*I32 -> 50.666574 | K32: =I32-J32 -> 673.14162 | L32: SEM DESCONTO. IPTU (4/5). SEGUROS (3/6).
A33: SHIRLEY | B33: 25 | C33: ='GERAL 2022'!G27 -> 704 | D33: =10%*C33 -> 70.4 | E33: =C33-D33 -> 633.6 | F33: =30 -> 30 | G33: =D95 -> 2.8368085 | H33: 0 | I33: =SUM(E33:H33) -> 666.43681 | J33: =7%*I33 -> 46.650577 | K33: =I33-J33 -> 619.78623 | L33: DESCONTO 10% (12/12). SEGURO QUITADO. IPTU (4/5). | M33: 10 | N33: 11
B34: 26 | J34: =7%*I34 -> 0
B35: 27
A36: TOTAL | C36: =SUM(C9:C35) -> 6824 | D36: =SUM(D9:D35) -> 323.4 | E36: =SUM(E9:E35) -> 6500.6 | F36: =SUM(F9:F35) -> 345 | G36: =SUM(G9:G35) -> 33.47434 | H36: =SUM(H9:H35) -> 118.40833 | I36: =SUM(I9:I35) -> 6997.4827 | J36: =SUM(J9:J35) -> 489.82379 | K36: =SUM(K9:K35) -> 6507.6589
A38: INADIMPLÊNCIAS
A39: NOME | B39: APTO | C39: PRINCIPAL | D39: CONDIÇÃO | I39: TOTAL | L39: OBSERVAÇÃO | M39: VENC. | N39: CARÊNCIA
A40: JOÃO PAULO | B40: 1 | C40: =4977.59-1520 -> 3457.59 | D40: R$ 4.977,59 (DÉBITO TOTAL) - R$ 1.520,00 (CAUÇÃO) | I40: =4977.59-1520 -> 3457.59 | L40: DÉBITO ATUALIZADO EM 19/02/2022 (OUT/21 A FEV/22 E MULTA), DIFERENÇA APÓS UTILIZAÇÃO DA CAUÇÃO | M40: 10 | N40: 11
A41: TOTAL | I41: =SUM(I40:I40) -> 3457.59
A43: OBSERVAÇÕES | L43: COMISSÕES
A44: SEGURO 01 | B44: ='GERAL 2022'!J3 -> 118.43 | C44: 6 | D44: =B44/C44 -> 19.738333 | L44: COMISSÃO 7% | N44: =J36 -> 489.82379
A45: IPTU 01 | B45: ='GERAL 2022'!H3 -> 14.184043 | C45: 5 | D45: =B45/C45 -> 2.8368085 | L45: INTERMEDIAÇÃO 60% | N45: =J6 -> 735
A46: SEGURO 02
A47: IPTU 02
A48: SEGURO 03 | L48: OUTRAS COMISSÕES E DESPESAS
A49: IPTU 03 | L49: SEGURO APTO 04 (3/6) | N49: 19.64
A50: SEGURO 04 | B50: ='GERAL 2022'!J6 -> 117.85 | C50: 6 | D50: =B50/C50 -> 19.641667 | L50: SEGURO APTO 06 (2/6) | N50: 19.84
A51: IPTU 04 | B51: ='GERAL 2022'!H6 -> 14.184043 | C51: 5 | D51: =B51/C51 -> 2.8368085 | L51: SEGURO APTO 08 (3/6) | N51: 19.76
A52: SEGURO 05 | L52: SEGURO APTO 09 (4/6) | N52: 19.7
A53: IPTU 05 | L53: SEGURO APTO 11 (1/6) | N53: 19.65
A54: SEGURO 06 | B54: ='GERAL 2022'!J8 -> 119.02 | C54: 6 | D54: =B54/C54 -> 19.836667 | L54: SEGURO APTO 14 (2/6) | N54: 19.64
A55: IPTU 06 | B55: ='GERAL 2022'!H8 -> 19.85766 | C55: 5 | D55: =B55/C55 -> 3.9715319 | L55: SEGURO APTO 15 (3/6) | N55: 19.84
A56: SEGURO 07 | L56: SEGURO APTO 24 (3/6) | N56: 19.84
A57: IPTU 07 | L57: 05 LIMPEZAS (02/04/2022 - 09/04/2022 - 16/04/2022 - 23/04/2022 - 30/04/2022) | N57: =120*5 -> 600
A58: SEGURO 08 | B58: ='GERAL 2022'!J10 -> 118.53 | C58: 6 | D58: =B58/C58 -> 19.755 | L58: RECONHECIMENTOS DE FIRMA CONTRATO APTO 11 | N58: =8.77 -> 8.77
A59: IPTU 08 | B59: ='GERAL 2022'!H10 -> 14.184043 | C59: 5 | D59: =B59/C59 -> 2.8368085 | L59: ENEL | N59: 148.87
A60: SEGURO 09 | B60: ='GERAL 2022'!J11 -> 118.18 | C60: 6 | D60: =B60/C60 -> 19.696667 | L60: CAGECE | N60: 192.8
A61: IPTU 09 | B61: ='GERAL 2022'!H11 -> 14.184043 | C61: 5 | D61: =B61/C61 -> 2.8368085 | L61: MATERIAL DE LIMPEZA | N61: 53.55
A62: SEGURO 10 | B62: ='GERAL 2022'!J12 -> 106.95 | C62: 6 | D62: =B62/C62 -> 17.825
A63: IPTU 10 | B63: ='GERAL 2022'!H12 -> 14.184043 | C63: 5 | D63: =B63/C63 -> 2.8368085
A64: SEGURO 11 | B64: ='GERAL 2022'!J13 -> 117.85 | C64: 6 | D64: =B64/C64 -> 19.641667
A65: IPTU 11 | B65: ='GERAL 2022'!H13 -> 14.184043 | C65: 5 | D65: =B65/C65 -> 2.8368085
A66: SEGURO 12
A67: IPTU 12
A68: SEGURO 13 | L68: TOTAL COMISSÃO + DESPESAS | N68: =SUM(N44:N67) -> 2386.7238
A69: IPTU 13
A70: SEGURO 14 | B70: ='GERAL 2022'!J16 -> 117.85 | C70: 6 | D70: =B70/C70 -> 19.641667 | L70: R$ RECEBIDOS EM NOME DO LOCADOR | N70: =I6+I36 -> 8268.7693
A71: IPTU 14 | B71: ='GERAL 2022'!H16 -> 14.184043 | C71: 5 | D71: =B71/C71 -> 2.8368085
A72: SEGURO 15 | B72: ='GERAL 2022'!J40 -> 119.02 | C72: 6 | D72: =B72/C72 -> 19.836667 | L72: TOTAL A REPASSAR | N72: =N70-N68 -> 5882.0456
A73: IPTU 15 | B73: ='GERAL 2022'!H17 -> 19.85766 | C73: 5 | D73: =B73/C73 -> 3.9715319
A74: SEGURO 15 NOVO | B74: ='GERAL 2022'!J40 -> 119.02 | C74: 6 | D74: =B74/C74 -> 19.836667
A75: IPTU 15 NOVO | B75: ='GERAL 2022'!H40 -> 19.85766 | C75: 5 | D75: =B75/C75 -> 3.9715319
A76: SEGURO 16 | B76: ='GERAL 2022'!J18 -> 118.87 | C76: 6 | D76: =B76/C76 -> 19.811667
A77: IPTU 16 | B77: ='GERAL 2022'!H18 -> 14.184043 | C77: 5 | D77: =B77/C77 -> 2.8368085
A78: SEGURO 17 | B78: ='GERAL 2022'!J19 -> 118.87 | C78: 6 | D78: =B78/C78 -> 19.811667
A79: IPTU 17 | B79: ='GERAL 2022'!H19 -> 14.184043 | C79: 5 | D79: =B79/C79 -> 2.8368085
A80: SEGURO 18 | B80: ='GERAL 2022'!J20 -> 119.02 | C80: 6 | D80: =B80/C80 -> 19.836667
A81: IPTU 18 | B81: ='GERAL 2022'!H20 -> 14.184043 | C81: 5 | D81: =B81/C81 -> 2.8368085
A82: SEGURO 19 | B82: ='GERAL 2022'!J21 -> 118.43 | C82: 6 | D82: =B82/C82 -> 19.738333
A83: IPTU 19 | B83: ='GERAL 2022'!H21 -> 14.184043 | C83: 5 | D83: =B83/C83 -> 2.8368085
A84: SEGURO 20
A85: IPTU 20
A86: SEGURO 21
A87: IPTU 21
A88: SEGURO 22
A89: IPTU 22
A90: SEGURO 23
A91: IPTU 23
A92: SEGURO 24 | B92: ='GERAL 2022'!J26 -> 119.02 | C92: 6 | D92: =B92/C92 -> 19.836667
A93: IPTU 24 | B93: ='GERAL 2022'!H26 -> 19.85766 | C93: 5 | D93: =B93/C93 -> 3.9715319
A94: SEGURO 25 | B94: ='GERAL 2022'!J27 -> 119.7 | C94: 6 | D94: =B94/C94 -> 19.95
A95: IPTU 25 | B95: ='GERAL 2022'!H27 -> 14.184043 | C95: 5 | D95: =B95/C95 -> 2.8368085
A96: SEGURO 26
A97: IPTU 26
A98: SEGURO 27 | B98: ='GERAL 2022'!J29 -> 119.02 | C98: 6 | D98: =B98/C98 -> 19.836667
A99: IPTU 27 | B99: ='GERAL 2022'!H29 -> 14.184043 | C99: 5 | D99: =B99/C99 -> 2.8368085

Sheet VIGÊNCIA MAIO 2022
A1: GRAND MESSEJANA II
A2: VIGÊNCIA DE MAIO 2022
A3: NOME | B3: APTO | C3: ALUGUEL | D3: DESCONTO | E3: ALUGUEL C/ DESCONTO | F3: GARAGEM | G3: IPTU | H3: SEG INC. | I3: TOTAL | J3: COMISSÃO | K3: REPASSE | L3: OBSERVAÇÃO | M3: VENC. | N3: CARÊNCIA
B4: 1
B5: 2 | J5: =7%*I5 -> 0
B6: 3 | J6: =7%*I6 -> 0
A7: AMANDA | B7: 4 | C7: ='GERAL 2022'!G16 -> 550 | D7: 0 | E7: =C7-D7 -> 550 | F7: 50 | G7: =D51 -> 2.8368085 | H7: =D50 -> 19.641667 | I7: =SUM(E7:H7) -> 622.47848 | J7: =7%*I7 -> 43.573493 | K7: =I7-J7 -> 578.90498 | L7: SEM DESCONTO. IPTU (5/5). SEGUROS (4/6). | M7: 10 | N7: 11
B8: 5 | J8: =7%*I8 -> 0
A9: LIGIA | B9: 6 | C9: ='GERAL 2022'!G8 -> 650 | D9: 0 | E9: =C9-D9 -> 650 | F9: 25 | G9: =D55 -> 3.9715319 | H9: =D54 -> 19.836667 | I9: =SUM(E9:H9) -> 698.8082 | J9: =7%*I9 -> 48.916574 | K9: =I9-J9 -> 649.89162 | L9: SEM DESCONTO. IPTU (3/5). SEGURO (3/6). | M9: 10 | N9: 11
B10: 7 | J10: =7%*I10 -> 0
A11: ARMANDO | B11: 8 | C11: ='GERAL 2022'!G10 -> 610 | D11: 0 | E11: =C11-D11 -> 610 | F11: 0 | G11: =D59 -> 2.8368085 | H11: =D58 -> 19.755 | I11: =SUM(E11:H11) -> 632.59181 | J11: =7%*I11 -> 44.281427 | K11: =I11-J11 -> 588.31038 | L11: SEM DESCONTO. IPTU (5/5). SEGUROS (4/6). | M11: 10 | N11: 11
A12: ALCIDES / RENÊ | B12: 9 | C12: ='GERAL 2022'!G11 -> 580 | D12: 0 | E12: =C12-D12 -> 580 | F12: =50 -> 50 | G12: =D61 -> 2.8368085 | H12: =D60 -> 19.696667 | I12: =SUM(E12:H12) -> 652.53348 | J12: =7%*I12 -> 45.677343 | K12: =I12-J12 -> 606.85613 | L12: SEM DESCONTO. SEGURO (5/6). IPTU (5/5). | M12: 10 | N12: 11
B13: 10
A14: JOCÉLIO | B14: 11 | C14: ='GERAL 2022'!G13 -> 550 | D14: 0 | E14: =C14-D14 -> 550 | F14: 0 | G14: =D65 -> 2.8368085 | H14: 19.81 | I14: =SUM(E14:H14) -> 572.64681 | J14: =7%*I14 -> 40.085277 | K14: =I14-J14 -> 532.56153 | L14: SEM DESCONTO. IPTU (2/5). SEGURO (2/6). | M14: 10 | N14: 11
B15: 12 | J15: =7%*I15 -> 0
A16: MARLON | B16: 13 | C16: ='GERAL 2022'!G15/31*5 -> 88.709677 | D16: 0 | E16: =C16-D16 -> 88.709677 | F16: 0 | G16: =D69/31*5 -> 0.45754976 | H16: =D68 -> 19.641667 | I16: =SUM(E16:H16) -> 108.80889 | J16: =7%*I16 -> 7.6166226 | K16: =I16-J16 -> 101.19227 | L16: PROPORCIONAL DE 05 DIAS (27/05 A 31/05). IPTU (1/5). SEGURO (1/6). | M16: 10 | N16: 11
A17: HOSANA | B17: 14 | C17: ='GERAL 2022'!G16 -> 550 | D17: 0 | E17: =C17-D17 -> 550 | F17: 0 | G17: =D71 -> 2.8368085 | H17: =D70 -> 19.641667 | I17: =SUM(E17:H17) -> 572.47848 | J17: =7%*I17 -> 40.073493 | K17: =I17-J17 -> 532.40498 | L17: SEM DESCONTO. IPTU (3/5). SEGUROS (3/6). | M17: 10 | N17: 11
A18: BIANCA | B18: 15 | C18: ='GERAL 2022'!G40 -> 650 | D18: 0 | E18: =C18-D18 -> 650 | F18: 25 | G18: =D73 -> 3.9715319 | H18: =D72 -> 19.836667 | I18: =SUM(E18:H18) -> 698.8082 | J18: =7%*I18 -> 48.916574 | K18: =I18-J18 -> 649.89162 | L18: SEM DESCONTO. IPTU (5/5). SEGUROS (4/6).
A19: VANESSA | B19: 16 | C19: ='GERAL 2022'!G18 -> 640 | D19: =10%*C19 -> 64 | E19: =C19-D19 -> 576 | F19: =60 -> 60 | G19: =D77 -> 2.8368085 | H19: 0 | I19: =SUM(E19:H19) -> 638.83681 | J19: =7%*I19 -> 44.718577 | K19: =I19-J19 -> 594.11823 | L19: DESCONTO 10% (12/12). SEGURO QUITADO. IPTU (5/5). | M19: 10 | N19: 11
A20: MATEUS LEVI | B20: 17 | C20: ='GERAL 2022'!G19/31*22 -> 454.19355 | D20: =10%*C20 -> 45.419355 | E20: =(C20-D20) -> 408.77419 | F20: 0 | G20: =D79/31*22 -> 2.0132189 | H20: 0 | I20: =SUM(E20:H20) -> 410.78741 | J20: =7%*I20 -> 28.755119 | K20: =I20-J20 -> 382.03229 | L20: RESCISÃO. PROPORCINAL DE 22 DIAS (01/05/2022 A 22/05/2022). DESCONTO 10% (11/12). IPTU (5/5). SEGURO QUITADO. | M20: 10 | N20: 11
A21: FREDSON | B21: 18 | C21: ='GERAL 2022'!G20 -> 650 | D21: =10%*C21 -> 65 | E21: =C21-D21 -> 585 | F21: =30 -> 30 | G21: =D81 -> 2.8368085 | H21: 0 | I21: =SUM(E21:H21) -> 617.83681 | J21: =7%*I21 -> 43.248577 | K21: =I21-J21 -> 574.58823 | L21: DESCONTO 10% (12/12). SEGURO QUITADO. IPTU (5/5). | M21: 10 | N21: 11
A22: ERIVANDO | B22: 19 | C22: ='GERAL 2022'!G21 -> 600 | D22: =10%*C22 -> 60 | E22: =(C22-D22) -> 540 | F22: =50 -> 50 | G22: =D83 -> 2.8368085 | H22: 0 | I22: =SUM(E22:H22) -> 592.83681 | J22: =7%*I22 -> 41.498577 | K22: =I22-J22 -> 551.33823 | L22: DESCONTO 10% (10/12). SEGURO QUITADO. IPTU (5/5). | M22: 10 | N22: 11
A23: RENAN | B23: 20 | C23: ='GERAL 2022'!G22/31*19 -> 404.51613 | D23: 0 | E23: =C23-D23 -> 404.51613 | F23: =50/31*19 -> 30.645161 | G23: =D85/31*19 -> 1.7386891 | H23: 19.87 | I23: =SUM(E23:H23) -> 456.76998 | J23: =7%*I23 -> 31.973899 | K23: =I23-J23 -> 424.79608 | L23: PROPORCIONAL DE 19 DIAS (13/05 A 31/05). IPTU (1/5). SEGURO (1/6). | M23: 10 | N23: 11
A24: KELSON | B24: 21 | C24: ='GERAL 2022'!G23/31*19 -> 306.45161 | D24: 0 | E24: =C24-D24 -> 306.45161 | F24: =25/31*19 -> 15.322581 | G24: =D87/31*19 -> 1.7386891 | H24: 19.56 | I24: =SUM(E24:H24) -> 343.07288 | J24: =7%*I24 -> 24.015102 | K24: =I24-J24 -> 319.05778 | L24: PROPORCIONAL DE 19 DIAS (13/05 A 31/05). IPTU (1/5). SEGURO (1/6). | M24: 10 | N24: 11
A25: MATEUS | B25: 22 | C25: ='GERAL 2022'!G24/31*19 -> 306.45161 | D25: 0 | E25: =C25-D25 -> 306.45161 | F25: =25/31*19 -> 15.322581 | G25: =D89/31*19 -> 1.7386891 | H25: 19.56 | I25: =SUM(E25:H25) -> 343.07288 | J25: =7%*I25 -> 24.015102 | K25: =I25-J25 -> 319.05778 | L25: PROPORCIONAL DE 19 DIAS (13/05 A 31/05). IPTU (1/5). SEGURO (1/6). | M25: 10 | N25: 11
A26: CÍCERO ABEL | B26: 23 | C26: ='GERAL 2022'!G25/31*12 -> 212.90323 | D26: 0 | E26: =C26-D26 -> 212.90323 | F26: 0 | G26: =D91/31*12 -> 1.0981194 | H26: 19.65 | I26: =SUM(E26:H26) -> 233.65135 | J26: =7%*I26 -> 16.355594 | K26: =I26-J26 -> 217.29575 | L26: PROPORCIONAL DE 12 DIAS (20/05 A 31/05). IPTU (1/5). SEGURO (1/6). | M26: 10 | N26: 11
A27: JOÃO LEVI | B27: 24 | C27: ='GERAL 2022'!G26 -> 650 | D27: 0 | E27: =C27-D27 -> 650 | F27: 50 | G27: =D93 -> 3.9715319 | H27: =D92 -> 19.836667 | I27: =SUM(E27:H27) -> 723.8082 | J27: =7%*I27 -> 50.666574 | K27: =I27-J27 -> 673.14162 | L27: SEM DESCONTO. IPTU (5/5). SEGUROS (4/6).
A28: SHIRLEY | B28: 25 | C28: ='GERAL 2022'!G27+(14.66086%*704) -> 807.21245 | D28: 0 | E28: =C28-D28 -> 807.21245 | F28: =30 -> 30 | G28: =D95 -> 2.8368085 | H28: =D94 -> 19.95 | I28: =SUM(E28:H28) -> 859.99926 | J28: =7%*I28 -> 60.199948 | K28: =I28-J28 -> 799.79931 | L28: REAJUSTE EM MAIO/2022. DESCONTO FINALIZADO. IPTU (5/5). SEGURO (1/6). | M28: 10 | N28: 11
A29: HENRIQUE | B29: 26 | C29: ='GERAL 2022'!G28/31*26 -> 469.67742 | D29: 0 | E29: =C29-D29 -> 469.67742 | F29: 0 | G29: =D97/31*26 -> 2.3792588 | H29: =D96 -> 19.658333 | I29: =SUM(E29:H29) -> 491.71501 | J29: =7%*I29 -> 34.420051 | K29: =I29-J29 -> 457.29496 | L29: PROPORCIONAL DE 26 DIAS (06/05 A 31/05). IPTU (1/5). SEGURO (1/6). | M29: 10 | N29: 11
A30: FABIANA | B30: 27 | C30: ='GERAL 2022'!G45/31*26 -> 486.45161 | D30: 0 | E30: =C30-D30 -> 486.45161 | F30: 0 | G30: =D99/31*26 -> 2.3792588 | H30: =D98 -> 19.696667 | I30: =SUM(E30:H30) -> 508.52754 | J30: =7%*I30 -> 35.596928 | K30: =I30-J30 -> 472.93061 | L30: PROPORCIONAL DE 26 DIAS (06/05 A 31/05). IPTU (1/5). SEGURO (1/6). | M30: 10 | N30: 11
A31: TOTAL | C31: =SUM(C4:C30) -> 10216.567 | D31: =SUM(D4:D30) -> 234.41935 | E31: =SUM(E4:E30) -> 9982.1479 | F31: =SUM(F4:F30) -> 431.29032 | G31: =SUM(G4:G30) -> 50.989345 | H31: =SUM(H4:H30) -> 315.64167 | I31: =SUM(I4:I30) -> 10780.069 | J31: =SUM(J4:J30) -> 754.60485 | K31: =SUM(K4:K30) -> 10025.464
A33: ACORDOS/RESCISÕES RECEBIDAS EM MAIO DE 2022
A34: NOME | B34: APTO | C34: PRINCIPAL | D34: CONDIÇÃO | I34: TOTAL | J34: COMISSÃO | K34: REPASSE | L34: OBSERVAÇÃO | M34: VENC. | N34: CARÊNCIA
A35: MATEUS LEVI | B35: 17 | C35: 1152 | D35: 1x R$ 1.152,00 | I35: 1152 | J35: =7%*I35 -> 80.64 | K35: =I35-J35 -> 1071.36 | L35: MULTA POR RESCISÃO ANTES DO PRAZO. PAGO DIA 29/03/2022. | M35: 10 | N35: 11
A36: TOTAL | I36: =SUM(I35) -> 1152 | J36: =SUM(J35) -> 80.64 | K36: =SUM(K35) -> 1071.36
A38: INADIMPLÊNCIAS
A39: NOME | B39: APTO | C39: PRINCIPAL | D39: CONDIÇÃO | I39: TOTAL | L39: OBSERVAÇÃO | M39: VENC. | N39: CARÊNCIA
A40: JOÃO PAULO | B40: 1 | C40: =4977.59-1520 -> 3457.59 | D40: R$ 4.977,59 (DÉBITO TOTAL) - R$ 1.520,00 (CAUÇÃO) | I40: =4977.59-1520 -> 3457.59 | L40: DÉBITO ATUALIZADO EM 19/02/2022 (OUT/21 A FEV/22 E MULTA), DIFERENÇA APÓS UTILIZAÇÃO DA CAUÇÃO | M40: 10 | N40: 11
A41: TOTAL | I41: =SUM(I40:I40) -> 3457.59
A43: OBSERVAÇÕES | L43: COMISSÕES
A44: SEGURO 01 | B44: ='GERAL 2022'!J3 -> 118.43 | C44: 6 | D44: =B44/C44 -> 19.738333 | L44: COMISSÃO 7% | N44: =J31+J36 -> 835.24485
A45: IPTU 01 | B45: ='GERAL 2022'!H3 -> 14.184043 | C45: 5 | D45: =B45/C45 -> 2.8368085 | L45: INTERMEDIAÇÃO 60%
A46: SEGURO 02
A47: IPTU 02
A48: SEGURO 03 | L48: OUTRAS COMISSÕES E DESPESAS
A49: IPTU 03 | L49: SEGURO APTO 04 (4/6) | N49: 19.64
A50: SEGURO 04 | B50: ='GERAL 2022'!J6 -> 117.85 | C50: 6 | D50: =B50/C50 -> 19.641667 | L50: SEGURO APTO 06 (3/6) | N50: 19.84
A51: IPTU 04 | B51: ='GERAL 2022'!H6 -> 14.184043 | C51: 5 | D51: =B51/C51 -> 2.8368085 | L51: SEGURO APTO 08 (4/6) | N51: 19.76
A52: SEGURO 05 | L52: SEGURO APTO 09 (5/6) | N52: 19.7
A53: IPTU 05 | L53: SEGURO APTO 11 (2/6) | N53: 19.81
A54: SEGURO 06 | B54: ='GERAL 2022'!J8 -> 119.02 | C54: 6 | D54: =B54/C54 -> 19.836667 | L54: SEGURO APTO 13 (1/6) | N54: 19.65
A55: IPTU 06 | B55: ='GERAL 2022'!H8 -> 19.85766 | C55: 5 | D55: =B55/C55 -> 3.9715319 | L55: SEGURO APTO 14 (3/6) | N55: 19.64
A56: SEGURO 07 | L56: SEGURO APTO 15 (4/6) | N56: 19.84
A57: IPTU 07 | L57: SEGURO APTO 20 (1/6) | N57: 19.87
A58: SEGURO 08 | B58: ='GERAL 2022'!J10 -> 118.53 | C58: 6 | D58: =B58/C58 -> 19.755 | L58: SEGURO APTO 21 (1/6) | N58: 19.56
A59: IPTU 08 | B59: ='GERAL 2022'!H10 -> 14.184043 | C59: 5 | D59: =B59/C59 -> 2.8368085 | L59: SEGURO APTO 22 (1/6) | N59: 19.56
A60: SEGURO 09 | B60: ='GERAL 2022'!J11 -> 118.18 | C60: 6 | D60: =B60/C60 -> 19.696667 | L60: SEGURO APTO 23 (1/6) | N60: 19.65
A61: IPTU 09 | B61: ='GERAL 2022'!H11 -> 14.184043 | C61: 5 | D61: =B61/C61 -> 2.8368085 | L61: SEGURO APTO 24 (4/6) | N61: 19.84
A62: SEGURO 10 | B62: ='GERAL 2022'!J12 -> 106.95 | C62: 6 | D62: =B62/C62 -> 17.825 | L62: SEGURO APTO 25 (1/6) | N62: 19.95
A63: IPTU 10 | B63: ='GERAL 2022'!H12 -> 14.184043 | C63: 5 | D63: =B63/C63 -> 2.8368085 | L63: SEGURO APTO 26 (1/6) | N63: 19.65
A64: SEGURO 11 | B64: ='GERAL 2022'!J13 -> 117.85 | C64: 6 | D64: =B64/C64 -> 19.641667 | L64: SEGURO APTO 27 (1/6) | N64: 19.68
A65: IPTU 11 | B65: ='GERAL 2022'!H13 -> 14.184043 | C65: 5 | D65: =B65/C65 -> 2.8368085 | L65: 04 LIMPEZAS (07/05/2022 - 14/05/2022 - 21/05/2022 - 28/05/2022) | N65: =120*4 -> 480
A66: SEGURO 12 | L66: RECONHECIMENTOS DE FIRMA CONTRATO APTO 13, 20, 21, 22, 23, 26 E 27 | N66: =8.77*7 -> 61.39
A67: IPTU 12 | L67: ENEL | N67: 134.45
A68: SEGURO 13 | B68: ='GERAL 2022'!J15 -> 117.85 | C68: 6 | D68: =B68/C68 -> 19.641667 | L68: CAGECE SEM FATURA
A69: IPTU 13 | B69: ='GERAL 2022'!H15 -> 14.184043 | C69: 5 | D69: =B69/C69 -> 2.8368085 | L69: MUDANÇA MOBILIA APTO 7 (TÉRREO) PARA APTO 20 (2º ANDAR) | N69: 70
A70: SEGURO 14 | B70: ='GERAL 2022'!J16 -> 117.85 | C70: 6 | D70: =B70/C70 -> 19.641667
A71: IPTU 14 | B71: ='GERAL 2022'!H16 -> 14.184043 | C71: 5 | D71: =B71/C71 -> 2.8368085
A72: SEGURO 15 | B72: ='GERAL 2022'!J40 -> 119.02 | C72: 6 | D72: =B72/C72 -> 19.836667
A73: IPTU 15 | B73: ='GERAL 2022'!H17 -> 19.85766 | C73: 5 | D73: =B73/C73 -> 3.9715319
A74: SEGURO 15 NOVO | B74: ='GERAL 2022'!J40 -> 119.02 | C74: 6 | D74: =B74/C74 -> 19.836667
A75: IPTU 15 NOVO | B75: ='GERAL 2022'!H40 -> 19.85766 | C75: 5 | D75: =B75/C75 -> 3.9715319
A76: SEGURO 16 | B76: ='GERAL 2022'!J18 -> 118.87 | C76: 6 | D76: =B76/C76 -> 19.811667 | L76: TOTAL COMISSÃO + DESPESAS | N76: =SUM(N44:N75) -> 1896.7248
A77: IPTU 16 | B77: ='GERAL 2022'!H18 -> 14.184043 | C77: 5 | D77: =B77/C77 -> 2.8368085
A78: SEGURO 17 | B78: ='GERAL 2022'!J19 -> 118.87 | C78: 6 | D78: =B78/C78 -> 19.811667 | L78: R$ RECEBIDOS EM NOME DO LOCADOR | N78: =I31+I36 -> 11932.069
A79: IPTU 17 | B79: ='GERAL 2022'!H19 -> 14.184043 | C79: 5 | D79: =B79/C79 -> 2.8368085
A80: SEGURO 18 | B80: ='GERAL 2022'!J20 -> 119.02 | C80: 6 | D80: =B80/C80 -> 19.836667 | L80: TOTAL A REPASSAR | N80: =N78-N76 -> 10035.344
A81: IPTU 18 | B81: ='GERAL 2022'!H20 -> 14.184043 | C81: 5 | D81: =B81/C81 -> 2.8368085
A82: SEGURO 19 | B82: ='GERAL 2022'!J21 -> 118.43 | C82: 6 | D82: =B82/C82 -> 19.738333
A83: IPTU 19 | B83: ='GERAL 2022'!H21 -> 14.184043 | C83: 5 | D83: =B83/C83 -> 2.8368085
A84: SEGURO 20 | B84: ='GERAL 2022'!J22 -> 119.12 | C84: 6 | D84: =B84/C84 -> 19.853333
A85: IPTU 20 | B85: ='GERAL 2022'!H22 -> 14.184043 | C85: 5 | D85: =B85/C85 -> 2.8368085
A86: SEGURO 21 | B86: ='GERAL 2022'!J23 -> 117.26 | C86: 6 | D86: =B86/C86 -> 19.543333
A87: IPTU 21 | B87: ='GERAL 2022'!H23 -> 14.184043 | C87: 5 | D87: =B87/C87 -> 2.8368085
A88: SEGURO 22 | B88: ='GERAL 2022'!J24 -> 117.26 | C88: 6 | D88: =B88/C88 -> 19.543333
A89: IPTU 22 | B89: ='GERAL 2022'!H24 -> 14.184043 | C89: 5 | D89: =B89/C89 -> 2.8368085
A90: SEGURO 23 | B90: ='GERAL 2022'!J25 -> 117.85 | C90: 6 | D90: =B90/C90 -> 19.641667
A91: IPTU 23 | B91: ='GERAL 2022'!H25 -> 14.184043 | C91: 5 | D91: =B91/C91 -> 2.8368085
A92: SEGURO 24 | B92: ='GERAL 2022'!J26 -> 119.02 | C92: 6 | D92: =B92/C92 -> 19.836667
A93: IPTU 24 | B93: ='GERAL 2022'!H26 -> 19.85766 | C93: 5 | D93: =B93/C93 -> 3.9715319
A94: SEGURO 25 | B94: ='GERAL 2022'!J27 -> 119.7 | C94: 6 | D94: =B94/C94 -> 19.95
A95: IPTU 25 | B95: ='GERAL 2022'!H27 -> 14.184043 | C95: 5 | D95: =B95/C95 -> 2.8368085
A96: SEGURO 26 | B96: ='GERAL 2022'!J28 -> 117.95 | C96: 6 | D96: =B96/C96 -> 19.658333
A97: IPTU 26 | B97: ='GERAL 2022'!H28 -> 14.184043 | C97: 5 | D97: =B97/C97 -> 2.8368085
A98: SEGURO 27 | B98: ='GERAL 2022'!J45 -> 118.18 | C98: 6 | D98: =B98/C98 -> 19.696667
A99: IPTU 27 | B99: ='GERAL 2022'!H45 -> 14.184043 | C99: 5 | D99: =B99/C99 -> 2.8368085

Sheet VIGÊNCIA JUNHO 2022
A1: GRAND MESSEJANA II
A2: INTERMEDIAÇÕES DE MAIO DE 2022
A3: NOME | B3: APTO | C3: ALUGUEL | D3: DESCONTO | E3: ALUGUEL C/ DESCONTO | F3: GARAGEM | G3: IPTU | H3: SEG INC. | I3: TOTAL | J3: COMISSÃO | K3: REPASSE | L3: OBSERVAÇÃO | M3: VENC. | N3: CARÊNCIA
A4: MARLON | B4: 13 | C4: ='GERAL 2022'!G15 -> 550 | D4: 0 | E4: =C4-D4 -> 550 | F4: 0 | G4: =D76 -> 2.8368085 | H4: =D75 -> 19.641667 | I4: =SUM(E4:H4) -> 572.47848 | J4: =60%*(C4+F4) -> 330 | K4: =I4-J4 -> 242.47848 | L4: IPTU (2/5). SEGURO (2/6). | M4: 10 | N4: 11
A5: RENAN | B5: 20 | C5: ='GERAL 2022'!G22 -> 660 | D5: 0 | E5: =C5-D5 -> 660 | F5: 50 | G5: =D90 -> 2.8368085 | H5: =D89 -> 19.853333 | I5: =SUM(E5:H5) -> 732.69014 | J5: =60%*(C5+F5) -> 426 | K5: =I5-J5 -> 306.69014 | L5: IPTU (2/5). SEGURO (2/6). | M5: 10 | N5: 11
A6: KELSON | B6: 21 | C6: ='GERAL 2022'!G23 -> 500 | D6: 0 | E6: =C6-D6 -> 500 | F6: 25 | G6: =D92 -> 2.8368085 | H6: =D91 -> 19.543333 | I6: =SUM(E6:H6) -> 547.38014 | J6: =60%*(C6+F6) -> 315 | K6: =I6-J6 -> 232.38014 | L6: IPTU (2/5). SEGURO (2/6). | M6: 10 | N6: 11
A7: MATEUS | B7: 22 | C7: ='GERAL 2022'!G24 -> 500 | D7: 0 | E7: =C7-D7 -> 500 | F7: 25 | G7: =D94 -> 2.8368085 | H7: =D93 -> 19.543333 | I7: =SUM(E7:H7) -> 547.38014 | J7: =60%*(C7+F7) -> 315 | K7: =I7-J7 -> 232.38014 | L7: IPTU (2/5). SEGURO (2/6). | M7: 10 | N7: 11
A8: CÍCERO | B8: 23 | C8: ='GERAL 2022'!G25 -> 550 | D8: 0 | E8: =C8-D8 -> 550 | F8: 0 | G8: =D96 -> 2.8368085 | H8: =D95 -> 19.641667 | I8: =SUM(E8:H8) -> 572.47848 | J8: =60%*(C8+F8) -> 330 | K8: =I8-J8 -> 242.47848 | L8: IPTU (2/5). SEGURO (2/6). | M8: 10 | N8: 11
A9: HENRIQUE | B9: 26 | C9: ='GERAL 2022'!G28 -> 560 | D9: 0 | E9: =C9-D9 -> 560 | F9: 25 | G9: =D102 -> 2.8368085 | H9: =D101 -> 19.658333 | I9: =SUM(E9:H9) -> 607.49514 | J9: =60%*(C9+F9) -> 351 | K9: =I9-J9 -> 256.49514 | L9: IPTU (2/5). SEGURO (2/6). | M9: 10 | N9: 11
A10: FABIANA | B10: 27 | C10: ='GERAL 2022'!G45 -> 580 | D10: 0 | E10: =C10-D10 -> 580 | F10: 0 | G10: =D104 -> 2.8368085 | H10: =D103 -> 19.696667 | I10: =SUM(E10:H10) -> 602.53348 | J10: =60%*(C10+F10) -> 348 | K10: =I10-J10 -> 254.53348 | L10: IPTU (2/5). SEGURO (2/6). | M10: 10 | N10: 11
A11: TOTAL | C11: =SUM(C4:C10) -> 3900 | D11: =SUM(D4:D10) -> 0 | E11: =SUM(E4:E10) -> 3900 | F11: =SUM(F4:F10) -> 125 | G11: =SUM(G4:G10) -> 19.85766 | H11: =SUM(H4:H10) -> 137.57833 | I11: =SUM(I4:I10) -> 4182.436 | J11: =SUM(J4:J10) -> 2415 | K11: =SUM(K4:K10) -> 1767.436
A13: VIGÊNCIA DE JUNHO 2022
A14: NOME | B14: APTO | C14: ALUGUEL | D14: DESCONTO | E14: ALUGUEL C/ DESCONTO | F14: GARAGEM | G14: IPTU | H14: SEG INC. | I14: TOTAL | J14: COMISSÃO | K14: REPASSE | L14: OBSERVAÇÃO | M14: VENC. | N14: CARÊNCIA
A15: ELISON | B15: 1 | C15: ='GERAL 2022'!G35/30*7 -> 135.33333 | D15: 0 | E15: =C15-D15 -> 135.33333 | F15: =50/30*7 -> 11.666667 | G15: =D52 -> 2.8368085 | H15: =D51 -> 19.696667 | I15: =SUM(E15:H15) -> 169.53348 | J15: =7%*I15 -> 11.867343 | K15: =I15-J15 -> 157.66613 | L15: PROPORCIONAL DE 07 DIAS (24/06 A 30/06). IPTU (1/5). SEGURO (1/6). | M15: 10 | N15: 11
B16: 2 | J16: =7%*I16 -> 0
B17: 3 | J17: =7%*I17 -> 0
A18: AMANDA | B18: 4 | C18: ='GERAL 2022'!G16 -> 550 | D18: 0 | E18: =C18-D18 -> 550 | F18: 50 | G18: 0 | H18: =D57 -> 19.641667 | I18: =SUM(E18:H18) -> 619.64167 | J18: =7%*I18 -> 43.374917 | K18: =I18-J18 -> 576.26675 | L18: SEM DESCONTO. IPTU QUITADO. SEGURO (5/6). | M18: 10 | N18: 11
B19: 5 | J19: =7%*I19 -> 0
A20: LIGIA | B20: 6 | C20: ='GERAL 2022'!G8 -> 650 | D20: 0 | E20: =C20-D20 -> 650 | F20: 25 | G20: =D62 -> 3.9715319 | H20: =D61 -> 19.836667 | I20: =SUM(E20:H20) -> 698.8082 | J20: =7%*I20 -> 48.916574 | K20: =I20-J20 -> 649.89162 | L20: SEM DESCONTO. IPTU (4/5). SEGURO (4/6). | M20: 10 | N20: 11
B21: 7 | J21: =7%*I21 -> 0
A22: ARMANDO | B22: 8 | C22: ='GERAL 2022'!G10 -> 610 | D22: 0 | E22: =C22-D22 -> 610 | F22: =50/30*8 -> 13.333333 | G22: 0 | H22: =D65 -> 19.755 | I22: =SUM(E22:H22) -> 643.08833 | J22: =7%*I22 -> 45.016183 | K22: =I22-J22 -> 598.07215 | L22: GARAGEM PROPORCIONAL DE 08 DIAS (23/06 A 30/06). SEM DESCONTO. IPTU QUITADO. SEGURO (5/6). | M22: 10 | N22: 11
A23: ALCIDES / RENÊ | B23: 9 | C23: ='GERAL 2022'!G11 -> 580 | D23: 0 | E23: =C23-D23 -> 580 | F23: =50 -> 50 | G23: 0 | H23: =D67 -> 19.696667 | I23: =SUM(E23:H23) -> 649.69667 | J23: =7%*I23 -> 45.478767 | K23: =I23-J23 -> 604.2179 | L23: SEM DESCONTO. IPTU QUITADO. SEGURO (6/6). | M23: 10 | N23: 11
A24: JAÍNE | B24: 10 | C24: ='GERAL 2022'!G38/30*25 -> 458.33333 | D24: 0 | E24: =C24-D24 -> 458.33333 | F24: =50/30*25 -> 41.666667 | G24: =D70/30*25 -> 2.3640071 | H24: 19.65 | I24: =SUM(E24:H24) -> 522.01401 | J24: =7%*I24 -> 36.54098 | K24: =I24-J24 -> 485.47303 | L24: PROPORCIONAL DE 25 DIAS (06/06 A 30/06). SEM DESCONTO. IPTU (1/5). SEGURO (1/6). | M24: 10 | N24: 11
A25: JOCÉLIO | B25: 11 | C25: ='GERAL 2022'!G13 -> 550 | D25: 0 | E25: =C25-D25 -> 550 | F25: 0 | G25: =D72 -> 2.8368085 | H25: =D71 -> 19.641667 | I25: =SUM(E25:H25) -> 572.47848 | J25: =7%*I25 -> 40.073493 | K25: =I25-J25 -> 532.40498 | L25: SEM DESCONTO. IPTU (3/5). SEGURO (3/6). | M25: 10 | N25: 11
A26: DAVID/FÁTIMA | B26: 12 | C26: ='GERAL 2022'!G14/30*21 -> 385 | D26: 0 | E26: =C26-D26 -> 385 | F26: =25/30*21 -> 17.5 | G26: =D74/30*21 -> 1.985766 | H26: 19.65 | I26: =SUM(E26:H26) -> 424.13577 | J26: =7%*I26 -> 29.689504 | K26: =I26-J26 -> 394.44626 | L26: PROPORCIONAL DE 21 DIAS (10/06 A 30/06). SEM DESCONTO. IPTU (1/5). SEGURO (1/6). | M26: 10 | N26: 11
A27: MARLON | B27: 13 | C27: 0 | D27: 0 | E27: =C27-D27 -> 0 | F27: 0 | G27: 0 | H27: 0 | I27: =SUM(E27:H27) -> 0 | J27: =7%*I27 -> 0 | K27: =I27-J27 -> 0 | L27: INTERMEDIAÇÃO | M27: 10 | N27: 11
A28: HOSANA | B28: 14 | C28: ='GERAL 2022'!G16 -> 550 | D28: 0 | E28: =C28-D28 -> 550 | F28: 0 | G28: =D78 -> 2.8368085 | H28: =D77 -> 19.641667 | I28: =SUM(E28:H28) -> 572.47848 | J28: =7%*I28 -> 40.073493 | K28: =I28-J28 -> 532.40498 | L28: SEM DESCONTO. IPTU (4/5). SEGURO (4/6). | M28: 10 | N28: 11
A29: BIANCA | B29: 15 | C29: ='GERAL 2022'!G40 -> 650 | D29: 0 | E29: =C29-D29 -> 650 | F29: 25 | G29: 0 | H29: =D79 -> 19.836667 | I29: =SUM(E29:H29) -> 694.83667 | J29: =7%*I29 -> 48.638567 | K29: =I29-J29 -> 646.1981 | L29: SEM DESCONTO. IPTU QUITADO. SEGURO (5/6).
A30: VANESSA | B30: 16 | C30: ='GERAL 2022'!G18+(10.72339%*640) -> 708.6297 | E30: =C30-D30 -> 708.6297 | F30: =60 -> 60 | G30: 0 | H30: 19.82 | I30: =SUM(E30:H30) -> 788.4497 | J30: =7%*I30 -> 55.191479 | K30: =I30-J30 -> 733.25822 | L30: REAJUSTADO EM JUNHO/2022. IPTU QUITADO. SEGURO (1/6). | M30: 10 | N30: 11
A31: IRAN | B31: 17 | C31: ='GERAL 2022'!G41/30*23 -> 444.66667 | D31: 0 | E31: =C31-D31 -> 444.66667 | F31: 0 | G31: =D84/30*23 -> 2.1748865 | H31: =D83 -> 19.696667 | I31: =SUM(E31:H31) -> 466.53822 | J31: =7%*I31 -> 32.657675 | K31: =I31-J31 -> 433.88054 | L31: PROPORCIONAL DE 23 DIAS (08/06 A 30/06). IPTU (1/5). SEGURO (1/6). | M31: 10 | N31: 11
A32: FREDSON | B32: 18 | C32: ='GERAL 2022'!G20+(10.72339%*650) -> 719.70204 | D32: 0 | E32: =C32-D32 -> 719.70204 | F32: =30 -> 30 | H32: =D85 -> 19.836667 | I32: =SUM(E32:H32) -> 769.5387 | J32: =7%*I32 -> 53.867709 | K32: =I32-J32 -> 715.67099 | L32: REAJUSTADO EM JUNHO/2022. IPTU QUITADO. SEGURO (1/6). | M32: 10 | N32: 11
A33: ERIVANDO | B33: 19 | C33: ='GERAL 2022'!G21 -> 600 | D33: =10%*C33 -> 60 | E33: =(C33-D33) -> 540 | F33: =50 -> 50 | G33: 0 | H33: 0 | I33: =SUM(E33:H33) -> 590 | J33: =7%*I33 -> 41.3 | K33: =I33-J33 -> 548.7 | L33: DESCONTO 10% (11/12). IPTU QUITADO. SEGURO QUITADO. | M33: 10 | N33: 11
A34: RENAN | B34: 20 | C34: 0 | D34: 0 | E34: =C34-D34 -> 0 | F34: 0 | G34: 0 | H34: 0 | I34: =SUM(E34:H34) -> 0 | J34: =7%*I34 -> 0 | K34: =I34-J34 -> 0 | L34: INTERMEDIAÇÃO | M34: 10 | N34: 11
A35: KELSON | B35: 21 | C35: 0 | D35: 0 | E35: =C35-D35 -> 0 | F35: 0 | G35: 0 | H35: 0 | I35: =SUM(E35:H35) -> 0 | J35: =7%*I35 -> 0 | K35: =I35-J35 -> 0 | L35: INTERMEDIAÇÃO | M35: 10 | N35: 11
A36: MATEUS | B36: 22 | C36: 0 | D36: 0 | E36: =C36-D36 -> 0 | F36: 0 | G36: 0 | H36: 0 | I36: =SUM(E36:H36) -> 0 | J36: =7%*I36 -> 0 | K36: =I36-J36 -> 0 | L36: INTERMEDIAÇÃO | M36: 10 | N36: 11
A37: CÍCERO ABEL | B37: 23 | C37: 0 | D37: 0 | E37: =C37-D37 -> 0 | F37: 0 | G37: 0 | H37: 0 | I37: =SUM(E37:H37) -> 0 | J37: =7%*I37 -> 0 | K37: =I37-J37 -> 0 | L37: INTERMEDIAÇÃO | M37: 10 | N37: 11
A38: JOÃO LEVI | B38: 24 | C38: ='GERAL 2022'!G26 -> 650 | D38: 0 | E38: =C38-D38 -> 650 | F38: 50 | G38: 0 | H38: =D97 -> 19.836667 | I38: =SUM(E38:H38) -> 719.83667 | J38: =7%*I38 -> 50.388567 | K38: =I38-J38 -> 669.4481 | L38: SEM DESCONTO. IPTU QUITADO. SEGURO (5/6). | M38: 10 | N38: 11
A39: SHIRLEY | B39: 25 | C39: ='GERAL 2022'!G27+(14.66086%*704) -> 807.21245 | D39: 0 | E39: =C39-D39 -> 807.21245 | F39: =30 -> 30 | G39: 0 | H39: =D99 -> 19.95 | I39: =SUM(E39:H39) -> 857.16245 | J39: =7%*I39 -> 60.001372 | K39: =I39-J39 -> 797.16108 | L39: REAJUSTADO EM MAIO/2022. DESCONTO FINALIZADO. IPTU QUITADO. SEGURO (2/6). | M39: 10 | N39: 11
A40: HENRIQUE | B40: 26 | C40: 0 | D40: 0 | E40: =C40-D40 -> 0 | F40: 0 | G40: 0 | H40: 0 | I40: =SUM(E40:H40) -> 0 | J40: =7%*I40 -> 0 | K40: =I40-J40 -> 0 | L40: INTERMEDIAÇÃO | M40: 10 | N40: 11
A41: FABIANA | B41: 27 | C41: 0 | D41: 0 | E41: =C41-D41 -> 0 | F41: 0 | G41: 0 | H41: 0 | I41: =SUM(E41:H41) -> 0 | J41: =7%*I41 -> 0 | K41: =I41-J41 -> 0 | L41: INTERMEDIAÇÃO | M41: 10 | N41: 11
A42: TOTAL | C42: =SUM(C15:C41) -> 9048.8775 | D42: =SUM(D15:D41) -> 60 | E42: =SUM(E15:E41) -> 8988.8775 | F42: =SUM(F15:F41) -> 454.16667 | G42: =SUM(G15:G41) -> 19.006617 | H42: =SUM(H15:H41) -> 296.18667 | I42: =SUM(I15:I41) -> 9758.2375 | J42: =SUM(J15:J41) -> 683.07662 | K42: =SUM(K15:K41) -> 9075.1608
A45: INADIMPLÊNCIAS
A46: NOME | B46: APTO | C46: PRINCIPAL | D46: CONDIÇÃO | I46: TOTAL | L46: OBSERVAÇÃO | M46: VENC. | N46: CARÊNCIA
A47: JOÃO PAULO | B47: 1 | C47: =4977.59-1520 -> 3457.59 | D47: R$ 4.977,59 (DÉBITO TOTAL) - R$ 1.520,00 (CAUÇÃO) | I47: =4977.59-1520 -> 3457.59 | L47: DÉBITO ATUALIZADO EM 19/02/2022 (OUT/21 A FEV/22 E MULTA), DIFERENÇA APÓS UTILIZAÇÃO DA CAUÇÃO | M47: 10 | N47: 11
A48: TOTAL | I48: =SUM(I47:I47) -> 3457.59
A50: OBSERVAÇÕES | L50: COMISSÕES
A51: SEGURO 01 | B51: ='GERAL 2022'!J35 -> 118.18 | C51: 6 | D51: =B51/C51 -> 19.696667 | L51: COMISSÃO 7% | N51: =J42 -> 683.07662
A52: IPTU 01 | B52: ='GERAL 2022'!H35 -> 14.184043 | C52: 5 | D52: =B52/C52 -> 2.8368085 | L52: INTERMEDIAÇÃO 60% | N52: =J11 -> 2415
A53: SEGURO 02
A54: IPTU 02
A55: SEGURO 03 | L55: OUTRAS COMISSÕES E DESPESAS
A56: IPTU 03 | L56: SEGURO APTO 01 (1/6) | N56: 19.68
A57: SEGURO 04 | B57: ='GERAL 2022'!J6 -> 117.85 | C57: 6 | D57: =B57/C57 -> 19.641667 | L57: SEGURO APTO 04 (5/6) | N57: 19.64
A58: IPTU 04 | B58: ='GERAL 2022'!H6 -> 14.184043 | C58: 5 | D58: =B58/C58 -> 2.8368085 | L58: SEGURO APTO 06 (4/6) | N58: 19.84
A59: SEGURO 05 | L59: SEGURO APTO 08 (5/6) | N59: 19.76
A60: IPTU 05 | L60: SEGURO APTO 09 (6/6) | N60: 19.7
A61: SEGURO 06 | B61: ='GERAL 2022'!J8 -> 119.02 | C61: 6 | D61: =B61/C61 -> 19.836667 | L61: SEGURO APTO 10 (1/6) | N61: 19.65
A62: IPTU 06 | B62: ='GERAL 2022'!H8 -> 19.85766 | C62: 5 | D62: =B62/C62 -> 3.9715319 | L62: SEGURO APTO 11 (3/6) | N62: 19.64
A63: SEGURO 07 | L63: SEGURO APTO 12 (1/6) | N63: 19.65
A64: IPTU 07 | L64: SEGURO APTO 13 (2/6) | N64: 19.64
A65: SEGURO 08 | B65: ='GERAL 2022'!J10 -> 118.53 | C65: 6 | D65: =B65/C65 -> 19.755 | L65: SEGURO APTO 14 (4/6) | N65: 19.64
A66: IPTU 08 | B66: ='GERAL 2022'!H10 -> 14.184043 | C66: 5 | D66: =B66/C66 -> 2.8368085 | L66: SEGURO APTO 15 (5/6) | N66: 19.84
A67: SEGURO 09 | B67: ='GERAL 2022'!J11 -> 118.18 | C67: 6 | D67: =B67/C67 -> 19.696667 | L67: SEGURO APTO 16 (1/6) | N67: 19.82
A68: IPTU 09 | B68: ='GERAL 2022'!H11 -> 14.184043 | C68: 5 | D68: =B68/C68 -> 2.8368085 | L68: SEGURO APTO 17 (1/6) | N68: 19.68
A69: SEGURO 10 | B69: ='GERAL 2022'!J38 -> 117.85 | C69: 6 | D69: =B69/C69 -> 19.641667 | L69: SEGURO APTO 18 (1/6) | N69: 19.82
A70: IPTU 10 | B70: ='GERAL 2022'!H38 -> 14.184043 | C70: 5 | D70: =B70/C70 -> 2.8368085 | L70: SEGURO APTO 20 (2/6) | N70: 19.85
A71: SEGURO 11 | B71: ='GERAL 2022'!J13 -> 117.85 | C71: 6 | D71: =B71/C71 -> 19.641667 | L71: SEGURO APTO 21 (2/6) | N71: 19.54
A72: IPTU 11 | B72: ='GERAL 2022'!H13 -> 14.184043 | C72: 5 | D72: =B72/C72 -> 2.8368085 | L72: SEGURO APTO 22 (2/6) | N72: 19.54
A73: SEGURO 12 | B73: ='GERAL 2022'!J14 -> 117.85 | C73: 6 | D73: =B73/C73 -> 19.641667 | L73: SEGURO APTO 23 (2/6) | N73: 19.64
A74: IPTU 12 | B74: ='GERAL 2022'!H14 -> 14.184043 | C74: 5 | D74: =B74/C74 -> 2.8368085 | L74: SEGURO APTO 24 (5/6) | N74: 19.84
A75: SEGURO 13 | B75: ='GERAL 2022'!J15 -> 117.85 | C75: 6 | D75: =B75/C75 -> 19.641667 | L75: SEGURO APTO 25 (2/6) | N75: 19.93
A76: IPTU 13 | B76: ='GERAL 2022'!H15 -> 14.184043 | C76: 5 | D76: =B76/C76 -> 2.8368085 | L76: SEGURO APTO 26 (2/6) | N76: 19.66
A77: SEGURO 14 | B77: ='GERAL 2022'!J16 -> 117.85 | C77: 6 | D77: =B77/C77 -> 19.641667 | L77: SEGURO APTO 27 (2/6) | N77: 19.7
A78: IPTU 14 | B78: ='GERAL 2022'!H16 -> 14.184043 | C78: 5 | D78: =B78/C78 -> 2.8368085 | L78: 04 LIMPEZAS (04/06/2022 - 11/06/2022 - 18/06/2022 - 25/06/2022) | N78: =120*4 -> 480
A79: SEGURO 15 | B79: ='GERAL 2022'!J40 -> 119.02 | C79: 6 | D79: =B79/C79 -> 19.836667 | L79: RECONHECIMENTOS DE FIRMA CONTRATO APTO 01, 10, 12 E 17 | N79: =8.77*4 -> 35.08
A80: IPTU 15 | B80: ='GERAL 2022'!H40 -> 19.85766 | C80: 5 | D80: =B80/C80 -> 3.9715319 | L80: ENEL | N80: 133.01
A81: SEGURO 16 | B81: ='GERAL 2022'!J18 -> 118.87 | C81: 6 | D81: =B81/C81 -> 19.811667 | L81: CAGECE SEM FATURA
A82: IPTU 16 | B82: ='GERAL 2022'!H18 -> 14.184043 | C82: 5 | D82: =B82/C82 -> 2.8368085 | L82: MATERIAL CONSERTO BOIA: R$ 38,00 (BOIA) + R$ 120,00 (RELÉ) | N82: 158
A83: SEGURO 17 | B83: ='GERAL 2022'!J41 -> 118.18 | C83: 6 | D83: =B83/C83 -> 19.696667 | L83: SERVIÇO CONSERTO BOIA | N83: 120
A84: IPTU 17 | B84: ='GERAL 2022'!H41 -> 14.184043 | C84: 5 | D84: =B84/C84 -> 2.8368085
A85: SEGURO 18 | B85: ='GERAL 2022'!J20 -> 119.02 | C85: 6 | D85: =B85/C85 -> 19.836667
A86: IPTU 18 | B86: ='GERAL 2022'!H20 -> 14.184043 | C86: 5 | D86: =B86/C86 -> 2.8368085
A87: SEGURO 19 | B87: ='GERAL 2022'!J21 -> 118.43 | C87: 6 | D87: =B87/C87 -> 19.738333
A88: IPTU 19 | B88: ='GERAL 2022'!H21 -> 14.184043 | C88: 5 | D88: =B88/C88 -> 2.8368085
A89: SEGURO 20 | B89: ='GERAL 2022'!J22 -> 119.12 | C89: 6 | D89: =B89/C89 -> 19.853333 | L89: TOTAL COMISSÃO + DESPESAS | N89: =SUM(N51:N88) -> 4457.8666
A90: IPTU 20 | B90: ='GERAL 2022'!H22 -> 14.184043 | C90: 5 | D90: =B90/C90 -> 2.8368085
A91: SEGURO 21 | B91: ='GERAL 2022'!J23 -> 117.26 | C91: 6 | D91: =B91/C91 -> 19.543333 | L91: R$ RECEBIDOS EM NOME DO LOCADOR | N91: =I42+I11 -> 13940.673
A92: IPTU 21 | B92: ='GERAL 2022'!H23 -> 14.184043 | C92: 5 | D92: =B92/C92 -> 2.8368085
A93: SEGURO 22 | B93: ='GERAL 2022'!J24 -> 117.26 | C93: 6 | D93: =B93/C93 -> 19.543333 | L93: TOTAL A REPASSAR | N93: =N91-N89 -> 9482.8068
A94: IPTU 22 | B94: ='GERAL 2022'!H24 -> 14.184043 | C94: 5 | D94: =B94/C94 -> 2.8368085
A95: SEGURO 23 | B95: ='GERAL 2022'!J25 -> 117.85 | C95: 6 | D95: =B95/C95 -> 19.641667
A96: IPTU 23 | B96: ='GERAL 2022'!H25 -> 14.184043 | C96: 5 | D96: =B96/C96 -> 2.8368085
A97: SEGURO 24 | B97: ='GERAL 2022'!J26 -> 119.02 | C97: 6 | D97: =B97/C97 -> 19.836667
A98: IPTU 24 | B98: ='GERAL 2022'!H26 -> 19.85766 | C98: 5 | D98: =B98/C98 -> 3.9715319
A99: SEGURO 25 | B99: ='GERAL 2022'!J27 -> 119.7 | C99: 6 | D99: =B99/C99 -> 19.95
A100: IPTU 25 | B100: ='GERAL 2022'!H27 -> 14.184043 | C100: 5 | D100: =B100/C100 -> 2.8368085
A101: SEGURO 26 | B101: ='GERAL 2022'!J28 -> 117.95 | C101: 6 | D101: =B101/C101 -> 19.658333
A102: IPTU 26 | B102: ='GERAL 2022'!H28 -> 14.184043 | C102: 5 | D102: =B102/C102 -> 2.8368085
A103: SEGURO 27 | B103: ='GERAL 2022'!J45 -> 118.18 | C103: 6 | D103: =B103/C103 -> 19.696667
A104: IPTU 27 | B104: ='GERAL 2022'!H45 -> 14.184043 | C104: 5 | D104: =B104/C104 -> 2.8368085

Sheet VIGÊNCIA JULHO 2022
A1: GRAND MESSEJANA II
A2: INTERMEDIAÇÕES DE JUNHO DE 2022
A3: NOME | B3: APTO | C3: ALUGUEL | D3: DESCONTO | E3: ALUGUEL C/ DESCONTO | F3: GARAGEM | G3: IPTU | H3: SEG INC. | I3: TOTAL | J3: COMISSÃO | K3: REPASSE | L3: OBSERVAÇÃO | M3: VENC. | N3: CARÊNCIA
A4: ELISON | B4: 1 | C4: ='GERAL 2022'!G35 -> 580 | D4: 0 | E4: =C4-D4 -> 580 | F4: =50 -> 50 | G4: =D48 -> 2.8368085 | H4: =D47 -> 19.696667 | I4: =SUM(E4:H4) -> 652.53348 | J4: =60%*(C4+F4) -> 378 | K4: =I4-J4 -> 274.53348 | L4: SEM DESCONTO. IPTU (2/5). SEGURO (2/6). | M4: 10 | N4: 11
A5: JAÍNE | B5: 10 | C5: ='GERAL 2022'!G38 -> 550 | D5: 0 | E5: =C5-D5 -> 550 | F5: =50 -> 50 | G5: =D66 -> 2.8368085 | H5: =D65 -> 19.641667 | I5: =SUM(E5:H5) -> 622.47848 | J5: =60%*(C5+F5) -> 360 | K5: =I5-J5 -> 262.47848 | L5: SEM DESCONTO. IPTU (2/5). SEGURO (2/6). | M5: 10 | N5: 11
A6: DAVID/FÁTIMA | B6: 12 | C6: ='GERAL 2022'!G14 -> 550 | D6: 0 | E6: =C6-D6 -> 550 | F6: =25 -> 25 | G6: =D70 -> 2.8368085 | H6: =D69 -> 19.641667 | I6: =SUM(E6:H6) -> 597.47848 | J6: =60%*(C6+F6) -> 345 | K6: =I6-J6 -> 252.47848 | L6: SEM DESCONTO. IPTU (2/5). SEGURO (2/6). | M6: 10 | N6: 11
A7: IRAN | B7: 17 | C7: ='GERAL 2022'!G41 -> 580 | D7: 0 | E7: =C7-D7 -> 580 | F7: 0 | G7: =D80 -> 2.8368085 | H7: =D79 -> 19.696667 | I7: =SUM(E7:H7) -> 602.53348 | J7: =60%*(C7+F7) -> 348 | K7: =I7-J7 -> 254.53348 | L7: SEM DESCONTO. IPTU (2/5). SEGURO (2/6). | M7: 10 | N7: 11
A8: TOTAL | C8: =SUM(C4:C7) -> 2260 | D8: =SUM(D4:D7) -> 0 | E8: =SUM(E4:E7) -> 2260 | F8: =SUM(F4:F7) -> 125 | G8: =SUM(G4:G7) -> 11.347234 | H8: =SUM(H4:H7) -> 78.676667 | I8: =SUM(I4:I7) -> 2475.0239 | J8: =SUM(J4:J7) -> 1431 | K8: =SUM(K4:K7) -> 1044.0239
A10: VIGÊNCIA DE JULHO 2022
A11: NOME | B11: APTO | C11: ALUGUEL | D11: DESCONTO | E11: ALUGUEL C/ DESCONTO | F11: GARAGEM | G11: IPTU | H11: SEG INC. | I11: TOTAL | J11: COMISSÃO | K11: REPASSE | L11: OBSERVAÇÃO | M11: VENC. | N11: CARÊNCIA
A12: ELISON | B12: 1 | C12: 0 | D12: 0 | E12: =C12-D12 -> 0 | F12: 0 | G12: 0 | H12: 0 | I12: =SUM(E12:H12) -> 0 | J12: =7%*I12 -> 0 | K12: =I12-J12 -> 0 | L12: INTERMEDIAÇÃO | M12: 10 | N12: 11
A13: FÁTIMA E RAFAELA | B13: 2 | C13: ='GERAL 2022'!G4/31*12 -> 224.51613 | D13: 0 | E13: =C13-D13 -> 224.51613 | F13: =50/31*12 -> 19.354839 | G13: =D50/31*12 -> 1.0981194 | H13: =D49 -> 19.696667 | I13: =SUM(E13:H13) -> 264.66575 | J13: =7%*I13 -> 18.526603 | K13: =I13-J13 -> 246.13915 | L13: PROPORCIONAL DE 12 DIAS (20/07 A 31/07). SEM DESCONTO. IPTU (1/5). SEGURO (1/6). | M13: 10 | N13: 11
A14: LETICIA | B14: 3 | C14: ='GERAL 2022'!G5/31*4 -> 70.967742 | D14: 0 | E14: =C14-D14 -> 70.967742 | F14: 0 | G14: =D52/31*4 -> 0.36603981 | H14: 19.65 | I14: =SUM(E14:H14) -> 90.983782 | J14: =7%*I14 -> 6.3688647 | K14: =I14-J14 -> 84.614917 | L14: PROPORCIONAL DE 04 DIAS (28/07 A 31/07). SEM DESCONTO. IPTU (1/5). SEGURO (1/6). | M14: 10 | N14: 11
A15: AMANDA | B15: 4 | C15: ='GERAL 2022'!G16 -> 550 | D15: 0 | E15: =C15-D15 -> 550 | F15: 50 | G15: 0 | H15: =D53 -> 19.641667 | I15: =SUM(E15:H15) -> 619.64167 | J15: =7%*I15 -> 43.374917 | K15: =I15-J15 -> 576.26675 | L15: SEM DESCONTO. IPTU QUITADO. SEGURO (6/6). | M15: 10 | N15: 11
A16: DAVID ÂNGELO | B16: 5 | C16: ='GERAL 2022'!G7 -> 580 | D16: 0 | E16: =C16-D16 -> 580 | F16: 50 | G16: =D56 -> 2.8368085 | H16: =D55 -> 19.696667 | I16: =SUM(E16:H16) -> 652.53348 | J16: =7%*I16 -> 45.677343 | K16: =I16-J16 -> 606.85613 | L16: SEM DESCONTO. IPTU (1/5). SEGURO (1/6). | M16: 10 | N16: 11
A17: LIGIA | B17: 6 | C17: ='GERAL 2022'!G8 -> 650 | D17: 0 | E17: =C17-D17 -> 650 | F17: 25 | G17: =D58 -> 3.9715319 | H17: =D57 -> 19.836667 | I17: =SUM(E17:H17) -> 698.8082 | J17: =7%*I17 -> 48.916574 | K17: =I17-J17 -> 649.89162 | L17: SEM DESCONTO. IPTU (5/5). SEGURO (5/6). | M17: 10 | N17: 11
A18: ALEXANDER | B18: 7 | C18: ='GERAL 2022'!G9/31*26 -> 486.45161 | D18: 0 | E18: =C18-D18 -> 486.45161 | F18: =50/31*26 -> 41.935484 | G18: =D60/31*26 -> 2.3792588 | H18: =D59 -> 19.696667 | I18: =SUM(E18:H18) -> 550.46302 | J18: =7%*I18 -> 38.532412 | K18: =I18-J18 -> 511.93061 | L18: PROPORCIONAL DE 26 DIAS (06/07 A 31/07). SEM DESCONTO. IPTU (1/5). SEGURO (1/6). | M18: 10 | N18: 11
A19: ARMANDO | B19: 8 | C19: ='GERAL 2022'!G10 -> 610 | D19: 0 | E19: =C19-D19 -> 610 | F19: =50/31*11 -> 17.741935 | G19: 0 | H19: =D61 -> 19.755 | I19: =SUM(E19:H19) -> 647.49694 | J19: =7%*I19 -> 45.324785 | K19: =I19-J19 -> 602.17215 | L19: GARAGEM PROPORCIONAL DE 11 DIAS (01/07 A 11/07). SEM DESCONTO. IPTU QUITADO. SEGURO (6/6). | M19: 10 | N19: 11
A20: ALCIDES / RENÊ | B20: 9 | C20: ='GERAL 2022'!G11 -> 580 | D20: 0 | E20: =C20-D20 -> 580 | F20: =25+(25/31*6) -> 29.83871 | G20: 0 | H20: 0 | I20: =SUM(E20:H20) -> 609.83871 | J20: =7%*I20 -> 42.68871 | K20: =I20-J20 -> 567.15 | L20: 01 GARAGEM PROPORCIONAL DE 06 DIAS (01/07 A 06/07). SEM DESCONTO. IPTU QUITADO. SEGURO QUITADO. | M20: 10 | N20: 11
A21: JAÍNE | B21: 10 | C21: 0 | D21: 0 | E21: =C21-D21 -> 0 | F21: 0 | G21: 0 | H21: 0 | I21: =SUM(E21:H21) -> 0 | J21: =7%*I21 -> 0 | K21: =I21-J21 -> 0 | L21: INTERMEDIAÇÃO | M21: 10 | N21: 11
A22: JOCÉLIO | B22: 11 | C22: ='GERAL 2022'!G13 -> 550 | D22: 0 | E22: =C22-D22 -> 550 | F22: 0 | G22: =D68 -> 2.8368085 | H22: =D67 -> 19.641667 | I22: =SUM(E22:H22) -> 572.47848 | J22: =7%*I22 -> 40.073493 | K22: =I22-J22 -> 532.40498 | L22: SEM DESCONTO. IPTU (4/5). SEGURO (4/6). | M22: 10 | N22: 11
A23: DAVID/FÁTIMA | B23: 12 | C23: 0 | D23: 0 | E23: =C23-D23 -> 0 | F23: 0 | G23: 0 | H23: 0 | I23: =SUM(E23:H23) -> 0 | J23: =7%*I23 -> 0 | K23: =I23-J23 -> 0 | L23: INTERMEDIAÇÃO | M23: 10 | N23: 11
A24: MARLON | B24: 13 | C24: ='GERAL 2022'!G15 -> 550 | D24: 0 | E24: =C24-D24 -> 550 | F24: 0 | G24: =D72 -> 2.8368085 | H24: =D71 -> 19.641667 | I24: =SUM(E24:H24) -> 572.47848 | J24: =7%*I24 -> 40.073493 | K24: =I24-J24 -> 532.40498 | L24: IPTU (3/5). SEGURO (3/6). | M24: 10 | N24: 11
A25: HOSANA | B25: 14 | C25: ='GERAL 2022'!G16 -> 550 | D25: 0 | E25: =C25-D25 -> 550 | F25: 0 | G25: =D74 -> 2.8368085 | H25: =D73 -> 19.641667 | I25: =SUM(E25:H25) -> 572.47848 | J25: =7%*I25 -> 40.073493 | K25: =I25-J25 -> 532.40498 | L25: SEM DESCONTO. IPTU (5/5). SEGURO (5/6). | M25: 10 | N25: 11
A26: BIANCA | B26: 15 | C26: ='GERAL 2022'!G40 -> 650 | D26: 0 | E26: =C26-D26 -> 650 | F26: 25 | G26: 0 | H26: =D75 -> 19.836667 | I26: =SUM(E26:H26) -> 694.83667 | J26: =7%*I26 -> 48.638567 | K26: =I26-J26 -> 646.1981 | L26: SEM DESCONTO. IPTU QUITADO. SEGURO (6/6). | M26: 10 | N26: 11
A27: VANESSA | B27: 16 | C27: ='GERAL 2022'!G18+(10.72339%*640) -> 708.6297 | E27: =C27-D27 -> 708.6297 | F27: =60 -> 60 | G27: 0 | H27: 19.82 | I27: =SUM(E27:H27) -> 788.4497 | J27: =7%*I27 -> 55.191479 | K27: =I27-J27 -> 733.25822 | L27: REAJUSTADO EM JUNHO/2022. IPTU QUITADO. SEGURO (2/6). | M27: 10 | N27: 11
A28: IRAN | B28: 17 | C28: 0 | D28: 0 | E28: =C28-D28 -> 0 | F28: 0 | G28: 0 | H28: 0 | I28: =SUM(E28:H28) -> 0 | J28: =7%*I28 -> 0 | K28: =I28-J28 -> 0 | L28: INTERMEDIAÇÃO | M28: 10 | N28: 11
A29: FREDSON | B29: 18 | C29: ='GERAL 2022'!G20+(10.72339%*650) -> 719.70204 | D29: 0 | E29: =C29-D29 -> 719.70204 | F29: =30 -> 30 | H29: =D81 -> 19.836667 | I29: =SUM(E29:H29) -> 769.5387 | J29: =7%*I29 -> 53.867709 | K29: =I29-J29 -> 715.67099 | L29: REAJUSTADO EM JUNHO/2022. IPTU QUITADO. SEGURO (2/6). | M29: 10 | N29: 11
A30: ERIVANDO | B30: 19 | C30: ='GERAL 2022'!G21 -> 600 | D30: =10%*C30 -> 60 | E30: =(C30-D30) -> 540 | F30: =50 -> 50 | G30: 0 | H30: 0 | I30: =SUM(E30:H30) -> 590 | J30: =7%*I30 -> 41.3 | K30: =I30-J30 -> 548.7 | L30: DESCONTO 10% (12/12). IPTU QUITADO. SEGURO QUITADO. | M30: 10 | N30: 11
A31: RENAN | B31: 20 | C31: ='GERAL 2022'!G22 -> 660 | D31: 0 | E31: =C31-D31 -> 660 | F31: 50 | G31: =D84 -> 2.8368085 | H31: =D85 -> 19.853333 | I31: =SUM(E31:H31) -> 732.69014 | J31: =7%*I31 -> 51.28831 | K31: =I31-J31 -> 681.40183 | L31: IPTU (3/5). SEGURO (3/6). | M31: 10 | N31: 11
A32: KELSON | B32: 21 | C32: ='GERAL 2022'!G23 -> 500 | D32: 0 | E32: =C32-D32 -> 500 | F32: 25 | G32: =D88 -> 2.8368085 | H32: =D87 -> 19.543333 | I32: =SUM(E32:H32) -> 547.38014 | J32: =7%*I32 -> 38.31661 | K32: =I32-J32 -> 509.06353 | L32: IPTU (3/5). SEGURO (3/6). | M32: 10 | N32: 11
A33: MATEUS | B33: 22 | C33: ='GERAL 2022'!G24 -> 500 | D33: 0 | E33: =C33-D33 -> 500 | F33: 25 | G33: =D90 -> 2.8368085 | H33: =D89 -> 19.543333 | I33: =SUM(E33:H33) -> 547.38014 | J33: =7%*I33 -> 38.31661 | K33: =I33-J33 -> 509.06353 | L33: IPTU (3/5). SEGURO (3/6). | M33: 10 | N33: 11
A34: CÍCERO ABEL | B34: 23 | C34: ='GERAL 2022'!G25 -> 550 | D34: 0 | E34: =C34-D34 -> 550 | F34: 0 | G34: =D92 -> 2.8368085 | H34: =D91 -> 19.641667 | I34: =SUM(E34:H34) -> 572.47848 | J34: =7%*I34 -> 40.073493 | K34: =I34-J34 -> 532.40498 | L34: IPTU (3/5). SEGURO (3/6). | M34: 10 | N34: 11
A35: JOÃO LEVI | B35: 24 | C35: ='GERAL 2022'!G26 -> 650 | D35: 0 | E35: =C35-D35 -> 650 | F35: 50 | G35: 0 | H35: =D93 -> 19.836667 | I35: =SUM(E35:H35) -> 719.83667 | J35: =7%*I35 -> 50.388567 | K35: =I35-J35 -> 669.4481 | L35: SEM DESCONTO. IPTU QUITADO. SEGURO (6/6). | M35: 10 | N35: 11
A36: HENRIQUE | B36: 26 | C36: ='GERAL 2022'!G28 -> 560 | D36: 0 | E36: =C36-D36 -> 560 | F36: 25 | G36: =D98 -> 2.8368085 | H36: =D97 -> 19.658333 | I36: =SUM(E36:H36) -> 607.49514 | J36: =7%*I36 -> 42.52466 | K36: =I36-J36 -> 564.97048 | L36: IPTU (3/5). SEGURO (3/6). | M36: 10 | N36: 11
A37: FABIANA | B37: 27 | C37: ='GERAL 2022'!G45 -> 580 | D37: 0 | E37: =C37-D37 -> 580 | F37: 0 | G37: =D100 -> 2.8368085 | H37: =D99 -> 19.696667 | I37: =SUM(E37:H37) -> 602.53348 | J37: =7%*I37 -> 42.177343 | K37: =I37-J37 -> 560.35613 | L37: IPTU (3/5). SEGURO (3/6). | M37: 10 | N37: 11
A38: TOTAL | C38: =SUM(C12:C37) -> 12080.267 | D38: =SUM(D12:D37) -> 60 | E38: =SUM(E12:E37) -> 12020.267 | F38: =SUM(F12:F37) -> 573.87097 | G38: =SUM(G12:G37) -> 36.183035 | H38: =SUM(H12:H37) -> 394.165 | I38: =SUM(I12:I37) -> 13024.486 | J38: =SUM(J12:J37) -> 911.71404 | K38: =SUM(K12:K37) -> 12112.772
A40: INADIMPLÊNCIAS
A41: NOME | B41: APTO | C41: PRINCIPAL | D41: CONDIÇÃO | I41: TOTAL | L41: OBSERVAÇÃO | M41: VENC. | N41: CARÊNCIA
A42: JOÃO PAULO | B42: 1 | C42: =4977.59-1520 -> 3457.59 | D42: R$ 4.977,59 (DÉBITO TOTAL) - R$ 1.520,00 (CAUÇÃO) | I42: =4977.59-1520 -> 3457.59 | L42: DÉBITO ATUALIZADO EM 19/02/2022 (OUT/21 A FEV/22 E MULTA), DIFERENÇA APÓS UTILIZAÇÃO DA CAUÇÃO | M42: 10 | N42: 11
A43: SHIRLEY | B43: 25 | C43: =807.21+30+19.95 -> 857.16 | D43: R$ 807,21 (ALUGUEL) + R$ 30,00 (GARAGEM MOTO) + R$ 19,95 (SEGURO 3/6) | I43: =807.21+30+19.95 -> 857.16 | L43: REAJUSTADO EM MAIO/2022. DESCONTO FINALIZADO. IPTU QUITADO. SEGURO (3/6). | M43: 10 | N43: 11
A44: TOTAL | I44: =SUM(I42:I43) -> 4314.75
A46: OBSERVAÇÕES | L46: COMISSÕES
A47: SEGURO 01 | B47: ='GERAL 2022'!J35 -> 118.18 | C47: 6 | D47: =B47/C47 -> 19.696667 | L47: COMISSÃO 7% | N47: =J38 -> 911.71404
A48: IPTU 01 | B48: ='GERAL 2022'!H35 -> 14.184043 | C48: 5 | D48: =B48/C48 -> 2.8368085 | L48: INTERMEDIAÇÃO 60% | N48: =J8 -> 1431
A49: SEGURO 02 | B49: ='GERAL 2022'!J4 -> 118.18 | C49: 6 | D49: =B49/C49 -> 19.696667
A50: IPTU 02 | B50: ='GERAL 2022'!H4 -> 14.184043 | C50: 5 | D50: =B50/C50 -> 2.8368085
A51: SEGURO 03 | B51: ='GERAL 2022'!J5 -> 117.85 | C51: 6 | D51: =B51/C51 -> 19.641667 | L51: OUTRAS COMISSÕES E DESPESAS
A52: IPTU 03 | B52: ='GERAL 2022'!H5 -> 14.184043 | C52: 5 | D52: =B52/C52 -> 2.8368085 | L52: SEGURO APTO 01 (2/6) | N52: 19.7
A53: SEGURO 04 | B53: ='GERAL 2022'!J6 -> 117.85 | C53: 6 | D53: =B53/C53 -> 19.641667 | L53: SEGURO APTO 02 (1/6) | N53: 19.68
A54: IPTU 04 | B54: ='GERAL 2022'!H6 -> 14.184043 | C54: 5 | D54: =B54/C54 -> 2.8368085 | L54: SEGURO APTO 03 (1/6) | N54: 19.65
A55: SEGURO 05 | B55: ='GERAL 2022'!J7 -> 118.18 | C55: 6 | D55: =B55/C55 -> 19.696667 | L55: SEGURO APTO 04 (6/6) | N55: 19.64
A56: IPTU 05 | B56: ='GERAL 2022'!H7 -> 14.184043 | C56: 5 | D56: =B56/C56 -> 2.8368085 | L56: SEGURO APTO 05 (1/6) | N56: 19.68
A57: SEGURO 06 | B57: ='GERAL 2022'!J8 -> 119.02 | C57: 6 | D57: =B57/C57 -> 19.836667 | L57: SEGURO APTO 06 (5/6) | N57: 19.84
A58: IPTU 06 | B58: ='GERAL 2022'!H8 -> 19.85766 | C58: 5 | D58: =B58/C58 -> 3.9715319 | L58: SEGURO APTO 07 (1/6) | N58: 19.68
A59: SEGURO 07 | B59: ='GERAL 2022'!J9 -> 118.18 | C59: 6 | D59: =B59/C59 -> 19.696667 | L59: SEGURO APTO 08 (6/6) | N59: 19.75
A60: IPTU 07 | B60: ='GERAL 2022'!H9 -> 14.184043 | C60: 5 | D60: =B60/C60 -> 2.8368085 | L60: SEGURO APTO 10 (2/6) | N60: 19.64
A61: SEGURO 08 | B61: ='GERAL 2022'!J10 -> 118.53 | C61: 6 | D61: =B61/C61 -> 19.755 | L61: SEGURO APTO 11 (4/6) | N61: 19.64
A62: IPTU 08 | B62: ='GERAL 2022'!H10 -> 14.184043 | C62: 5 | D62: =B62/C62 -> 2.8368085 | L62: SEGURO APTO 12 (2/6) | N62: 19.64
A63: SEGURO 09 | B63: ='GERAL 2022'!J11 -> 118.18 | C63: 6 | D63: =B63/C63 -> 19.696667 | L63: SEGURO APTO 13 (3/6) | N63: 19.64
A64: IPTU 09 | B64: ='GERAL 2022'!H11 -> 14.184043 | C64: 5 | D64: =B64/C64 -> 2.8368085 | L64: SEGURO APTO 14 (5/6) | N64: 19.64
A65: SEGURO 10 | B65: ='GERAL 2022'!J38 -> 117.85 | C65: 6 | D65: =B65/C65 -> 19.641667 | L65: SEGURO APTO 15 (6/6) | N65: 19.84
A66: IPTU 10 | B66: ='GERAL 2022'!H38 -> 14.184043 | C66: 5 | D66: =B66/C66 -> 2.8368085 | L66: SEGURO APTO 16 (2/6) | N66: 19.81
A67: SEGURO 11 | B67: ='GERAL 2022'!J13 -> 117.85 | C67: 6 | D67: =B67/C67 -> 19.641667 | L67: SEGURO APTO 17 (2/6) | N67: 19.7
A68: IPTU 11 | B68: ='GERAL 2022'!H13 -> 14.184043 | C68: 5 | D68: =B68/C68 -> 2.8368085 | L68: SEGURO APTO 18 (2/6) | N68: 19.84
A69: SEGURO 12 | B69: ='GERAL 2022'!J14 -> 117.85 | C69: 6 | D69: =B69/C69 -> 19.641667 | L69: SEGURO APTO 20 (3/6) | N69: 19.85
A70: IPTU 12 | B70: ='GERAL 2022'!H14 -> 14.184043 | C70: 5 | D70: =B70/C70 -> 2.8368085 | L70: SEGURO APTO 21 (3/6) | N70: 19.54
A71: SEGURO 13 | B71: ='GERAL 2022'!J15 -> 117.85 | C71: 6 | D71: =B71/C71 -> 19.641667 | L71: SEGURO APTO 22 (3/6) | N71: 19.54
A72: IPTU 13 | B72: ='GERAL 2022'!H15 -> 14.184043 | C72: 5 | D72: =B72/C72 -> 2.8368085 | L72: SEGURO APTO 23 (3/6) | N72: 19.64
A73: SEGURO 14 | B73: ='GERAL 2022'!J16 -> 117.85 | C73: 6 | D73: =B73/C73 -> 19.641667 | L73: SEGURO APTO 24 (6/6) | N73: 19.84
A74: IPTU 14 | B74: ='GERAL 2022'!H16 -> 14.184043 | C74: 5 | D74: =B74/C74 -> 2.8368085 | L74: SEGURO APTO 25 (3/6) | N74: 19.93
A75: SEGURO 15 | B75: ='GERAL 2022'!J40 -> 119.02 | C75: 6 | D75: =B75/C75 -> 19.836667 | L75: SEGURO APTO 26 (3/6) | N75: 19.66
A76: IPTU 15 | B76: ='GERAL 2022'!H40 -> 19.85766 | C76: 5 | D76: =B76/C76 -> 3.9715319 | L76: SEGURO APTO 27 (3/6) | N76: 19.7
A77: SEGURO 16 | B77: ='GERAL 2022'!J18 -> 118.87 | C77: 6 | D77: =B77/C77 -> 19.811667 | L77: 05 LIMPEZAS (02/07/2022 - 09/07/2022 - 16/07/2022 - 23/07/2022 - 30/07/2022) | N77: =120*5 -> 600
A78: IPTU 16 | B78: ='GERAL 2022'!H18 -> 14.184043 | C78: 5 | D78: =B78/C78 -> 2.8368085 | L78: RECONHECIMENTOS DE FIRMA CONTRATO APTO 02, 03, 05 E 07 | N78: =8.77*4 -> 35.08
A79: SEGURO 17 | B79: ='GERAL 2022'!J41 -> 118.18 | C79: 6 | D79: =B79/C79 -> 19.696667 | L79: ENEL | N79: 125.73
A80: IPTU 17 | B80: ='GERAL 2022'!H41 -> 14.184043 | C80: 5 | D80: =B80/C80 -> 2.8368085 | L80: MATERIAL DE LIMPEZA | N80: 48.52
A81: SEGURO 18 | B81: ='GERAL 2022'!J20 -> 119.02 | C81: 6 | D81: =B81/C81 -> 19.836667 | L81: CONSERTO FECHADURA TETRA | N81: 350
A82: IPTU 18 | B82: ='GERAL 2022'!H20 -> 14.184043 | C82: 5 | D82: =B82/C82 -> 2.8368085 | L82: CAGECE SEM FATURA
A83: SEGURO 19 | B83: ='GERAL 2022'!J21 -> 118.43 | C83: 6 | D83: =B83/C83 -> 19.738333
A84: IPTU 19 | B84: ='GERAL 2022'!H21 -> 14.184043 | C84: 5 | D84: =B84/C84 -> 2.8368085
A85: SEGURO 20 | B85: ='GERAL 2022'!J22 -> 119.12 | C85: 6 | D85: =B85/C85 -> 19.853333
A86: IPTU 20 | B86: ='GERAL 2022'!H22 -> 14.184043 | C86: 5 | D86: =B86/C86 -> 2.8368085
A87: SEGURO 21 | B87: ='GERAL 2022'!J23 -> 117.26 | C87: 6 | D87: =B87/C87 -> 19.543333
A88: IPTU 21 | B88: ='GERAL 2022'!H23 -> 14.184043 | C88: 5 | D88: =B88/C88 -> 2.8368085 | L88: TOTAL COMISSÃO + DESPESAS | N88: =SUM(N47:N87) -> 3994.754
A89: SEGURO 22 | B89: ='GERAL 2022'!J24 -> 117.26 | C89: 6 | D89: =B89/C89 -> 19.543333
A90: IPTU 22 | B90: ='GERAL 2022'!H24 -> 14.184043 | C90: 5 | D90: =B90/C90 -> 2.8368085 | L90: R$ RECEBIDOS EM NOME DO LOCADOR | N90: =I38+I8 -> 15499.51
A91: SEGURO 23 | B91: ='GERAL 2022'!J25 -> 117.85 | C91: 6 | D91: =B91/C91 -> 19.641667
A92: IPTU 23 | B92: ='GERAL 2022'!H25 -> 14.184043 | C92: 5 | D92: =B92/C92 -> 2.8368085 | L92: TOTAL A REPASSAR | N92: =N90-N88 -> 11504.756
A93: SEGURO 24 | B93: ='GERAL 2022'!J26 -> 119.02 | C93: 6 | D93: =B93/C93 -> 19.836667
A94: IPTU 24 | B94: ='GERAL 2022'!H26 -> 19.85766 | C94: 5 | D94: =B94/C94 -> 3.9715319
A95: SEGURO 25 | B95: ='GERAL 2022'!J27 -> 119.7 | C95: 6 | D95: =B95/C95 -> 19.95
A96: IPTU 25 | B96: ='GERAL 2022'!H27 -> 14.184043 | C96: 5 | D96: =B96/C96 -> 2.8368085
A97: SEGURO 26 | B97: ='GERAL 2022'!J28 -> 117.95 | C97: 6 | D97: =B97/C97 -> 19.658333
A98: IPTU 26 | B98: ='GERAL 2022'!H28 -> 14.184043 | C98: 5 | D98: =B98/C98 -> 2.8368085
A99: SEGURO 27 | B99: ='GERAL 2022'!J45 -> 118.18 | C99: 6 | D99: =B99/C99 -> 19.696667
A100: IPTU 27 | B100: ='GERAL 2022'!H45 -> 14.184043 | C100: 5 | D100: =B100/C100 -> 2.8368085

Sheet VIGÊNCIA AGOSTO 2022
A1: GRAND MESSEJANA II
A2: INTERMEDIAÇÕES DE JULHO DE 2022
A3: NOME | B3: APTO | C3: ALUGUEL | D3: DESCONTO | E3: ALUGUEL C/ DESCONTO | F3: GARAGEM | G3: IPTU | H3: SEG INC. | I3: TOTAL | J3: COMISSÃO | K3: REPASSE | L3: OBSERVAÇÃO | M3: VENC. | N3: CARÊNCIA
A4: FÁTIMA E RAFAELA | B4: 2 | C4: ='GERAL 2022'!G4 -> 580 | D4: 0 | E4: =C4-D4 -> 580 | F4: =50 -> 50 | G4: =D59 -> 2.8368085 | H4: =D58 -> 19.696667 | I4: =SUM(E4:H4) -> 652.53348 | J4: =60%*(C4+F4) -> 378 | K4: =I4-J4 -> 274.53348 | L4: SEM DESCONTO. IPTU (2/5). SEGURO (2/6). | M4: 10 | N4: 11
A5: LETICIA | B5: 3 | C5: ='GERAL 2022'!G5 -> 550 | D5: 0 | E5: =C5-D5 -> 550 | F5: 0 | G5: =D61 -> 2.8368085 | H5: =D60 -> 19.641667 | I5: =SUM(E5:H5) -> 572.47848 | J5: =60%*(C5+F5) -> 330 | K5: =I5-J5 -> 242.47848 | L5: SEM DESCONTO. IPTU (2/5). SEGURO (2/6). | M5: 10 | N5: 11
A6: DAVID ÂNGELO | B6: 5 | C6: ='GERAL 2022'!G7 -> 580 | D6: 0 | E6: =C6-D6 -> 580 | F6: 50 | G6: =D65 -> 2.8368085 | H6: =D64 -> 19.696667 | I6: =SUM(E6:H6) -> 652.53348 | J6: =60%*(C6+F6) -> 378 | K6: =I6-J6 -> 274.53348 | L6: SEM DESCONTO. IPTU (2/5). SEGURO (2/6). | M6: 10 | N6: 11
A7: ALEXANDER | B7: 7 | C7: ='GERAL 2022'!G9 -> 580 | D7: 0 | E7: =C7-D7 -> 580 | F7: =50 -> 50 | G7: =D69 -> 2.8368085 | H7: =D68 -> 19.696667 | I7: =SUM(E7:H7) -> 652.53348 | J7: =60%*(C7+F7) -> 378 | K7: =I7-J7 -> 274.53348 | L7: SEM DESCONTO. IPTU (2/5). SEGURO (2/6). | M7: 10 | N7: 11
A8: TOTAL | C8: =SUM(C4:C7) -> 2290 | D8: =SUM(D4:D7) -> 0 | E8: =SUM(E4:E7) -> 2290 | F8: =SUM(F4:F7) -> 150 | G8: =SUM(G4:G7) -> 11.347234 | H8: =SUM(H4:H7) -> 78.731667 | I8: =SUM(I4:I7) -> 2530.0789 | J8: =SUM(J4:J7) -> 1464 | K8: =SUM(K4:K7) -> 1066.0789
A10: VIGÊNCIA DE AGOSTO 2022
A11: NOME | B11: APTO | C11: ALUGUEL | D11: DESCONTO | E11: ALUGUEL C/ DESCONTO | F11: GARAGEM | G11: IPTU | H11: SEG INC. | I11: TOTAL | J11: COMISSÃO | K11: REPASSE | L11: OBSERVAÇÃO | M11: VENC. | N11: CARÊNCIA
A12: ELISON | B12: 1 | C12: ='GERAL 2022'!G35 -> 580 | D12: 0 | E12: =C12-D12 -> 580 | F12: 50 | G12: =D57 -> 2.8368085 | H12: =D56 -> 19.696667 | I12: =SUM(E12:H12) -> 652.53348 | J12: =7%*I12 -> 45.677343 | K12: =I12-J12 -> 606.85613 | L12: SEM DESCONTO. IPTU (3/5). SEGURO (3/6). | M12: 10 | N12: 11
A13: FÁTIMA E RAFAELA | B13: 2 | C13: 0 | D13: 0 | E13: =C13-D13 -> 0 | F13: 0 | G13: 0 | H13: 0 | I13: =SUM(E13:H13) -> 0 | J13: =7%*I13 -> 0 | K13: =I13-J13 -> 0 | L13: INTERMEDIAÇÃO | M13: 10 | N13: 11
A14: LETICIA | B14: 3 | C14: 0 | D14: 0 | E14: =C14-D14 -> 0 | F14: 0 | G14: 0 | H14: 0 | I14: =SUM(E14:H14) -> 0 | J14: =7%*I14 -> 0 | K14: =I14-J14 -> 0 | L14: INTERMEDIAÇÃO | M14: 10 | N14: 11
A15: AMANDA | B15: 4 | C15: ='GERAL 2022'!G16 -> 550 | D15: 0 | E15: =C15-D15 -> 550 | F15: 50 | G15: 0 | H15: 0 | I15: =SUM(E15:H15) -> 600 | J15: =7%*I15 -> 42 | K15: =I15-J15 -> 558 | L15: SEM DESCONTO. IPTU QUITADO. SEGURO QUITADO. | M15: 10 | N15: 11
A16: DAVID ÂNGELO | B16: 5 | C16: 0 | D16: 0 | E16: =C16-D16 -> 0 | F16: 0 | G16: 0 | H16: 0 | I16: =SUM(E16:H16) -> 0 | J16: =7%*I16 -> 0 | K16: =I16-J16 -> 0 | L16: INTERMEDIAÇÃO | M16: 10 | N16: 11
A17: LIGIA | B17: 6 | C17: ='GERAL 2022'!G8 -> 650 | D17: 0 | E17: =C17-D17 -> 650 | F17: 25 | G17: 0 | H17: =D66 -> 19.836667 | I17: =SUM(E17:H17) -> 694.83667 | J17: =7%*I17 -> 48.638567 | K17: =I17-J17 -> 646.1981 | L17: SEM DESCONTO. IPTU QUITADO. SEGURO (6/6). | M17: 10 | N17: 11
A18: ALEXANDER | B18: 7 | C18: 0 | D18: 0 | E18: =C18-D18 -> 0 | F18: 0 | G18: 0 | H18: 0 | I18: =SUM(E18:H18) -> 0 | J18: =7%*I18 -> 0 | K18: =I18-J18 -> 0 | L18: INTERMEDIAÇÃO | M18: 10 | N18: 11
A19: ARMANDO | B19: 8 | C19: ='GERAL 2022'!G10/31*6 -> 118.06452 | D19: 0 | E19: =C19-D19 -> 118.06452 | F19: 0 | G19: 0 | H19: 0 | I19: =SUM(E19:H19) -> 118.06452 | J19: =7%*I19 -> 8.2645161 | K19: =I19-J19 -> 109.8 | L19: RESCISÃO. PROPORCIONAL DE 06 DIAS (01/08 A 06/08. IPTU QUITADO. SEGURO QUITADO. | M19: 10 | N19: 11
A20: HERBERT | B20: 8 | C20: ='GERAL 2022'!G37/31*26 -> 486.45161 | D20: 0 | E20: =C20-D20 -> 486.45161 | F20: =50/31*26 -> 41.935484 | G20: =D73/31*26 -> 2.3792588 | H20: =D72 -> 19.696667 | I20: =SUM(E20:H20) -> 550.46302 | J20: =7%*I20 -> 38.532412 | K20: =I20-J20 -> 511.93061 | L20: PROPORCIONAL DE 26 DIAS (05/08 A 31/08). IPTU (1/5). SEGURO (1/6). | M20: 10 | N20: 11
A21: ALCIDES / RENÊ | B21: 9 | C21: ='GERAL 2022'!G11 -> 580 | D21: 0 | E21: =C21-D21 -> 580 | F21: =25 -> 25 | G21: 0 | H21: 0 | I21: =SUM(E21:H21) -> 605 | J21: =7%*I21 -> 42.35 | K21: =I21-J21 -> 562.65 | L21: SEM DESCONTO. IPTU QUITADO. SEGURO QUITADO. | M21: 10 | N21: 11
A22: JAÍNE | B22: 10 | C22: ='GERAL 2022'!G38 -> 550 | D22: 0 | E22: =C22-D22 -> 550 | F22: 50 | G22: =D77 -> 2.8368085 | H22: =D76 -> 19.641667 | I22: =SUM(E22:H22) -> 622.47848 | J22: =7%*I22 -> 43.573493 | K22: =I22-J22 -> 578.90498 | L22: SEM DESCONTO. IPTU (3/5). SEGURO (3/6). | M22: 10 | N22: 11
A23: JOCÉLIO | B23: 11 | C23: ='GERAL 2022'!G13 -> 550 | D23: 0 | E23: =C23-D23 -> 550 | F23: 0 | G23: =D79 -> 2.8368085 | H23: =D78 -> 19.641667 | I23: =SUM(E23:H23) -> 572.47848 | J23: =7%*I23 -> 40.073493 | K23: =I23-J23 -> 532.40498 | L23: SEM DESCONTO. IPTU (5/5). SEGURO (5/6). | M23: 10 | N23: 11
A24: DAVID/FÁTIMA | B24: 12 | C24: ='GERAL 2022'!G14 -> 550 | D24: 0 | E24: =C24-D24 -> 550 | F24: 25 | G24: =D81 -> 2.8368085 | H24: =D80 -> 19.641667 | I24: =SUM(E24:H24) -> 597.47848 | J24: =7%*I24 -> 41.823493 | K24: =I24-J24 -> 555.65498 | L24: SEM DESCONTO. IPTU (3/5). SEGURO (3/6). | M24: 10 | N24: 11
A25: MARLON | B25: 13 | C25: ='GERAL 2022'!G15 -> 550 | D25: 0 | E25: =C25-D25 -> 550 | F25: 0 | G25: =D83 -> 2.8368085 | H25: =D82 -> 19.641667 | I25: =SUM(E25:H25) -> 572.47848 | J25: =7%*I25 -> 40.073493 | K25: =I25-J25 -> 532.40498 | L25: SEM DESCONTO. IPTU (4/5). SEGURO (4/6). | M25: 10 | N25: 11
A26: HOSANA | B26: 14 | C26: ='GERAL 2022'!G16 -> 550 | D26: 0 | E26: =C26-D26 -> 550 | F26: 0 | G26: 0 | H26: =D84 -> 19.641667 | I26: =SUM(E26:H26) -> 569.64167 | J26: =7%*I26 -> 39.874917 | K26: =I26-J26 -> 529.76675 | L26: SEM DESCONTO. IPTU QUITADO. SEGURO (6/6). | M26: 10 | N26: 11
A27: BIANCA | B27: 15 | C27: ='GERAL 2022'!G40 -> 650 | D27: 0 | E27: =C27-D27 -> 650 | F27: 25 | G27: 0 | H27: 0 | I27: =SUM(E27:H27) -> 675 | J27: =7%*I27 -> 47.25 | K27: =I27-J27 -> 627.75 | L27: SEM DESCONTO. IPTU QUITADO. SEGURO QUITADO. | M27: 10 | N27: 11
A28: VANESSA | B28: 16 | C28: ='GERAL 2022'!G18+(10.72339%*640) -> 708.6297 | E28: =C28-D28 -> 708.6297 | F28: =60 -> 60 | G28: 0 | H28: 19.82 | I28: =SUM(E28:H28) -> 788.4497 | J28: =7%*I28 -> 55.191479 | K28: =I28-J28 -> 733.25822 | L28: REAJUSTADO EM JUNHO/2022. IPTU QUITADO. SEGURO (3/6). | M28: 10 | N28: 11
A29: IRAN | B29: 17 | C29: ='GERAL 2022'!G41 -> 580 | D29: 0 | E29: =C29-D29 -> 580 | F29: 0 | G29: =D91 -> 2.8368085 | H29: =D90 -> 19.696667 | I29: =SUM(E29:H29) -> 602.53348 | J29: =7%*I29 -> 42.177343 | K29: =I29-J29 -> 560.35613 | L29: SEM DESCONTO. IPTU (3/5). SEGURO (3/6). | M29: 10 | N29: 11
A30: FREDSON | B30: 18 | C30: ='GERAL 2022'!G20+(10.72339%*650) -> 719.70204 | D30: 0 | E30: =C30-D30 -> 719.70204 | F30: =30 -> 30 | H30: =D92 -> 19.836667 | I30: =SUM(E30:H30) -> 769.5387 | J30: =7%*I30 -> 53.867709 | K30: =I30-J30 -> 715.67099 | L30: REAJUSTADO EM JUNHO/2022. IPTU QUITADO. SEGURO (3/6). | M30: 10 | N30: 11
A31: ERIVANDO | B31: 19 | C31: =('GERAL 2022'!G21+(10.07679%*600))/31*29 -> 617.85037 | D31: 0 | E31: =(C31-D31) -> 617.85037 | F31: =50/31*29 -> 46.774194 | G31: 0 | H31: 0 | I31: =SUM(E31:H31) -> 664.62456 | J31: =7%*I31 -> 46.523719 | K31: =I31-J31 -> 618.10084 | L31: RESCISÃO. PROPORCIONAL DE 29 DIAS (01/08 a 29/08). IPTU QUITADO. SEGURO QUITADO. | M31: 10 | N31: 11
A32: SAMUEL | B32: 19 | C32: ='GERAL 2022'!G43/31*6 -> 106.45161 | D32: 0 | E32: =(C32-D32) -> 106.45161 | F32: =50/31*6 -> 9.6774194 | G32: =D97/31*6 -> 0.54905971 | H32: 19.65 | I32: =SUM(E32:H32) -> 136.32809 | J32: =7%*I32 -> 9.5429664 | K32: =I32-J32 -> 126.78513 | L32: PROPORCIONAL DE 06 DIAS (26/08 A 31/08). IPTU (1/5). SEGURO (1/6). | M32: 10 | N32: 11
A33: RENAN | B33: 20 | C33: ='GERAL 2022'!G22 -> 660 | D33: 0 | E33: =C33-D33 -> 660 | F33: 50 | G33: =D95 -> 2.8368085 | H33: =D98 -> 19.853333 | I33: =SUM(E33:H33) -> 732.69014 | J33: =7%*I33 -> 51.28831 | K33: =I33-J33 -> 681.40183 | L33: SEM DESCONTO. IPTU (4/5). SEGURO (4/6). | M33: 10 | N33: 11
A34: KELSON | B34: 21 | C34: ='GERAL 2022'!G23 -> 500 | D34: 0 | E34: =C34-D34 -> 500 | F34: 25 | G34: =D101 -> 2.8368085 | H34: =D100 -> 19.543333 | I34: =SUM(E34:H34) -> 547.38014 | J34: =7%*I34 -> 38.31661 | K34: =I34-J34 -> 509.06353 | L34: SEM DESCONTO. IPTU (4/5). SEGURO (4/6). | M34: 10 | N34: 11
A35: MATEUS | B35: 22 | C35: ='GERAL 2022'!G24 -> 500 | D35: 0 | E35: =C35-D35 -> 500 | F35: 25 | G35: =D103 -> 2.8368085 | H35: =D102 -> 19.543333 | I35: =SUM(E35:H35) -> 547.38014 | J35: =7%*I35 -> 38.31661 | K35: =I35-J35 -> 509.06353 | L35: SEM DESCONTO. IPTU (4/5). SEGURO (4/6). | M35: 10 | N35: 11
A36: CÍCERO ABEL | B36: 23 | C36: ='GERAL 2022'!G25 -> 550 | D36: 0 | E36: =C36-D36 -> 550 | F36: 0 | G36: =D105 -> 2.8368085 | H36: =D104 -> 19.641667 | I36: =SUM(E36:H36) -> 572.47848 | J36: =7%*I36 -> 40.073493 | K36: =I36-J36 -> 532.40498 | L36: SEM DESCONTO. IPTU (4/5). SEGURO (4/6). | M36: 10 | N36: 11
A37: JOÃO LEVI | B37: 24 | C37: ='GERAL 2022'!G26 -> 650 | D37: 0 | E37: =C37-D37 -> 650 | F37: 50 | G37: 0 | H37: 0 | I37: =SUM(E37:H37) -> 700 | J37: =7%*I37 -> 49 | K37: =I37-J37 -> 651 | L37: SEM DESCONTO. IPTU QUITADO. SEGURO QUITADO. | M37: 10 | N37: 11
A38: SHIRLEY | B38: 25 | I38: =SUM(E38:H38) -> 0 | L38: RESCISÃO. INADIMPLÊNCIA. | M38: 10 | N38: 11
A39: HENRIQUE | B39: 26 | C39: ='GERAL 2022'!G28 -> 560 | D39: 0 | E39: =C39-D39 -> 560 | F39: 25 | G39: =D111 -> 2.8368085 | H39: =D110 -> 19.658333 | I39: =SUM(E39:H39) -> 607.49514 | J39: =7%*I39 -> 42.52466 | K39: =I39-J39 -> 564.97048 | L39: SEM DESCONTO. IPTU (4/5). SEGURO (4/6). | M39: 10 | N39: 11
A40: FABIANA | B40: 27 | C40: ='GERAL 2022'!G45 -> 580 | D40: 0 | E40: =C40-D40 -> 580 | F40: 0 | G40: =D113 -> 2.8368085 | H40: =D112 -> 19.696667 | I40: =SUM(E40:H40) -> 602.53348 | J40: =7%*I40 -> 42.177343 | K40: =I40-J40 -> 560.35613 | L40: SEM DESCONTO. IPTU (4/5). SEGURO (4/6). | M40: 10 | N40: 11
A41: TOTAL | C41: =SUM(C12:C40) -> 13097.15 | D41: =SUM(D12:D40) -> 0 | E41: =SUM(E12:E40) -> 13097.15 | F41: =SUM(F12:F40) -> 613.3871 | G41: =SUM(G12:G40) -> 36.970021 | H41: =SUM(H12:H40) -> 354.37833 | I41: =SUM(I12:I40) -> 14101.885 | J41: =SUM(J12:J40) -> 987.13197 | K41: =SUM(K12:K40) -> 13114.753
A43: ACORDOS/RESCISÕES RECEBIDAS EM AGOSTO DE 2022
A44: NOME | B44: APTO | C44: PRINCIPAL | D44: CONDIÇÃO | I44: TOTAL | J44: COMISSÃO | K44: REPASSE | L44: OBSERVAÇÃO | M44: VENC. | N44: CARÊNCIA
A45: ARMANDO | B45: 8 | C45: 1403 | D45: 1x R$ 1.403,00 | I45: 1403 | J45: =7%*I45 -> 98.21 | K45: =I45-J45 -> 1304.79 | L45: MULTA POR RESCISÃO ANTES DO PRAZO. PAGO DIA 03/08/2022. | M45: 10 | N45: 11
A46: ERIVANDO | B46: 19 | C46: 1188.83 | D46: 1x R$ 1.188,83 | I46: 1188.83 | J46: =7%*I46 -> 83.2181 | K46: =I46-J46 -> 1105.6119 | L46: MULTA POR RESCISÃO ANTES DO PRAZO. PAGO DIA 20/08/2022. | M46: 10 | N46: 11
A47: TOTAL | I47: =SUM(I45:I46) -> 2591.83 | J47: =SUM(J45:J46) -> 181.4281 | K47: =SUM(K45:K46) -> 2410.4019
A49: INADIMPLÊNCIAS
A50: NOME | B50: APTO | C50: PRINCIPAL | D50: CONDIÇÃO | I50: TOTAL | L50: OBSERVAÇÃO | M50: VENC. | N50: CARÊNCIA
A51: JOÃO PAULO | B51: 1 | C51: =4977.59-1520 -> 3457.59 | D51: R$ 4.977,59 (DÉBITO TOTAL) - R$ 1.520,00 (CAUÇÃO) | I51: =4977.59-1520 -> 3457.59 | L51: DÉBITO ATUALIZADO EM 19/02/2022 (OUT/21 A FEV/22 E MULTA). | M51: 10 | N51: 11
A52: SHIRLEY | B52: 25 | C52: 3013.33 | D52: MÊS DE JULHO ATUALIZADO, AGOSTO E MULTA POR RESCISÃO ANTES DO PRAZO | I52: 3013.33 | L52: DÉBITO ATUALIZADO EM 30/08/2022 (JULHO, AGOSTO E MULTA POR RESCISÃO ANTES DO PRAZO. | M52: 10 | N52: 11
A53: TOTAL | I53: =SUM(I51:I52) -> 6470.92
A55: OBSERVAÇÕES | L55: COMISSÕES
A56: SEGURO 01 | B56: ='GERAL 2022'!J35 -> 118.18 | C56: 6 | D56: =B56/C56 -> 19.696667 | L56: COMISSÃO 7% | N56: =J41+J47 -> 1168.5601
A57: IPTU 01 | B57: ='GERAL 2022'!H35 -> 14.184043 | C57: 5 | D57: =B57/C57 -> 2.8368085 | L57: INTERMEDIAÇÃO 60% | N57: =J8 -> 1464
A58: SEGURO 02 | B58: ='GERAL 2022'!J4 -> 118.18 | C58: 6 | D58: =B58/C58 -> 19.696667
A59: IPTU 02 | B59: ='GERAL 2022'!H4 -> 14.184043 | C59: 5 | D59: =B59/C59 -> 2.8368085
A60: SEGURO 03 | B60: ='GERAL 2022'!J5 -> 117.85 | C60: 6 | D60: =B60/C60 -> 19.641667 | L60: OUTRAS COMISSÕES E DESPESAS
A61: IPTU 03 | B61: ='GERAL 2022'!H5 -> 14.184043 | C61: 5 | D61: =B61/C61 -> 2.8368085 | L61: SEGURO APTO 01 (3/6) | N61: 19.7
A62: SEGURO 04 | B62: ='GERAL 2022'!J6 -> 117.85 | C62: 6 | D62: =B62/C62 -> 19.641667 | L62: SEGURO APTO 02 (2/6) | N62: 19.7
A63: IPTU 04 | B63: ='GERAL 2022'!H6 -> 14.184043 | C63: 5 | D63: =B63/C63 -> 2.8368085 | L63: SEGURO APTO 03 (2/6) | N63: 19.64
A64: SEGURO 05 | B64: ='GERAL 2022'!J7 -> 118.18 | C64: 6 | D64: =B64/C64 -> 19.696667 | L64: SEGURO APTO 05 (2/6) | N64: 19.7
A65: IPTU 05 | B65: ='GERAL 2022'!H7 -> 14.184043 | C65: 5 | D65: =B65/C65 -> 2.8368085 | L65: SEGURO APTO 06 (6/6) | N65: 19.84
A66: SEGURO 06 | B66: ='GERAL 2022'!J8 -> 119.02 | C66: 6 | D66: =B66/C66 -> 19.836667 | L66: SEGURO APTO 07 (2/6) | N66: 19.7
A67: IPTU 06 | B67: ='GERAL 2022'!H8 -> 19.85766 | C67: 5 | D67: =B67/C67 -> 3.9715319 | L67: SEGURO APTO 08 (1/6) | N67: 19.68
A68: SEGURO 07 | B68: ='GERAL 2022'!J9 -> 118.18 | C68: 6 | D68: =B68/C68 -> 19.696667 | L68: SEGURO APTO 10 (3/6) | N68: 19.64
A69: IPTU 07 | B69: ='GERAL 2022'!H9 -> 14.184043 | C69: 5 | D69: =B69/C69 -> 2.8368085 | L69: SEGURO APTO 11 (5/6) | N69: 19.64
A70: SEGURO 08 | B70: ='GERAL 2022'!J10 -> 118.53 | C70: 6 | D70: =B70/C70 -> 19.755 | L70: SEGURO APTO 12 (3/6) | N70: 19.64
A71: IPTU 08 | B71: ='GERAL 2022'!H10 -> 14.184043 | C71: 5 | D71: =B71/C71 -> 2.8368085 | L71: SEGURO APTO 13 (4/6) | N71: 19.64
A72: SEGURO 08 NOVO | B72: ='GERAL 2022'!J37 -> 118.18 | C72: 6 | D72: =B72/C72 -> 19.696667 | L72: SEGURO APTO 14 (6/6) | N72: 19.64
A73: IPTU 08 NOVO | B73: ='GERAL 2022'!H37 -> 14.184043 | C73: 5 | D73: =B73/C73 -> 2.8368085 | L73: SEGURO APTO 16 (3/6) | N73: 19.81
A74: SEGURO 09 | B74: ='GERAL 2022'!J11 -> 118.18 | C74: 6 | D74: =B74/C74 -> 19.696667 | L74: SEGURO APTO 17 (3/6) | N74: 19.7
A75: IPTU 09 | B75: ='GERAL 2022'!H11 -> 14.184043 | C75: 5 | D75: =B75/C75 -> 2.8368085 | L75: SEGURO APTO 18 (3/6) | N75: 19.84
A76: SEGURO 10 | B76: ='GERAL 2022'!J38 -> 117.85 | C76: 6 | D76: =B76/C76 -> 19.641667 | L76: SEGURO APTO 19 (1/6) | N76: 19.65
A77: IPTU 10 | B77: ='GERAL 2022'!H38 -> 14.184043 | C77: 5 | D77: =B77/C77 -> 2.8368085 | L77: SEGURO APTO 20 (4/6) | N77: 19.85
A78: SEGURO 11 | B78: ='GERAL 2022'!J13 -> 117.85 | C78: 6 | D78: =B78/C78 -> 19.641667 | L78: SEGURO APTO 21 (4/6) | N78: 19.54
A79: IPTU 11 | B79: ='GERAL 2022'!H13 -> 14.184043 | C79: 5 | D79: =B79/C79 -> 2.8368085 | L79: SEGURO APTO 22 (4/6) | N79: 19.54
A80: SEGURO 12 | B80: ='GERAL 2022'!J14 -> 117.85 | C80: 6 | D80: =B80/C80 -> 19.641667 | L80: SEGURO APTO 23 (4/6) | N80: 19.64
A81: IPTU 12 | B81: ='GERAL 2022'!H14 -> 14.184043 | C81: 5 | D81: =B81/C81 -> 2.8368085 | L81: SEGURO APTO 25 (4/6) | N81: 19.93
A82: SEGURO 13 | B82: ='GERAL 2022'!J15 -> 117.85 | C82: 6 | D82: =B82/C82 -> 19.641667 | L82: SEGURO APTO 26 (4/6) | N82: 19.66
A83: IPTU 13 | B83: ='GERAL 2022'!H15 -> 14.184043 | C83: 5 | D83: =B83/C83 -> 2.8368085 | L83: SEGURO APTO 27 (4/6) | N83: 19.7
A84: SEGURO 14 | B84: ='GERAL 2022'!J16 -> 117.85 | C84: 6 | D84: =B84/C84 -> 19.641667 | L84: 04 LIMPEZAS (06/08/2022 - 13/08/2022 - 20/08/2022 - 27/08/2022) | N84: =120*4 -> 480
A85: IPTU 14 | B85: ='GERAL 2022'!H16 -> 14.184043 | C85: 5 | D85: =B85/C85 -> 2.8368085 | L85: RECONHECIMENTOS DE FIRMA CONTRATO APTO 8 E 19 | N85: =8.77*2 -> 17.54
A86: SEGURO 15 | B86: ='GERAL 2022'!J40 -> 119.02 | C86: 6 | D86: =B86/C86 -> 19.836667 | L86: ENEL | N86: 129.58
A87: IPTU 15 | B87: ='GERAL 2022'!H40 -> 19.85766 | C87: 5 | D87: =B87/C87 -> 3.9715319 | L87: CAGECE SEM FATURA
A88: SEGURO 16 | B88: ='GERAL 2022'!J18 -> 118.87 | C88: 6 | D88: =B88/C88 -> 19.811667 | L88: CONFECÇÃO CHAVE MOTOR PORTÃO | N88: 120
A89: IPTU 16 | B89: ='GERAL 2022'!H18 -> 14.184043 | C89: 5 | D89: =B89/C89 -> 2.8368085 | L89: SERVIÇO FECHADURA TETRA | N89: 100
A90: SEGURO 17 | B90: ='GERAL 2022'!J41 -> 118.18 | C90: 6 | D90: =B90/C90 -> 19.696667 | L90: MANUTENÇÃO PORTÃO GARAGEM | N90: 320
A91: IPTU 17 | B91: ='GERAL 2022'!H41 -> 14.184043 | C91: 5 | D91: =B91/C91 -> 2.8368085
A92: SEGURO 18 | B92: ='GERAL 2022'!J20 -> 119.02 | C92: 6 | D92: =B92/C92 -> 19.836667
A93: IPTU 18 | B93: ='GERAL 2022'!H20 -> 14.184043 | C93: 5 | D93: =B93/C93 -> 2.8368085
A94: SEGURO 19 | B94: ='GERAL 2022'!J21 -> 118.43 | C94: 6 | D94: =B94/C94 -> 19.738333
A95: IPTU 19 | B95: ='GERAL 2022'!H21 -> 14.184043 | C95: 5 | D95: =B95/C95 -> 2.8368085 | L95: TOTAL COMISSÃO + DESPESAS | N95: =SUM(N56:N94) -> 4252.7001
A96: SEGURO 19 NOVO | B96: ='GERAL 2022'!J43 -> 117.85 | C96: 6 | D96: =B96/C96 -> 19.641667
A97: IPTU 19 NOVO | B97: ='GERAL 2022'!H43 -> 14.184043 | C97: 5 | D97: =B97/C97 -> 2.8368085 | L97: R$ RECEBIDOS EM NOME DO LOCADOR | N97: =I41+I8+I47 -> 19223.794
A98: SEGURO 20 | B98: ='GERAL 2022'!J22 -> 119.12 | C98: 6 | D98: =B98/C98 -> 19.853333
A99: IPTU 20 | B99: ='GERAL 2022'!H22 -> 14.184043 | C99: 5 | D99: =B99/C99 -> 2.8368085 | L99: TOTAL A REPASSAR | N99: =N97-N95 -> 14971.094
A100: SEGURO 21 | B100: ='GERAL 2022'!J23 -> 117.26 | C100: 6 | D100: =B100/C100 -> 19.543333 | L100: VALOR REPASSADO | N100: 15152.52
A101: IPTU 21 | B101: ='GERAL 2022'!H23 -> 14.184043 | C101: 5 | D101: =B101/C101 -> 2.8368085 | L101: CRÉDITO DA IMOBILIÁRIA A SER ACERTADO NA VIGÊNCIA DE SETEMBRO | N101: =N100-N99 -> 181.42588
A102: SEGURO 22 | B102: ='GERAL 2022'!J24 -> 117.26 | C102: 6 | D102: =B102/C102 -> 19.543333
A103: IPTU 22 | B103: ='GERAL 2022'!H24 -> 14.184043 | C103: 5 | D103: =B103/C103 -> 2.8368085
A104: SEGURO 23 | B104: ='GERAL 2022'!J25 -> 117.85 | C104: 6 | D104: =B104/C104 -> 19.641667
...

Sheet VIGÊNCIA SETEMBRO 2022
A1: GRAND MESSEJANA II
A2: INTERMEDIAÇÕES DE AGOSTO DE 2022
A3: NOME | B3: APTO | C3: ALUGUEL | D3: DESCONTO | E3: ALUGUEL C/ DESCONTO | F3: GARAGEM | G3: IPTU | H3: SEG INC. | I3: TOTAL | J3: COMISSÃO | K3: REPASSE | L3: OBSERVAÇÃO | M3: VENC. | N3: CARÊNCIA
A4: HERBERT | B4: 8 | C4: ='GERAL 2022'!G37 -> 580 | D4: 0 | E4: =C4-D4 -> 580 | F4: 50 | G4: =D67 -> 2.8368085 | H4: =D66 -> 19.696667 | I4: =SUM(E4:H4) -> 652.53348 | J4: =60%*(C4+F4) -> 378 | K4: =I4-J4 -> 274.53348 | L4: SEM DESCONTO. IPTU (2/5). SEGURO (2/6). | M4: 10 | N4: 11
A5: SAMUEL | B5: 19 | C5: ='GERAL 2022'!G43 -> 550 | D5: 0 | E5: =C5-D5 -> 550 | F5: 50 | G5: =D89 -> 2.8368085 | H5: =D88 -> 19.641667 | I5: =SUM(E5:H5) -> 622.47848 | J5: =60%*(C5+F5) -> 360 | K5: =I5-J5 -> 262.47848 | L5: SEM DESCONTO. IPTU (2/5). SEGURO (2/6). | M5: 10 | N5: 11
A6: TOTAL | C6: =SUM(C4:C5) -> 1130 | D6: =SUM(D4:D5) -> 0 | E6: =SUM(E4:E5) -> 1130 | F6: =SUM(F4:F5) -> 100 | G6: =SUM(G4:G5) -> 5.673617 | H6: =SUM(H4:H5) -> 39.338333 | I6: =SUM(I4:I5) -> 1275.012 | J6: =SUM(J4:J5) -> 738 | K6: =SUM(K4:K5) -> 537.01195
A8: VIGÊNCIA DE SETEMBRO 2022
A9: NOME | B9: APTO | C9: ALUGUEL | D9: DESCONTO | E9: ALUGUEL C/ DESCONTO | F9: GARAGEM | G9: IPTU | H9: SEG INC. | I9: TOTAL | J9: COMISSÃO | K9: REPASSE | L9: OBSERVAÇÃO | M9: VENC. | N9: CARÊNCIA
A10: ELISON | B10: 1 | C10: ='GERAL 2022'!G35 -> 580 | D10: 0 | E10: =C10-D10 -> 580 | F10: 50 | G10: =D53 -> 2.8368085 | H10: =D52 -> 19.696667 | I10: =SUM(E10:H10) -> 652.53348 | J10: =7%*I10 -> 45.677343 | K10: =I10-J10 -> 606.85613 | L10: SEM DESCONTO. IPTU (4/5). SEGURO (4/6). | M10: 10 | N10: 11
A11: FÁTIMA E RAFAELA | B11: 2 | C11: ='GERAL 2022'!G4 -> 580 | D11: 0 | E11: =C11-D11 -> 580 | F11: 50 | G11: =D55 -> 2.8368085 | H11: =D54 -> 19.696667 | I11: =SUM(E11:H11) -> 652.53348 | J11: =7%*I11 -> 45.677343 | K11: =I11-J11 -> 606.85613 | L11: SEM DESCONTO. IPTU (3/5). SEGURO (3/6). | M11: 10 | N11: 11
A12: LETICIA | B12: 3 | C12: ='GERAL 2022'!G5 -> 550 | D12: 0 | E12: =C12-D12 -> 550 | F12: 0 | G12: =D57 -> 2.8368085 | H12: =D56 -> 19.641667 | I12: =SUM(E12:H12) -> 572.47848 | J12: =7%*I12 -> 40.073493 | K12: =I12-J12 -> 532.40498 | L12: SEM DESCONTO. IPTU (3/5). SEGURO (3/6). | M12: 10 | N12: 11
A13: AMANDA | B13: 4 | C13: ='GERAL 2022'!G16 -> 550 | D13: 0 | E13: =C13-D13 -> 550 | F13: 50 | G13: 0 | H13: 0 | I13: =SUM(E13:H13) -> 600 | J13: =7%*I13 -> 42 | K13: =I13-J13 -> 558 | L13: SEM DESCONTO. IPTU QUITADO. SEGURO QUITADO. | M13: 10 | N13: 11
A14: DAVID ÂNGELO | B14: 5 | C14: 0 | D14: 0 | E14: =C14-D14 -> 0 | F14: 0 | G14: 0 | H14: 0 | I14: =SUM(E14:H14) -> 0 | J14: =7%*I14 -> 0 | K14: =I14-J14 -> 0 | L14: INADIMPLÊNCIA | M14: 10 | N14: 11
A15: LIGIA | B15: 6 | C15: ='GERAL 2022'!G8 -> 650 | D15: 0 | E15: =C15-D15 -> 650 | F15: 25 | G15: 0 | H15: 0 | I15: =SUM(E15:H15) -> 675 | J15: =7%*I15 -> 47.25 | K15: =I15-J15 -> 627.75 | L15: RESCISÃO. SEM DESCONTO. IPTU QUITADO. SEGURO QUITADO. | M15: 10 | N15: 11
A16: ALEXANDER | B16: 7 | C16: ='GERAL 2022'!G9 -> 580 | D16: 0 | E16: =C16-D16 -> 580 | F16: 50 | G16: =D65 -> 2.8368085 | H16: =D64 -> 19.696667 | I16: =SUM(E16:H16) -> 652.53348 | J16: =7%*I16 -> 45.677343 | K16: =I16-J16 -> 606.85613 | L16: SEM DESCONTO. IPTU (3/5). SEGURO (3/6). | M16: 10 | N16: 11
A17: HERBERT | B17: 8 | C17: 0 | D17: 0 | E17: =C17-D17 -> 0 | F17: 0 | G17: 0 | H17: 0 | I17: =SUM(E17:H17) -> 0 | J17: =7%*I17 -> 0 | K17: =I17-J17 -> 0 | L17: INTERMEDIAÇÃO | M17: 10 | N17: 11
A18: ALCIDES / RENÊ | B18: 9 | C18: ='GERAL 2022'!G11 -> 580 | D18: 0 | E18: =C18-D18 -> 580 | F18: =25 -> 25 | G18: 0 | H18: 0 | I18: =SUM(E18:H18) -> 605 | J18: =7%*I18 -> 42.35 | K18: =I18-J18 -> 562.65 | L18: SEM DESCONTO. IPTU QUITADO. SEGURO QUITADO. | M18: 10 | N18: 11
A19: JAÍNE | B19: 10 | C19: ='GERAL 2022'!G38 -> 550 | D19: 0 | E19: =C19-D19 -> 550 | F19: 50 | G19: =D71 -> 2.8368085 | H19: =D70 -> 19.641667 | I19: =SUM(E19:H19) -> 622.47848 | J19: =7%*I19 -> 43.573493 | K19: =I19-J19 -> 578.90498 | L19: SEM DESCONTO. IPTU (4/5). SEGURO (4/6). | M19: 10 | N19: 11
A20: JOCÉLIO | B20: 11 | C20: ='GERAL 2022'!G13 -> 550 | D20: 0 | E20: =C20-D20 -> 550 | F20: 0 | G20: 0 | H20: =D72 -> 19.641667 | I20: =SUM(E20:H20) -> 569.64167 | J20: =7%*I20 -> 39.874917 | K20: =I20-J20 -> 529.76675 | L20: SEM DESCONTO. IPTU QUITADO. SEGURO (6/6). | M20: 10 | N20: 11
A21: DAVID/FÁTIMA | B21: 12 | C21: ='GERAL 2022'!G14 -> 550 | D21: 0 | E21: =C21-D21 -> 550 | F21: 25 | G21: =D75 -> 2.8368085 | H21: =D78 -> 19.641667 | I21: =SUM(E21:H21) -> 597.47848 | J21: =7%*I21 -> 41.823493 | K21: =I21-J21 -> 555.65498 | L21: SEM DESCONTO. IPTU (4/5). SEGURO (4/6). | M21: 10 | N21: 11
A22: MARLON | B22: 13 | C22: ='GERAL 2022'!G15 -> 550 | D22: 0 | E22: =C22-D22 -> 550 | F22: 0 | G22: =D77 -> 2.8368085 | H22: =D76 -> 19.641667 | I22: =SUM(E22:H22) -> 572.47848 | J22: =7%*I22 -> 40.073493 | K22: =I22-J22 -> 532.40498 | L22: SEM DESCONTO. IPTU (5/5). SEGURO (5/6). | M22: 10 | N22: 11
A23: HOSANA | B23: 14 | C23: ='GERAL 2022'!G16 -> 550 | D23: 0 | E23: =C23-D23 -> 550 | F23: 0 | G23: 0 | H23: 0 | I23: =SUM(E23:H23) -> 550 | J23: =7%*I23 -> 38.5 | K23: =I23-J23 -> 511.5 | L23: SEM DESCONTO. IPTU QUITADO. SEGURO QUITADO. | M23: 10 | N23: 11
A24: BIANCA | B24: 15 | C24: ='GERAL 2022'!G40 -> 650 | D24: 0 | E24: =C24-D24 -> 650 | F24: 25 | G24: 0 | H24: 0 | I24: =SUM(E24:H24) -> 675 | J24: =7%*I24 -> 47.25 | K24: =I24-J24 -> 627.75 | L24: SEM DESCONTO. IPTU QUITADO. SEGURO QUITADO. | M24: 10 | N24: 11
A25: VANESSA | B25: 16 | C25: ='GERAL 2022'!G18+(10.72339%*640) -> 708.6297 | E25: =C25-D25 -> 708.6297 | F25: =60 -> 60 | G25: 0 | H25: 19.82 | I25: =SUM(E25:H25) -> 788.4497 | J25: =7%*I25 -> 55.191479 | K25: =I25-J25 -> 733.25822 | L25: REAJUSTADO EM JUNHO/2022. IPTU QUITADO. SEGURO (4/6). | M25: 10 | N25: 11
A26: IRAN | B26: 17 | C26: ='GERAL 2022'!G41 -> 580 | D26: 0 | E26: =C26-D26 -> 580 | F26: 0 | G26: =D85 -> 2.8368085 | H26: =D84 -> 19.696667 | I26: =SUM(E26:H26) -> 602.53348 | J26: =7%*I26 -> 42.177343 | K26: =I26-J26 -> 560.35613 | L26: SEM DESCONTO. IPTU (4/5). SEGURO (4/6). | M26: 10 | N26: 11
A27: FREDSON | B27: 18 | C27: ='GERAL 2022'!G20+(10.72339%*650) -> 719.70204 | D27: 0 | E27: =C27-D27 -> 719.70204 | F27: =30 -> 30 | H27: =D86 -> 19.836667 | I27: =SUM(E27:H27) -> 769.5387 | J27: =7%*I27 -> 53.867709 | K27: =I27-J27 -> 715.67099 | L27: REAJUSTADO EM JUNHO/2022. IPTU QUITADO. SEGURO (4/6). | M27: 10 | N27: 11
A28: SAMUEL | B28: 19 | C28: 0 | D28: 0 | E28: =(C28-D28) -> 0 | F28: 0 | G28: 0 | H28: 0 | I28: =SUM(E28:H28) -> 0 | J28: =7%*I28 -> 0 | K28: =I28-J28 -> 0 | L28: INTERMEDIAÇÃO | M28: 10 | N28: 11
A29: RENAN | B29: 20 | C29: ='GERAL 2022'!G22 -> 660 | D29: 0 | E29: =C29-D29 -> 660 | F29: 50 | G29: =D91 -> 2.8368085 | H29: =D90 -> 19.853333 | I29: =SUM(E29:H29) -> 732.69014 | J29: =7%*I29 -> 51.28831 | K29: =I29-J29 -> 681.40183 | L29: SEM DESCONTO. IPTU (5/5). SEGURO (5/6). | M29: 10 | N29: 11
A30: KELSON | B30: 21 | C30: ='GERAL 2022'!G23 -> 500 | D30: 0 | E30: =C30-D30 -> 500 | F30: 25 | G30: =D93 -> 2.8368085 | H30: =D92 -> 19.543333 | I30: =SUM(E30:H30) -> 547.38014 | J30: =7%*I30 -> 38.31661 | K30: =I30-J30 -> 509.06353 | L30: SEM DESCONTO. IPTU (5/5). SEGURO (5/6). | M30: 10 | N30: 11
A31: MATEUS | B31: 22 | C31: ='GERAL 2022'!G24 -> 500 | D31: 0 | E31: =C31-D31 -> 500 | F31: 25 | G31: =D95 -> 2.8368085 | H31: =D94 -> 19.543333 | I31: =SUM(E31:H31) -> 547.38014 | J31: =7%*I31 -> 38.31661 | K31: =I31-J31 -> 509.06353 | L31: SEM DESCONTO. IPTU (5/5). SEGURO (5/6). | M31: 10 | N31: 11
A32: CÍCERO ABEL | B32: 23 | C32: ='GERAL 2022'!G25 -> 550 | D32: 0 | E32: =C32-D32 -> 550 | F32: 0 | G32: =D97 -> 2.8368085 | H32: =D96 -> 19.641667 | I32: =SUM(E32:H32) -> 572.47848 | J32: =7%*I32 -> 40.073493 | K32: =I32-J32 -> 532.40498 | L32: SEM DESCONTO. IPTU (5/5). SEGURO (5/6). | M32: 10 | N32: 11
A33: JOÃO LEVI | B33: 24 | C33: ='GERAL 2022'!G26 -> 650 | D33: 0 | E33: =C33-D33 -> 650 | F33: 50 | G33: 0 | H33: 0 | I33: =SUM(E33:H33) -> 700 | J33: =7%*I33 -> 49 | K33: =I33-J33 -> 651 | L33: SEM DESCONTO. IPTU QUITADO. SEGURO QUITADO. | M33: 10 | N33: 11
B34: 25 | I34: =SUM(E34:H34) -> 0 | L34: DESOCUPADO | M34: 10 | N34: 11
A35: HENRIQUE | B35: 26 | C35: ='GERAL 2022'!G28 -> 560 | D35: 0 | E35: =C35-D35 -> 560 | F35: 25 | G35: =D103 -> 2.8368085 | H35: =D102 -> 19.658333 | I35: =SUM(E35:H35) -> 607.49514 | J35: =7%*I35 -> 42.52466 | K35: =I35-J35 -> 564.97048 | L35: SEM DESCONTO. IPTU (5/5). SEGURO (5/6). | M35: 10 | N35: 11
A36: FABIANA | B36: 27 | C36: ='GERAL 2022'!G45 -> 580 | D36: 0 | E36: =C36-D36 -> 580 | F36: 0 | G36: =D105 -> 2.8368085 | H36: =D104 -> 19.696667 | I36: =SUM(E36:H36) -> 602.53348 | J36: =7%*I36 -> 42.177343 | K36: =I36-J36 -> 560.35613 | L36: SEM DESCONTO. IPTU (5/5). SEGURO (5/6). | M36: 10 | N36: 11
A37: TOTAL | C37: =SUM(C10:C36) -> 13478.332 | D37: =SUM(D10:D36) -> 0 | E37: =SUM(E10:E36) -> 13478.332 | F37: =SUM(F10:F36) -> 615 | G37: =SUM(G10:G36) -> 39.715319 | H37: =SUM(H10:H36) -> 334.58833 | I37: =SUM(I10:I36) -> 14467.635 | J37: =SUM(J10:J36) -> 1012.7345 | K37: =SUM(K10:K36) -> 13454.901
A39: ACORDOS/RESCISÕES RECEBIDAS EM SETEMBRO DE 2022
A40: NOME | B40: APTO | C40: PRINCIPAL | D40: CONDIÇÃO | I40: TOTAL | J40: COMISSÃO | K40: REPASSE | L40: OBSERVAÇÃO | M40: VENC. | N40: CARÊNCIA
A41: LIGIA | B41: 6 | C41: 1560 | D41: 01 PARCELA DE R$ 1.560,00 | I41: 1560 | J41: =7%*I41 -> 109.2 | K41: =I41-J41 -> 1450.8 | L41: MULTA POR RESCISÃO ANTES DO PRAZO. PAGAMENTO DIA 26/09/2022. | M41: 10 | N41: 11
A42: TOTAL | I42: =SUM(I41:I41) -> 1560 | J42: =SUM(J41:J41) -> 109.2 | K42: =SUM(K41:K41) -> 1450.8
A44: INADIMPLÊNCIAS
A45: NOME | B45: APTO | C45: PRINCIPAL | D45: CONDIÇÃO | I45: TOTAL | L45: OBSERVAÇÃO | M45: VENC. | N45: CARÊNCIA
A46: JOÃO PAULO | B46: 1 | C46: =4977.59-1520 -> 3457.59 | D46: R$ 4.977,59 (DÉBITO TOTAL) - R$ 1.520,00 (CAUÇÃO) | I46: =4977.59-1520 -> 3457.59 | L46: DÉBITO ATUALIZADO EM 19/02/2022 (OUT/21 A FEV/22 E MULTA). | M46: 10 | N46: 11
A47: SHIRLEY | B47: 25 | C47: 3013.33 | D47: MÊS DE JULHO ATUALIZADO, AGOSTO, MULTA POR RESCISÃO ANTES DO PRAZO E REPAROS | I47: 3040.58 | L47: REFERENTE A JULHO, AGOSTO, MULTA POR RESCISÃO ANTES DO PRAZO E REPAROS. | M47: 10 | N47: 11
A48: DAVID ÂNGELO | B48: 5 | C48: =580+50+2.84+19.7 -> 652.54 | D48: SEM DESCONTO. IPTU (3/5). SEGURO (3/6). | I48: =580+50+2.84+19.7 -> 652.54 | L48: SEM DESCONTO. IPTU (3/5). SEGURO (3/6). | M48: 10 | N48: 11
A49: TOTAL | I49: =SUM(I46:I48) -> 7150.71
A51: OBSERVAÇÕES | L51: COMISSÕES
A52: SEGURO 01 | B52: ='GERAL 2022'!J35 -> 118.18 | C52: 6 | D52: =B52/C52 -> 19.696667 | L52: COMISSÃO 7% | N52: =J37+J42 -> 1121.9345
A53: IPTU 01 | B53: ='GERAL 2022'!H35 -> 14.184043 | C53: 5 | D53: =B53/C53 -> 2.8368085 | L53: INTERMEDIAÇÃO 60% | N53: =J6 -> 738
A54: SEGURO 02 | B54: ='GERAL 2022'!J4 -> 118.18 | C54: 6 | D54: =B54/C54 -> 19.696667
A55: IPTU 02 | B55: ='GERAL 2022'!H4 -> 14.184043 | C55: 5 | D55: =B55/C55 -> 2.8368085
A56: SEGURO 03 | B56: ='GERAL 2022'!J5 -> 117.85 | C56: 6 | D56: =B56/C56 -> 19.641667 | L56: OUTRAS COMISSÕES E DESPESAS
A57: IPTU 03 | B57: ='GERAL 2022'!H5 -> 14.184043 | C57: 5 | D57: =B57/C57 -> 2.8368085 | L57: SEGURO APTO 01 (4/6) | N57: 19.7
A58: SEGURO 04 | B58: ='GERAL 2022'!J6 -> 117.85 | C58: 6 | D58: =B58/C58 -> 19.641667 | L58: SEGURO APTO 02 (3/6) | N58: 19.7
A59: IPTU 04 | B59: ='GERAL 2022'!H6 -> 14.184043 | C59: 5 | D59: =B59/C59 -> 2.8368085 | L59: SEGURO APTO 03 (3/6) | N59: 19.64
A60: SEGURO 05 | B60: ='GERAL 2022'!J7 -> 118.18 | C60: 6 | D60: =B60/C60 -> 19.696667 | L60: SEGURO APTO 05 (3/6) | N60: 19.7
A61: IPTU 05 | B61: ='GERAL 2022'!H7 -> 14.184043 | C61: 5 | D61: =B61/C61 -> 2.8368085 | L61: SEGURO APTO 07 (3/6) | N61: 19.7
A62: SEGURO 06 | B62: ='GERAL 2022'!J8 -> 119.02 | C62: 6 | D62: =B62/C62 -> 19.836667 | L62: SEGURO APTO 08 (2/6) | N62: 19.7
A63: IPTU 06 | B63: ='GERAL 2022'!H8 -> 19.85766 | C63: 5 | D63: =B63/C63 -> 3.9715319 | L63: SEGURO APTO 10 (4/6) | N63: 19.64
A64: SEGURO 07 | B64: ='GERAL 2022'!J9 -> 118.18 | C64: 6 | D64: =B64/C64 -> 19.696667 | L64: SEGURO APTO 11 (6/6) | N64: 19.64
A65: IPTU 07 | B65: ='GERAL 2022'!H9 -> 14.184043 | C65: 5 | D65: =B65/C65 -> 2.8368085 | L65: SEGURO APTO 12 (4/6) | N65: 19.64
A66: SEGURO 08 | B66: ='GERAL 2022'!J37 -> 118.18 | C66: 6 | D66: =B66/C66 -> 19.696667 | L66: SEGURO APTO 13 (5/6) | N66: 19.64
A67: IPTU 08 | B67: ='GERAL 2022'!H37 -> 14.184043 | C67: 5 | D67: =B67/C67 -> 2.8368085 | L67: SEGURO APTO 16 (4/6) | N67: 19.81
A68: SEGURO 09 | B68: ='GERAL 2022'!J11 -> 118.18 | C68: 6 | D68: =B68/C68 -> 19.696667 | L68: SEGURO APTO 17 (4/6) | N68: 19.7
A69: IPTU 09 | B69: ='GERAL 2022'!H11 -> 14.184043 | C69: 5 | D69: =B69/C69 -> 2.8368085 | L69: SEGURO APTO 18 (4/6) | N69: 19.84
A70: SEGURO 10 | B70: ='GERAL 2022'!J38 -> 117.85 | C70: 6 | D70: =B70/C70 -> 19.641667 | L70: SEGURO APTO 19 (2/6) | N70: 19.64
A71: IPTU 10 | B71: ='GERAL 2022'!H38 -> 14.184043 | C71: 5 | D71: =B71/C71 -> 2.8368085 | L71: SEGURO APTO 20 (5/6) | N71: 19.85
A72: SEGURO 11 | B72: ='GERAL 2022'!J13 -> 117.85 | C72: 6 | D72: =B72/C72 -> 19.641667 | L72: SEGURO APTO 21 (5/6) | N72: 19.54
A73: IPTU 11 | B73: ='GERAL 2022'!H13 -> 14.184043 | C73: 5 | D73: =B73/C73 -> 2.8368085 | L73: SEGURO APTO 22 (5/6) | N73: 19.54
A74: SEGURO 12 | B74: ='GERAL 2022'!J14 -> 117.85 | C74: 6 | D74: =B74/C74 -> 19.641667 | L74: SEGURO APTO 23 (5/6) | N74: 19.64
A75: IPTU 12 | B75: ='GERAL 2022'!H14 -> 14.184043 | C75: 5 | D75: =B75/C75 -> 2.8368085 | L75: SEGURO APTO 25 (5/6) | N75: 19.93
A76: SEGURO 13 | B76: ='GERAL 2022'!J15 -> 117.85 | C76: 6 | D76: =B76/C76 -> 19.641667 | L76: SEGURO APTO 26 (5/6) | N76: 19.66
A77: IPTU 13 | B77: ='GERAL 2022'!H15 -> 14.184043 | C77: 5 | D77: =B77/C77 -> 2.8368085 | L77: SEGURO APTO 27 (5/6) | N77: 19.7
A78: SEGURO 14 | B78: ='GERAL 2022'!J16 -> 117.85 | C78: 6 | D78: =B78/C78 -> 19.641667 | L78: 04 LIMPEZAS (03/09/2022 - 10/09/2022 - 17/09/2022 - 24/09/2022) | N78: =120*4 -> 480
A79: IPTU 14 | B79: ='GERAL 2022'!H16 -> 14.184043 | C79: 5 | D79: =B79/C79 -> 2.8368085 | L79: ENEL | N79: 153.6
A80: SEGURO 15 | B80: ='GERAL 2022'!J40 -> 119.02 | C80: 6 | D80: =B80/C80 -> 19.836667 | L80: CAGECE SEM FATURA
A81: IPTU 15 | B81: ='GERAL 2022'!H40 -> 19.85766 | C81: 5 | D81: =B81/C81 -> 3.9715319 | L81: CHAVEIRO: RETIRADA DE CHAVE DA FECHADURA DA PORTA DOS CORREDORES | N81: 120
A82: SEGURO 16 | B82: ='GERAL 2022'!J18 -> 118.87 | C82: 6 | D82: =B82/C82 -> 19.811667 | L82: CONSERTO PORTÃO | N82: 700
A83: IPTU 16 | B83: ='GERAL 2022'!H18 -> 14.184043 | C83: 5 | D83: =B83/C83 -> 2.8368085 | L83: DOCUMENTAÇÃO PARA PROTESTO DÉBITO APTO 25 SHIRLEY | N83: 24.35
A84: SEGURO 17 | B84: ='GERAL 2022'!J41 -> 118.18 | C84: 6 | D84: =B84/C84 -> 19.696667 | L84: DIFERENÇA REPAROS APTO 25 SHIRLEY | N84: 2.9
A85: IPTU 17 | B85: ='GERAL 2022'!H41 -> 14.184043 | C85: 5 | D85: =B85/C85 -> 2.8368085 | L85: CRÉDITO DA IMOBILIÁRIA (ERRO NA VIGÊNCIA DE AGOSTO) | N85: 181.43
A86: SEGURO 18 | B86: ='GERAL 2022'!J20 -> 119.02 | C86: 6 | D86: =B86/C86 -> 19.836667 | L86: TOTAL COMISSÃO + DESPESAS | N86: =SUM(N52:N85) -> 3935.7645
A87: IPTU 18 | B87: ='GERAL 2022'!H20 -> 14.184043 | C87: 5 | D87: =B87/C87 -> 2.8368085
A88: SEGURO 19 | B88: ='GERAL 2022'!J43 -> 117.85 | C88: 6 | D88: =B88/C88 -> 19.641667 | L88: R$ RECEBIDOS EM NOME DO LOCADOR | N88: =I37+I6+I42 -> 17302.647
A89: IPTU 19 | B89: ='GERAL 2022'!H43 -> 14.184043 | C89: 5 | D89: =B89/C89 -> 2.8368085
A90: SEGURO 20 | B90: ='GERAL 2022'!J22 -> 119.12 | C90: 6 | D90: =B90/C90 -> 19.853333 | L90: TOTAL A REPASSAR | N90: =N88-N86 -> 13366.883
A91: IPTU 20 | B91: ='GERAL 2022'!H22 -> 14.184043 | C91: 5 | D91: =B91/C91 -> 2.8368085
A92: SEGURO 21 | B92: ='GERAL 2022'!J23 -> 117.26 | C92: 6 | D92: =B92/C92 -> 19.543333
A93: IPTU 21 | B93: ='GERAL 2022'!H23 -> 14.184043 | C93: 5 | D93: =B93/C93 -> 2.8368085
A94: SEGURO 22 | B94: ='GERAL 2022'!J24 -> 117.26 | C94: 6 | D94: =B94/C94 -> 19.543333
A95: IPTU 22 | B95: ='GERAL 2022'!H24 -> 14.184043 | C95: 5 | D95: =B95/C95 -> 2.8368085
A96: SEGURO 23 | B96: ='GERAL 2022'!J25 -> 117.85 | C96: 6 | D96: =B96/C96 -> 19.641667
A97: IPTU 23 | B97: ='GERAL 2022'!H25 -> 14.184043 | C97: 5 | D97: =B97/C97 -> 2.8368085
A98: SEGURO 24 | B98: ='GERAL 2022'!J26 -> 119.02 | C98: 6 | D98: =B98/C98 -> 19.836667
A99: IPTU 24 | B99: ='GERAL 2022'!H26 -> 19.85766 | C99: 5 | D99: =B99/C99 -> 3.9715319
A100: SEGURO 25 | B100: ='GERAL 2022'!J27 -> 119.7 | C100: 6 | D100: =B100/C100 -> 19.95
A101: IPTU 25 | B101: ='GERAL 2022'!H27 -> 14.184043 | C101: 5 | D101: =B101/C101 -> 2.8368085
A102: SEGURO 26 | B102: ='GERAL 2022'!J28 -> 117.95 | C102: 6 | D102: =B102/C102 -> 19.658333
A103: IPTU 26 | B103: ='GERAL 2022'!H28 -> 14.184043 | C103: 5 | D103: =B103/C103 -> 2.8368085
A104: SEGURO 27 | B104: ='GERAL 2022'!J45 -> 118.18 | C104: 6 | D104: =B104/C104 -> 19.696667
...

Sheet VIGÊNCIA OUTUBRO 2022
A1: GRAND MESSEJANA II
A2: VIGÊNCIA DE OUTUBRO 2022
A3: NOME | B3: APTO | C3: ALUGUEL | D3: DESCONTO | E3: ALUGUEL C/ DESCONTO | F3: GARAGEM | G3: IPTU | H3: SEG INC. | I3: TOTAL | J3: COMISSÃO | K3: REPASSE | L3: OBSERVAÇÃO | M3: VENC. | N3: CARÊNCIA
A4: ELISON | B4: 1 | C4: ='GERAL 2022'!G35 -> 580 | D4: 0 | E4: =C4-D4 -> 580 | F4: 50 | G4: =D48 -> 2.8368085 | H4: =D47 -> 19.696667 | I4: =SUM(E4:H4) -> 652.53348 | J4: =7%*I4 -> 45.677343 | K4: =I4-J4 -> 606.85613 | L4: SEM DESCONTO. IPTU (5/5). SEGURO (5/6). | M4: 10 | N4: 11
A5: FÁTIMA E RAFAELA | B5: 2 | C5: ='GERAL 2022'!G4 -> 580 | D5: 0 | E5: =C5-D5 -> 580 | F5: 50 | G5: =D50 -> 2.8368085 | H5: =D49 -> 19.696667 | I5: =SUM(E5:H5) -> 652.53348 | J5: =7%*I5 -> 45.677343 | K5: =I5-J5 -> 606.85613 | L5: SEM DESCONTO. IPTU (4/5). SEGURO (4/6). | M5: 10 | N5: 11
A6: LETICIA | B6: 3 | C6: ='GERAL 2022'!G5 -> 550 | D6: 0 | E6: =C6-D6 -> 550 | F6: 0 | G6: =D52 -> 2.8368085 | H6: =D51 -> 19.641667 | I6: =SUM(E6:H6) -> 572.47848 | J6: =7%*I6 -> 40.073493 | K6: =I6-J6 -> 532.40498 | L6: SEM DESCONTO. IPTU (4/5). SEGURO (4/6). | M6: 10 | N6: 11
A7: AMANDA | B7: 4 | C7: ='GERAL 2022'!G16 -> 550 | D7: 0 | E7: =C7-D7 -> 550 | F7: 50 | G7: 0 | H7: 0 | I7: =SUM(E7:H7) -> 600 | J7: =7%*I7 -> 42 | K7: =I7-J7 -> 558 | L7: SEM DESCONTO. IPTU QUITADO. SEGURO QUITADO. | M7: 10 | N7: 11
A8: DAVID ÂNGELO | B8: 5 | C8: ='GERAL 2022'!G7 -> 580 | D8: 0 | E8: =C8-D8 -> 580 | F8: 50 | G8: =D56 -> 2.8368085 | H8: =D55 -> 19.696667 | I8: =SUM(E8:H8) -> 652.53348 | J8: =7%*I8 -> 45.677343 | K8: =I8-J8 -> 606.85613 | L8: SEM DESCONTO. IPTU (4/5). SEGURO (4/6). | M8: 10 | N8: 11
A9: BRENA E RAYANE | B9: 6 | C9: ='GERAL 2022'!G36/31*22 -> 482.58065 | D9: 0 | E9: =C9-D9 -> 482.58065 | F9: =25/31*22 -> 17.741935 | G9: =D58/31*22 -> 2.8235699 | H9: 19.91 | I9: =SUM(E9:H9) -> 523.05615 | J9: =7%*I9 -> 36.613931 | K9: =I9-J9 -> 486.44222 | L9: PROPORCIONAL DE 22 DIAS (10/10 A 31/10). IPTU (3/5). SEGURO (1/6). | M9: 10 | N9: 11
A10: ALEXANDER | B10: 7 | C10: ='GERAL 2022'!G9 -> 580 | D10: 0 | E10: =C10-D10 -> 580 | F10: 50 | G10: =D60 -> 2.8368085 | H10: =D59 -> 19.696667 | I10: =SUM(E10:H10) -> 652.53348 | J10: =7%*I10 -> 45.677343 | K10: =I10-J10 -> 606.85613 | L10: SEM DESCONTO. IPTU (4/5). SEGURO (4/6). | M10: 10 | N10: 11
A11: HERBERT | B11: 8 | C11: ='GERAL 2022'!G37 -> 580 | D11: 0 | E11: =C11-D11 -> 580 | F11: 50 | G11: =D62 -> 2.8368085 | H11: =D61 -> 19.696667 | I11: =SUM(E11:H11) -> 652.53348 | J11: =7%*I11 -> 45.677343 | K11: =I11-J11 -> 606.85613 | L11: SEM DESCONTO. IPTU (3/5). SEGURO (3/6). | M11: 10 | N11: 11
A12: ALCIDES / RENÊ | B12: 9 | C12: ='GERAL 2022'!G11 -> 580 | D12: 0 | E12: =C12-D12 -> 580 | F12: =25 -> 25 | G12: 0 | H12: 0 | I12: =SUM(E12:H12) -> 605 | J12: =7%*I12 -> 42.35 | K12: =I12-J12 -> 562.65 | L12: SEM DESCONTO. IPTU QUITADO. SEGURO QUITADO. | M12: 10 | N12: 11
A13: JAÍNE | B13: 10 | C13: ='GERAL 2022'!G38 -> 550 | D13: 0 | E13: =C13-D13 -> 550 | F13: 50 | G13: =D66 -> 2.8368085 | H13: =D65 -> 19.641667 | I13: =SUM(E13:H13) -> 622.47848 | J13: =7%*I13 -> 43.573493 | K13: =I13-J13 -> 578.90498 | L13: SEM DESCONTO. IPTU (5/5). SEGURO (5/6). | M13: 10 | N13: 11
A14: JOCÉLIO | B14: 11 | C14: ='GERAL 2022'!G13 -> 550 | D14: 0 | E14: =C14-D14 -> 550 | F14: 0 | G14: 0 | H14: 0 | I14: =SUM(E14:H14) -> 550 | J14: =7%*I14 -> 38.5 | K14: =I14-J14 -> 511.5 | L14: SEM DESCONTO. IPTU QUITADO. SEGURO QUITADO. | M14: 10 | N14: 11
A15: DAVID/FÁTIMA MONTE | B15: 12 | C15: ='GERAL 2022'!G14 -> 550 | D15: 0 | E15: =C15-D15 -> 550 | F15: 25 | G15: =D70 -> 2.8368085 | H15: 19.64 | I15: =SUM(E15:H15) -> 597.47681 | J15: =7%*I15 -> 41.823377 | K15: =I15-J15 -> 555.65343 | L15: SEM DESCONTO. IPTU (5/5). SEGURO (5/6). | M15: 10 | N15: 11
A16: MARLON | B16: 13 | C16: ='GERAL 2022'!G15 -> 550 | D16: 0 | E16: =C16-D16 -> 550 | F16: 0 | G16: 0 | H16: =D71 -> 19.641667 | I16: =SUM(E16:H16) -> 569.64167 | J16: =7%*I16 -> 39.874917 | K16: =I16-J16 -> 529.76675 | L16: SEM DESCONTO. IPTU QUITADO. SEGURO (6/6). | M16: 10 | N16: 11
A17: HOSANA | B17: 14 | C17: ='GERAL 2022'!G16/31*15 -> 266.12903 | D17: 0 | E17: =C17-D17 -> 266.12903 | F17: 0 | G17: 0 | H17: 0 | I17: =SUM(E17:H17) -> 266.12903 | J17: =7%*I17 -> 18.629032 | K17: =I17-J17 -> 247.5 | L17: RESCISÃO. PROPORCIONAL DE 15 DIAS (01/10 A 15/10). SEM DESCONTO. IPTU QUITADO. SEGURO QUITADO. | M17: 10 | N17: 11
A18: DEIVID | B18: 14 | C18: ='GERAL 2022'!G39/31*5 -> 93.548387 | D18: 0 | E18: =C18-D18 -> 93.548387 | F18: =50/31*5 -> 8.0645161 | G18: =D76/31*5 -> 0.45754976 | H18: =D75 -> 19.696667 | I18: =SUM(E18:H18) -> 121.76712 | J18: =7%*I18 -> 8.5236984 | K18: =I18-J18 -> 113.24342 | L18: PROPORCIONAL DE 05 DIAS (27/10 A 31/10). IPTU (3/5). SEGURO (1/6). | M18: 10 | N18: 11
A19: BIANCA | B19: 15 | C19: ='GERAL 2022'!G40 -> 650 | D19: 0 | E19: =C19-D19 -> 650 | F19: 25 | G19: 0 | H19: 0 | I19: =SUM(E19:H19) -> 675 | J19: =7%*I19 -> 47.25 | K19: =I19-J19 -> 627.75 | L19: SEM DESCONTO. IPTU QUITADO. SEGURO QUITADO. | M19: 10 | N19: 11
A20: VANESSA | B20: 16 | C20: ='GERAL 2022'!G18+(10.72339%*640) -> 708.6297 | E20: =C20-D20 -> 708.6297 | F20: =60 -> 60 | G20: 0 | H20: 19.82 | I20: =SUM(E20:H20) -> 788.4497 | J20: =7%*I20 -> 55.191479 | K20: =I20-J20 -> 733.25822 | L20: REAJUSTADO EM JUNHO/2022. IPTU QUITADO. SEGURO (5/6). | M20: 10 | N20: 11
A21: IRAN | B21: 17 | C21: ='GERAL 2022'!G41 -> 580 | D21: 0 | E21: =C21-D21 -> 580 | F21: 0 | G21: =D82 -> 2.8368085 | H21: =D81 -> 19.696667 | I21: =SUM(E21:H21) -> 602.53348 | J21: =7%*I21 -> 42.177343 | K21: =I21-J21 -> 560.35613 | L21: SEM DESCONTO. IPTU (5/5). SEGURO (5/6). | M21: 10 | N21: 11
A22: FREDSON | B22: 18 | C22: ='GERAL 2022'!G20+(10.72339%*650) -> 719.70204 | D22: 0 | E22: =C22-D22 -> 719.70204 | F22: =30 -> 30 | H22: =D83 -> 19.836667 | I22: =SUM(E22:H22) -> 769.5387 | J22: =7%*I22 -> 53.867709 | K22: =I22-J22 -> 715.67099 | L22: REAJUSTADO EM JUNHO/2022. IPTU QUITADO. SEGURO (5/6). | M22: 10 | N22: 11
A23: SAMUEL | B23: 19 | C23: ='GERAL 2022'!G43 -> 550 | D23: 0 | E23: =(C23-D23) -> 550 | F23: 50 | G23: =D86 -> 2.8368085 | H23: =D85 -> 19.641667 | I23: =SUM(E23:H23) -> 622.47848 | J23: =7%*I23 -> 43.573493 | K23: =I23-J23 -> 578.90498 | L23: SEM DESCONTO. IPTU (3/5). SEGURO (3/6). | M23: 10 | N23: 11
A24: RENAN | B24: 20 | C24: ='GERAL 2022'!G22 -> 660 | D24: 0 | E24: =C24-D24 -> 660 | F24: 50 | G24: 0 | H24: =D87 -> 19.853333 | I24: =SUM(E24:H24) -> 729.85333 | J24: =7%*I24 -> 51.089733 | K24: =I24-J24 -> 678.7636 | L24: SEM DESCONTO. IPTU QUITADO. SEGURO (6/6). | M24: 10 | N24: 11
A25: KELSON | B25: 21 | C25: ='GERAL 2022'!G23 -> 500 | D25: 0 | E25: =C25-D25 -> 500 | F25: 25 | G25: 0 | H25: =D89 -> 19.543333 | I25: =SUM(E25:H25) -> 544.54333 | J25: =7%*I25 -> 38.118033 | K25: =I25-J25 -> 506.4253 | L25: SEM DESCONTO. IPTU QUITADO. SEGURO (6/6). | M25: 10 | N25: 11
A26: MATEUS | B26: 22 | C26: ='GERAL 2022'!G24 -> 500 | D26: 0 | E26: =C26-D26 -> 500 | F26: 25 | G26: 0 | H26: =D91 -> 19.543333 | I26: =SUM(E26:H26) -> 544.54333 | J26: =7%*I26 -> 38.118033 | K26: =I26-J26 -> 506.4253 | L26: SEM DESCONTO. IPTU QUITADO. SEGURO (6/6). | M26: 10 | N26: 11
A27: CÍCERO ABEL | B27: 23 | C27: ='GERAL 2022'!G25 -> 550 | D27: 0 | E27: =C27-D27 -> 550 | F27: 0 | G27: 0 | H27: =D93 -> 19.641667 | I27: =SUM(E27:H27) -> 569.64167 | J27: =7%*I27 -> 39.874917 | K27: =I27-J27 -> 529.76675 | L27: SEM DESCONTO. IPTU QUITADO. SEGURO (6/6). | M27: 10 | N27: 11
A28: JOÃO LEVI | B28: 24 | C28: ='GERAL 2022'!G26 -> 650 | D28: 0 | E28: =C28-D28 -> 650 | F28: 50 | G28: 0 | H28: 0 | I28: =SUM(E28:H28) -> 700 | J28: =7%*I28 -> 49 | K28: =I28-J28 -> 651 | L28: SEM DESCONTO. IPTU QUITADO. SEGURO QUITADO. | M28: 10 | N28: 11
A29: JEAN E FCO EDUARDO | B29: 25 | C29: ='GERAL 2022'!G44/31*13 -> 255.80645 | D29: 0 | E29: =C29-D29 -> 255.80645 | F29: 0 | G29: =D98/31*13 -> 1.1896294 | H29: 19.78 | I29: =SUM(E29:H29) -> 276.77608 | J29: =7%*I29 -> 19.374326 | K29: =I29-J29 -> 257.40176 | L29: PROPORCIONAL DE 13 DIAS (19/10 A 31/10). IPTU (3/5). SEGURO (1/6). | M29: 10 | N29: 11
A30: HENRIQUE | B30: 26 | C30: ='GERAL 2022'!G28 -> 560 | D30: 0 | E30: =C30-D30 -> 560 | F30: 25 | G30: 0 | H30: =D99 -> 19.658333 | I30: =SUM(E30:H30) -> 604.65833 | J30: =7%*I30 -> 42.326083 | K30: =I30-J30 -> 562.33225 | L30: SEM DESCONTO. IPTU QUITADO. SEGURO (6/6). | M30: 10 | N30: 11
A31: FABIANA | B31: 27 | C31: ='GERAL 2022'!G45 -> 580 | D31: 0 | E31: =C31-D31 -> 580 | F31: 0 | G31: 0 | H31: =D101 -> 19.696667 | I31: =SUM(E31:H31) -> 599.69667 | J31: =7%*I31 -> 41.978767 | K31: =I31-J31 -> 557.7179 | L31: SEM DESCONTO. IPTU QUITADO. SEGURO (6/6). | M31: 10 | N31: 11
A32: TOTAL | C32: =SUM(C4:C31) -> 15086.396 | D32: =SUM(D4:D31) -> 0 | E32: =SUM(E4:E31) -> 15086.396 | F32: =SUM(F4:F31) -> 765.80645 | G32: =SUM(G4:G31) -> 32.838834 | H32: =SUM(H4:H31) -> 433.36667 | I32: =SUM(I4:I31) -> 16318.408 | J32: =SUM(J4:J31) -> 1142.2886 | K32: =SUM(K4:K31) -> 15176.12
A34: ACORDOS/RESCISÕES RECEBIDAS EM OUTUBRO DE 2022
A35: NOME | B35: APTO | C35: PRINCIPAL | D35: CONDIÇÃO | I35: TOTAL | J35: COMISSÃO | K35: REPASSE | L35: OBSERVAÇÃO | M35: VENC. | N35: CARÊNCIA
A36: HOSANA | B36: 14 | C36: 1265 | D36: 01 PARCELA DE R$ 1.265,00 | I36: 1265 | J36: =7%*I36 -> 88.55 | K36: =I36-J36 -> 1176.45 | L36: MULTA POR RESCISÃO ANTES DO PRAZO. PAGAMENTO DIA 15/10/2022. | M36: 10 | N36: 11
A37: DAVID ÂNGELO | B37: 5 | C37: 722.03 | D37: R$ 580,00 (ALUGUEL) + R$ 50,00 (GARAGEM CARRO) + R$ 2,84 (IPTU) + R$ 19,70 (SEGURO) + R$ 69,49 (ENCARGOS PELO ATRASO) = R$ 722,03 | I37: =580+50+2.84+19.7+69.49 -> 722.03 | J37: =7%*I37 -> 50.5421 | K37: =I37-J37 -> 671.4879 | L37: ALUGUEL E ENCARGOS DE SETEMBRO. SEM DESCONTO. IPTU (3/5). SEGURO (3/6). PAGAMENTO DIA 28/10/2022. | M37: 10 | N37: 11
A38: TOTAL | I38: =SUM(I36:I37) -> 1987.03 | J38: =SUM(J36:J37) -> 139.0921 | K38: =SUM(K36:K37) -> 1847.9379
A40: INADIMPLÊNCIAS
A41: NOME | B41: APTO | C41: PRINCIPAL | D41: CONDIÇÃO | I41: TOTAL | L41: OBSERVAÇÃO | M41: VENC. | N41: CARÊNCIA
A42: JOÃO PAULO | B42: 1 | C42: =4977.59-1520 -> 3457.59 | D42: R$ 4.977,59 (DÉBITO TOTAL) - R$ 1.520,00 (CAUÇÃO) | I42: =4977.59-1520 -> 3457.59 | L42: DÉBITO ATUALIZADO EM 19/02/2022 (OUT/21 A FEV/22 E MULTA). | M42: 10 | N42: 11
A43: SHIRLEY | B43: 25 | C43: 3013.33 | D43: MÊS DE JULHO ATUALIZADO, AGOSTO, MULTA POR RESCISÃO ANTES DO PRAZO E REPAROS | I43: 3040.58 | L43: REFERENTE A JULHO, AGOSTO, MULTA POR RESCISÃO ANTES DO PRAZO E REPAROS. | M43: 10 | N43: 11
A44: TOTAL | I44: =SUM(I42:I43) -> 6498.17
A46: OBSERVAÇÕES | L46: COMISSÕES
A47: SEGURO 01 | B47: ='GERAL 2022'!J35 -> 118.18 | C47: 6 | D47: =B47/C47 -> 19.696667 | L47: COMISSÃO 7% | N47: =J32+J38 -> 1281.3807
A48: IPTU 01 | B48: ='GERAL 2022'!H35 -> 14.184043 | C48: 5 | D48: =B48/C48 -> 2.8368085 | L48: INTERMEDIAÇÃO 60%
A49: SEGURO 02 | B49: ='GERAL 2022'!J4 -> 118.18 | C49: 6 | D49: =B49/C49 -> 19.696667
A50: IPTU 02 | B50: ='GERAL 2022'!H4 -> 14.184043 | C50: 5 | D50: =B50/C50 -> 2.8368085
A51: SEGURO 03 | B51: ='GERAL 2022'!J5 -> 117.85 | C51: 6 | D51: =B51/C51 -> 19.641667 | L51: OUTRAS COMISSÕES E DESPESAS
A52: IPTU 03 | B52: ='GERAL 2022'!H5 -> 14.184043 | C52: 5 | D52: =B52/C52 -> 2.8368085 | L52: SEGURO APTO 01 (5/6) | N52: 19.7
A53: SEGURO 04 | B53: ='GERAL 2022'!J6 -> 117.85 | C53: 6 | D53: =B53/C53 -> 19.641667 | L53: SEGURO APTO 02 (4/6) | N53: 19.7
A54: IPTU 04 | B54: ='GERAL 2022'!H6 -> 14.184043 | C54: 5 | D54: =B54/C54 -> 2.8368085 | L54: SEGURO APTO 03 (4/6) | N54: 19.64
A55: SEGURO 05 | B55: ='GERAL 2022'!J7 -> 118.18 | C55: 6 | D55: =B55/C55 -> 19.696667 | L55: SEGURO APTO 05 (4/6) | N55: 19.7
A56: IPTU 05 | B56: ='GERAL 2022'!H7 -> 14.184043 | C56: 5 | D56: =B56/C56 -> 2.8368085 | L56: SEGURO APTO 06 (1/6) | N56: 19.91
A57: SEGURO 06 | B57: ='GERAL 2022'!J36 -> 119.36 | C57: 6 | D57: =B57/C57 -> 19.893333 | L57: SEGURO APTO 07 (4/6) | N57: 19.7
A58: IPTU 06 | B58: ='GERAL 2022'!K36 -> 19.893333 | C58: 5 | D58: =B58/C58 -> 3.9786667 | L58: SEGURO APTO 08 (3/6) | N58: 19.7
A59: SEGURO 07 | B59: ='GERAL 2022'!J9 -> 118.18 | C59: 6 | D59: =B59/C59 -> 19.696667 | L59: SEGURO APTO 10 (5/6) | N59: 19.64
A60: IPTU 07 | B60: ='GERAL 2022'!H9 -> 14.184043 | C60: 5 | D60: =B60/C60 -> 2.8368085 | L60: SEGURO APTO 12 (4/6) | N60: 19.64
A61: SEGURO 08 | B61: ='GERAL 2022'!J37 -> 118.18 | C61: 6 | D61: =B61/C61 -> 19.696667 | L61: SEGURO APTO 13 (6/6) | N61: 19.64
A62: IPTU 08 | B62: ='GERAL 2022'!H37 -> 14.184043 | C62: 5 | D62: =B62/C62 -> 2.8368085 | L62: SEGURO APTO 14 (1/6) | N62: 19.68
A63: SEGURO 09 | B63: ='GERAL 2022'!J11 -> 118.18 | C63: 6 | D63: =B63/C63 -> 19.696667 | L63: SEGURO APTO 16 (5/6) | N63: 19.81
A64: IPTU 09 | B64: ='GERAL 2022'!H11 -> 14.184043 | C64: 5 | D64: =B64/C64 -> 2.8368085 | L64: SEGURO APTO 17 (5/6) | N64: 19.7
A65: SEGURO 10 | B65: ='GERAL 2022'!J38 -> 117.85 | C65: 6 | D65: =B65/C65 -> 19.641667 | L65: SEGURO APTO 18 (5/6) | N65: 19.84
A66: IPTU 10 | B66: ='GERAL 2022'!H38 -> 14.184043 | C66: 5 | D66: =B66/C66 -> 2.8368085 | L66: SEGURO APTO 19 (3/6) | N66: 19.64
A67: SEGURO 11 | B67: ='GERAL 2022'!J13 -> 117.85 | C67: 6 | D67: =B67/C67 -> 19.641667 | L67: SEGURO APTO 20 (6/6) | N67: 19.85
A68: IPTU 11 | B68: ='GERAL 2022'!H13 -> 14.184043 | C68: 5 | D68: =B68/C68 -> 2.8368085 | L68: SEGURO APTO 21 (6/6) | N68: 19.54
A69: SEGURO 12 | B69: ='GERAL 2022'!J14 -> 117.85 | C69: 6 | D69: =B69/C69 -> 19.641667 | L69: SEGURO APTO 22 (6/6) | N69: 19.54
A70: IPTU 12 | B70: ='GERAL 2022'!H14 -> 14.184043 | C70: 5 | D70: =B70/C70 -> 2.8368085 | L70: SEGURO APTO 23 (6/6) | N70: 19.64
A71: SEGURO 13 | B71: ='GERAL 2022'!J15 -> 117.85 | C71: 6 | D71: =B71/C71 -> 19.641667 | L71: SEGURO APTO 25 (1/6) | N71: 19.78
A72: IPTU 13 | B72: ='GERAL 2022'!H15 -> 14.184043 | C72: 5 | D72: =B72/C72 -> 2.8368085 | L72: SEGURO APTO 26 (6/6) | N72: 19.66
A73: SEGURO 14 | B73: ='GERAL 2022'!J16 -> 117.85 | C73: 6 | D73: =B73/C73 -> 19.641667 | L73: SEGURO APTO 27 (6/6) | N73: 19.7
A74: IPTU 14 | B74: ='GERAL 2022'!H16 -> 14.184043 | C74: 5 | D74: =B74/C74 -> 2.8368085 | L74: 05 LIMPEZAS (01/10/2022 - 08/10/2022 - 15/10/2022 - 22/10/2022 - 29/10/2022) | N74: =120*5 -> 600
A75: SEGURO 14 NOVO | B75: ='GERAL 2022'!J39 -> 118.18 | C75: 6 | D75: =B75/C75 -> 19.696667 | L75: ENEL | N75: 128.17
A76: IPTU 14 NOVO | B76: ='GERAL 2022'!H39 -> 14.184043 | C76: 5 | D76: =B76/C76 -> 2.8368085 | L76: CAGECE SEM FATURA
A77: SEGURO 15 | B77: ='GERAL 2022'!J40 -> 119.02 | C77: 6 | D77: =B77/C77 -> 19.836667
A78: IPTU 15 | B78: ='GERAL 2022'!H40 -> 19.85766 | C78: 5 | D78: =B78/C78 -> 3.9715319
A79: SEGURO 16 | B79: ='GERAL 2022'!J18 -> 118.87 | C79: 6 | D79: =B79/C79 -> 19.811667
A80: IPTU 16 | B80: ='GERAL 2022'!H18 -> 14.184043 | C80: 5 | D80: =B80/C80 -> 2.8368085
A81: SEGURO 17 | B81: ='GERAL 2022'!J41 -> 118.18 | C81: 6 | D81: =B81/C81 -> 19.696667
A82: IPTU 17 | B82: ='GERAL 2022'!H41 -> 14.184043 | C82: 5 | D82: =B82/C82 -> 2.8368085 | L82: TOTAL COMISSÃO + DESPESAS | N82: =SUM(N47:N81) -> 2442.9007
A83: SEGURO 18 | B83: ='GERAL 2022'!J20 -> 119.02 | C83: 6 | D83: =B83/C83 -> 19.836667
A84: IPTU 18 | B84: ='GERAL 2022'!H20 -> 14.184043 | C84: 5 | D84: =B84/C84 -> 2.8368085 | L84: R$ RECEBIDOS EM NOME DO LOCADOR | N84: =I32+I38 -> 18305.438
A85: SEGURO 19 | B85: ='GERAL 2022'!J43 -> 117.85 | C85: 6 | D85: =B85/C85 -> 19.641667
A86: IPTU 19 | B86: ='GERAL 2022'!H43 -> 14.184043 | C86: 5 | D86: =B86/C86 -> 2.8368085 | L86: TOTAL A REPASSAR | N86: =N84-N82 -> 15862.538
A87: SEGURO 20 | B87: ='GERAL 2022'!J22 -> 119.12 | C87: 6 | D87: =B87/C87 -> 19.853333
A88: IPTU 20 | B88: ='GERAL 2022'!H22 -> 14.184043 | C88: 5 | D88: =B88/C88 -> 2.8368085
A89: SEGURO 21 | B89: ='GERAL 2022'!J23 -> 117.26 | C89: 6 | D89: =B89/C89 -> 19.543333
A90: IPTU 21 | B90: ='GERAL 2022'!H23 -> 14.184043 | C90: 5 | D90: =B90/C90 -> 2.8368085
A91: SEGURO 22 | B91: ='GERAL 2022'!J24 -> 117.26 | C91: 6 | D91: =B91/C91 -> 19.543333
A92: IPTU 22 | B92: ='GERAL 2022'!H24 -> 14.184043 | C92: 5 | D92: =B92/C92 -> 2.8368085
A93: SEGURO 23 | B93: ='GERAL 2022'!J25 -> 117.85 | C93: 6 | D93: =B93/C93 -> 19.641667
A94: IPTU 23 | B94: ='GERAL 2022'!H25 -> 14.184043 | C94: 5 | D94: =B94/C94 -> 2.8368085
A95: SEGURO 24 | B95: ='GERAL 2022'!J26 -> 119.02 | C95: 6 | D95: =B95/C95 -> 19.836667
A96: IPTU 24 | B96: ='GERAL 2022'!H26 -> 19.85766 | C96: 5 | D96: =B96/C96 -> 3.9715319
A97: SEGURO 25 | B97: ='GERAL 2022'!J44 -> 118.53 | C97: 6 | D97: =B97/C97 -> 19.755
A98: IPTU 25 | B98: ='GERAL 2022'!H44 -> 14.184043 | C98: 5 | D98: =B98/C98 -> 2.8368085
A99: SEGURO 26 | B99: ='GERAL 2022'!J28 -> 117.95 | C99: 6 | D99: =B99/C99 -> 19.658333
A100: IPTU 26 | B100: ='GERAL 2022'!H28 -> 14.184043 | C100: 5 | D100: =B100/C100 -> 2.8368085
A101: SEGURO 27 | B101: ='GERAL 2022'!J45 -> 118.18 | C101: 6 | D101: =B101/C101 -> 19.696667
A102: IPTU 27 | B102: ='GERAL 2022'!H45 -> 14.184043 | C102: 5 | D102: =B102/C102 -> 2.8368085

Sheet VIGÊNCIA NOVEMBRO 2022
A1: GRAND MESSEJANA II
A2: INTERMEDIAÇÕES DE OUTUBRO DE 2022
A3: NOME | B3: APTO | C3: ALUGUEL | D3: DESCONTO | E3: ALUGUEL C/ DESCONTO | F3: GARAGEM | G3: ÁGUA | H3: IPTU | I3: SEG INC. | J3: TOTAL | K3: COMISSÃO | L3: REPASSE | M3: OBSERVAÇÃO | N3: VENC. | O3: CARÊNCIA
A4: BRENA E RAYANE | B4: 6 | C4: ='GERAL 2022'!G36 -> 680 | D4: 0 | E4: =C4-D4 -> 680 | F4: =25 -> 25 | G4: =1639.44/27 -> 60.72 | H4: =D63 -> 3.9786667 | I4: =D62 -> 19.893333 | J4: =SUM(E4:I4) -> 789.592 | K4: =60%*(C4+F4) -> 423 | L4: =J4-K4 -> 366.592 | M4: IPTU (4/5). SEGURO (2/6). | N4: 10 | O4: 11
A5: DEIVID | B5: 14 | C5: ='GERAL 2022'!G39 -> 580 | D5: 0 | E5: =C5-D5 -> 580 | F5: =50 -> 50 | G5: =1639.44/27 -> 60.72 | H5: =D81 -> 2.8368085 | I5: =D80 -> 19.696667 | J5: =SUM(E5:I5) -> 713.25348 | K5: =60%*(C5+F5) -> 378 | L5: =J5-K5 -> 335.25348 | M5: IPTU (4/5). SEGURO (2/6). | N5: 10 | O5: 11
A6: JEAN E FCO EDUARDO | B6: 25 | C6: ='GERAL 2022'!G44 -> 610 | D6: 0 | E6: =C6-D6 -> 610 | F6: 0 | G6: =1639.44/27 -> 60.72 | H6: =D103 -> 2.8368085 | I6: =D102 -> 19.755 | J6: =SUM(E6:I6) -> 693.31181 | K6: =60%*(C6+F6) -> 366 | L6: =J6-K6 -> 327.31181 | M6: IPTU (4/5). SEGURO (2/6). | N6: 10 | O6: 11
A7: TOTAL | C7: =SUM(C4:C6) -> 1870 | D7: =SUM(D4:D6) -> 0 | E7: =SUM(E4:E6) -> 1870 | F7: =SUM(F4:F6) -> 75 | G7: =SUM(G4:G6) -> 182.16 | H7: =SUM(H4:H6) -> 9.6522837 | I7: =SUM(I4:I6) -> 59.345 | J7: =SUM(J4:J6) -> 2196.1573 | ... L7: =SUM(L4:L6) -> 1029.1573
A8: VIGÊNCIA DE NOVEMBRO 2022
A9: NOME | B9: APTO | C9: ALUGUEL | D9: DESCONTO | E9: ALUGUEL C/ DESCONTO | F9: GARAGEM | G9: ÁGUA | H9: IPTU | I9: SEG INC. | J9: TOTAL | K9: COMISSÃO | L9: REPASSE | M9: OBSERVAÇÃO | N9: VENC. | O9: CARÊNCIA
A10: ELISON | B10: 1 | C10: ='GERAL 2022'!G35 -> 580 | D10: 0 | E10: =C10-D10 -> 580 | F10: 50 | G10: =1639.44/27 -> 60.72 | H10: 0 | I10: =D52 -> 19.696667 | J10: =SUM(E10:I10) -> 710.41667 | K10: =7%*J10 -> 49.729167 | L10: =J10-K10 -> 660.6875 | M10: SEM DESCONTO. IPTU QUITADO. SEGURO (6/6). | N10: 10 | O10: 11
A11: FÁTIMA E RAFAELA | B11: 2 | C11: ='GERAL 2022'!G4 -> 580 | D11: 0 | E11: =C11-D11 -> 580 | F11: 50 | G11: =1639.44/27 -> 60.72 | H11: =D55 -> 2.8368085 | I11: =D54 -> 19.696667 | J11: =SUM(E11:I11) -> 713.25348 | K11: =7%*J11 -> 49.927743 | L11: =J11-K11 -> 663.32573 | M11: SEM DESCONTO. IPTU (5/5). SEGURO (5/6). | N11: 10 | O11: 11
A12: LETICIA | B12: 3 | C12: ='GERAL 2022'!G5 -> 550 | D12: 0 | E12: =C12-D12 -> 550 | F12: 0 | G12: =1639.44/27 -> 60.72 | H12: =D57 -> 2.8368085 | I12: =D56 -> 19.641667 | J12: =SUM(E12:I12) -> 633.19848 | K12: =7%*J12 -> 44.323893 | L12: =J12-K12 -> 588.87458 | M12: SEM DESCONTO. IPTU (5/5). SEGURO (5/6). | N12: 10 | O12: 11
A13: AMANDA | B13: 4 | C13: ='GERAL 2022'!G16 -> 550 | D13: 0 | E13: =C13-D13 -> 550 | F13: 50 | G13: =1639.44/27 -> 60.72 | H13: 0 | I13: 0 | J13: =SUM(E13:I13) -> 660.72 | K13: =7%*J13 -> 46.2504 | L13: =J13-K13 -> 614.4696 | M13: SEM DESCONTO. IPTU QUITADO. SEGURO QUITADO. | N13: 10 | O13: 11
A14: DAVID ÂNGELO | B14: 5 | C14: ='GERAL 2022'!G7/30*1 -> 19.333333 | D14: 0 | E14: =C14-D14 -> 19.333333 | F14: =50/30*1 -> 1.6666667 | G14: =(1639.44/27)/30*1 -> 2.024 | H14: =D61/30*1 -> 0.094560284 | I14: =D60 -> 19.696667 | J14: =SUM(E14:I14) -> 42.815227 | K14: =7%*J14 -> 2.9970659 | L14: =J14-K14 -> 39.818161 | M14: RESCISÃO. PROPORCIONAL DE 01 DIA (01/11/2022).SEM DESCONTO. IPTU (5/5). SEGURO (5/6). | N14: 10 | O14: 11
A15: BRENA E RAYANE | B15: 6 | C15: 0 | D15: 0 | E15: =C15-D15 -> 0 | F15: 0 | G15: 0 | H15: 0 | I15: 0 | J15: =SUM(E15:I15) -> 0 | K15: =7%*J15 -> 0 | L15: =J15-K15 -> 0 | M15: INTERMEDIAÇÃO | N15: 10 | O15: 11
A16: ALEXANDER | B16: 7 | C16: ='GERAL 2022'!G9 -> 580 | D16: 0 | E16: =C16-D16 -> 580 | F16: 50 | G16: =1639.44/27 -> 60.72 | H16: =D65 -> 2.8368085 | I16: =D64 -> 19.696667 | J16: =SUM(E16:I16) -> 713.25348 | K16: =7%*J16 -> 49.927743 | L16: =J16-K16 -> 663.32573 | M16: SEM DESCONTO. IPTU (5/5). SEGURO (5/6). | N16: 10 | O16: 11
A17: HERBERT | B17: 8 | C17: ='GERAL 2022'!G37 -> 580 | D17: 0 | E17: =C17-D17 -> 580 | F17: 50 | G17: =1639.44/27 -> 60.72 | H17: =D67 -> 2.8368085 | I17: =D66 -> 19.696667 | J17: =SUM(E17:I17) -> 713.25348 | K17: =7%*J17 -> 49.927743 | L17: =J17-K17 -> 663.32573 | M17: SEM DESCONTO. IPTU (4/5). SEGURO (4/6). | N17: 10 | O17: 11
A18: ALCIDES / RENÊ | B18: 9 | C18: ='GERAL 2022'!G11 -> 580 | D18: 0 | E18: =C18-D18 -> 580 | F18: =25 -> 25 | G18: =1639.44/27 -> 60.72 | H18: 0 | I18: 0 | J18: =SUM(E18:I18) -> 665.72 | K18: =7%*J18 -> 46.6004 | L18: =J18-K18 -> 619.1196 | M18: SEM DESCONTO. IPTU QUITADO. SEGURO QUITADO. | N18: 10 | O18: 11
A19: JAÍNE | B19: 10 | C19: ='GERAL 2022'!G38 -> 550 | D19: 0 | E19: =C19-D19 -> 550 | F19: 50 | G19: =1639.44/27 -> 60.72 | H19: 0 | I19: =D70 -> 19.641667 | J19: =SUM(E19:I19) -> 680.36167 | K19: =7%*J19 -> 47.625317 | L19: =J19-K19 -> 632.73635 | M19: SEM DESCONTO. IPTU QUITADO. SEGURO (6/6). | N19: 10 | O19: 11
A20: JOCÉLIO | B20: 11 | C20: ='GERAL 2022'!G13 -> 550 | D20: 0 | E20: =C20-D20 -> 550 | F20: 0 | G20: =1639.44/27 -> 60.72 | H20: 0 | I20: 0 | J20: =SUM(E20:I20) -> 610.72 | K20: =7%*J20 -> 42.7504 | L20: =J20-K20 -> 567.9696 | M20: SEM DESCONTO. IPTU QUITADO. SEGURO QUITADO. | N20: 10 | O20: 11
A21: DAVID/FÁTIMA MONTE | B21: 12 | C21: ='GERAL 2022'!G14 -> 550 | D21: 0 | E21: =C21-D21 -> 550 | F21: 25 | G21: =1639.44/27 -> 60.72 | H21: 0 | I21: 19.64 | J21: =SUM(E21:I21) -> 655.36 | K21: =7%*J21 -> 45.8752 | L21: =J21-K21 -> 609.4848 | M21: SEM DESCONTO. IPTU QUITADO. SEGURO (6/6). | N21: 10 | O21: 11
A22: MARLON | B22: 13 | C22: ='GERAL 2022'!G15 -> 550 | D22: 0 | E22: =C22-D22 -> 550 | F22: 0 | G22: =1639.44/27 -> 60.72 | H22: 0 | I22: 0 | J22: =SUM(E22:I22) -> 610.72 | K22: =7%*J22 -> 42.7504 | L22: =J22-K22 -> 567.9696 | M22: SEM DESCONTO. IPTU QUITADO. SEGURO QUITADO. | N22: 10 | O22: 11
A23: DEIVID | B23: 14 | C23: 0 | D23: 0 | E23: =C23-D23 -> 0 | F23: 0 | G23: 0 | H23: 0 | I23: 0 | J23: =SUM(E23:I23) -> 0 | K23: =7%*J23 -> 0 | L23: =J23-K23 -> 0 | M23: INTERMEDIAÇÃO | N23: 10 | O23: 11
A24: BIANCA | B24: 15 | C24: ='GERAL 2022'!G40 -> 650 | D24: 0 | E24: =C24-D24 -> 650 | F24: 25 | G24: =1639.44/27 -> 60.72 | H24: 0 | I24: 0 | J24: =SUM(E24:I24) -> 735.72 | K24: =7%*J24 -> 51.5004 | L24: =J24-K24 -> 684.2196 | M24: SEM DESCONTO. IPTU QUITADO. SEGURO QUITADO. | N24: 10 | O24: 11
A25: VANESSA | B25: 16 | C25: ='GERAL 2022'!G18+(10.72339%*640) -> 708.6297 | D25: 0 | E25: =C25-D25 -> 708.6297 | F25: =60 -> 60 | G25: =1639.44/27 -> 60.72 | H25: 0 | I25: 19.82 | J25: =SUM(E25:I25) -> 849.1697 | K25: =7%*J25 -> 59.441879 | L25: =J25-K25 -> 789.72782 | M25: REAJUSTADO EM JUNHO/2022. IPTU QUITADO. SEGURO (6/6). | N25: 10 | O25: 11
A26: IRAN | B26: 17 | C26: ='GERAL 2022'!G41 -> 580 | D26: 0 | E26: =C26-D26 -> 580 | F26: 0 | G26: =1639.44/27 -> 60.72 | H26: 0 | I26: =D86 -> 19.696667 | J26: =SUM(E26:I26) -> 660.41667 | K26: =7%*J26 -> 46.229167 | L26: =J26-K26 -> 614.1875 | M26: SEM DESCONTO. IPTU QUITADO. SEGURO (6/6). | N26: 10 | O26: 11
A27: FREDSON | B27: 18 | C27: =('GERAL 2022'!G20+(10.72339%*650))/30*10 -> 239.90068 | D27: 0 | E27: =C27-D27 -> 239.90068 | F27: =30/30*10 -> 10 | G27: =(1639.44/27)/30*10 -> 20.24 | H27: 0 | I27: =D88 -> 19.836667 | J27: =SUM(E27:I27) -> 289.97735 | K27: =7%*J27 -> 20.298414 | L27: =J27-K27 -> 269.67893 | M27: RESCISÃO. PROPORCINAL DE 10 DIAS (01/11/2022 A 10/11/2022). IPTU QUITADO. SEGURO (6/6). | N27: 10 | O27: 11
A28: SAMUEL | B28: 19 | C28: ='GERAL 2022'!G43 -> 550 | D28: 0 | E28: =(C28-D28) -> 550 | F28: 50 | G28: =1639.44/27 -> 60.72 | H28: =D91 -> 2.8368085 | I28: =D90 -> 19.641667 | J28: =SUM(E28:I28) -> 683.19848 | K28: =7%*J28 -> 47.823893 | L28: =J28-K28 -> 635.37458 | M28: SEM DESCONTO. IPTU (4/5). SEGURO (4/6). | N28: 10 | O28: 11
A29: RENAN | B29: 20 | C29: ='GERAL 2022'!G22 -> 660 | D29: 0 | E29: =C29-D29 -> 660 | F29: 50 | G29: =1639.44/27 -> 60.72 | H29: 0 | I29: 0 | J29: =SUM(E29:I29) -> 770.72 | K29: =7%*J29 -> 53.9504 | L29: =J29-K29 -> 716.7696 | M29: SEM DESCONTO. IPTU QUITADO. SEGURO QUITADO. | N29: 10 | O29: 11
A30: KELSON | B30: 21 | C30: ='GERAL 2022'!G23 -> 500 | D30: 0 | E30: =C30-D30 -> 500 | F30: 25 | G30: =1639.44/27 -> 60.72 | H30: 0 | I30: 0 | J30: =SUM(E30:I30) -> 585.72 | K30: =7%*J30 -> 41.0004 | L30: =J30-K30 -> 544.7196 | M30: SEM DESCONTO. IPTU QUITADO. SEGURO QUITADO. | N30: 10 | O30: 11
A31: MATEUS | B31: 22 | C31: ='GERAL 2022'!G24 -> 500 | D31: 0 | E31: =C31-D31 -> 500 | F31: 25 | G31: =1639.44/27 -> 60.72 | H31: 0 | I31: 0 | J31: =SUM(E31:I31) -> 585.72 | K31: =7%*J31 -> 41.0004 | L31: =J31-K31 -> 544.7196 | M31: SEM DESCONTO. IPTU QUITADO. SEGURO QUITADO. | N31: 10 | O31: 11
A32: CÍCERO ABEL | B32: 23 | C32: ='GERAL 2022'!G25 -> 550 | D32: 0 | E32: =C32-D32 -> 550 | F32: 0 | G32: =1639.44/27 -> 60.72 | H32: 0 | I32: 0 | J32: =SUM(E32:I32) -> 610.72 | K32: =7%*J32 -> 42.7504 | L32: =J32-K32 -> 567.9696 | M32: SEM DESCONTO. IPTU QUITADO. SEGURO QUITADO. | N32: 10 | O32: 11
A33: JOÃO LEVI | B33: 24 | C33: ='GERAL 2022'!G26 -> 650 | D33: 0 | E33: =C33-D33 -> 650 | F33: 50 | G33: =1639.44/27 -> 60.72 | H33: 0 | I33: 0 | J33: =SUM(E33:I33) -> 760.72 | K33: =7%*J33 -> 53.2504 | L33: =J33-K33 -> 707.4696 | M33: SEM DESCONTO. IPTU QUITADO. SEGURO QUITADO. | N33: 10 | O33: 11
